Workbook

Sheet Resumen Inventario
B1: DICIEMBRE . 2025
A2: Cliente / Bodega | B2: Valo inventario | C2: Cajas en inventario | D2: Costo promedio | E2: Venta de cajas del mes | G2: Llegadas | H2: Ventas estimadas | I2: Inv actual + llegadas | J2: Inv - ventas estimadas
A3: Abastos logicos
A4: CDMX: Arcosa | Fresco | Frigarsa | Canbelt
A5: Bajo Cero
A6: Frjalisco
A7: Alfrimex
A8: Vulpes
A9: Importe Total
B10: ENERO . 2026
A11: Cliente / Bodega | B11: Valo invent | C11: Cajas invent | D11: costo prom | E11: vta cajas mes | G11: Llegadas | H11: Ventas estimadas | I11: Inv actual + llegadas | J11: Inv - ventas estimadas
A12: Abastos logicos | B12: =+'$$$$$'!S22 -> 2232136.3 | C12: =+'$$$$$'!R22 -> 7406.75 | D12: =+B12/C12 -> 301.36514 | E12: =+CANCÚN!J26 -> 1803 | G12: 2268 | H12: 2000 | I12: =+G12+C12 -> 9674.75 | J12: =+I12-H12 -> 7674.75 | K12: =+J12/H12 -> 3.837375
A13: CDMX: Arcosa | Fresco | Frigarsa | Canbelt | B13: =+'$$$$$'!S46+'$$$$$'!S70+'$$$$$'!S94+'$$$$$'!S171 -> 1775097.1 | C13: =+'$$$$$'!T171+'$$$$$'!T94+'$$$$$'!T70+'$$$$$'!T46 -> 3774.6 | D13: =+B13/C13 -> 470.27424 | E13: =+'RESUMEN CDMX'!J26+FRIGARSA!G24+FRESCO!G25+CANBELT!L8 -> 1539.7 | G13: 2268 | H13: 1200 | I13: =+G13+C13 -> 6042.6 | J13: =+I13-H13 -> 4842.6 | K13: =+J13/H13 -> 4.0355
A14: Bajo Cero | B14: =+'$$$$$'!S139 -> 1544466.5 | C14: =+'$$$$$'!R139 -> 5539.16 | D14: =+B14/C14 -> 278.82685 | E14: =+'VULPES PAPAS'!G35 -> 2324.58 | H14: 3200 | I14: =+G14+C14 -> 5539.16 | J14: =+I14-H14 -> 2339.16 | K14: =+J14/H14 -> 0.7309875
A15: Frjalisco | B15: =+'$$$$$'!S112 -> 449970.4 | C15: =+'$$$$$'!R112 -> 1372 | D15: =+B15/C15 -> 327.96676 | E15: =+FRIJALISCO!J28 -> 2613 | H15: 2200 | I15: =+G15+C15 -> 1372 | J15: =+I15-H15 -> -828 | K15: =+J15/H15 -> -0.37636364
A16: Alfrimex | B16: =+'$$$$$'!S175 -> 94930.96 | C16: =+'$$$$$'!R174 -> 356 | D16: =+B16/C16 -> 266.66 | E16: =+ALFRIMEX!H8 -> 158 | H16: 50 | I16: =+G16+C16 -> 356 | J16: =+I16-H16 -> 306 | K16: =+J16/H16 -> 6.12
A17: Vulpes | B17: =+'$$$$$'!S167 -> 307923.39 | C17: =+'$$$$$'!R167 -> 980.84 | D17: =+B17/C17 -> 313.93845 | E17: 0 | I17: =+G17+C17 -> 980.84 | J17: =+I17-H17 -> 980.84
A18: Importe Total | B18: =+SUM(B12:B17) -> 6404524.7 | C18: =+SUM(C12:C17) -> 19429.35 | D18: =+AVERAGE(D12:D17) -> 326.50524 | E18: =+SUM(E12:E16) -> 8438.28 | G18: =+SUM(G12:G17) -> 4536 | H18: =+SUM(H12:H17) -> 8650 | J18: =+SUM(J12:J17) -> 15315.35 | K18: =+J18/H18 -> 1.7705607
B20: FEBRERO . 2026
A21: Cliente / Bodega | B21: Valo invent | C21: Cajas invent | D21: costo prom | E21: vta cajas mes | G21: Llegadas | H21: Ventas estimadas | I21: Inv actual + llegadas | J21: Inv - ventas estimadas
A22: Abastos logicos | B22: =+'$$$$$'!U22 -> 1713755.1 | C22: =+'$$$$$'!T22 -> 5630 | D22: =+B22/C22 -> 304.39699 | E22: =+CANCÚN!O26 -> 1776.75
A23: CDMX: Arcosa | Fresco | Frigarsa | Canbelt | B23: =+'$$$$$'!U198+'$$$$$'!U171+'$$$$$'!U94+'$$$$$'!U70+'$$$$$'!U46 -> 1961617.5 | C23: =+'$$$$$'!T46+'$$$$$'!T70+'$$$$$'!T94+'$$$$$'!T171+'$$$$$'!T198 -> 5822.6 | D23: =+B23/C23 -> 336.89718 | E23: =+'RESUMEN CDMX'!O26+FRIGARSA!L24+FRESCO!L25+MEXIDELI!L24+CANBELT!L8 -> 1420 | G23: 2198
A24: Bajo Cero | B24: =+'$$$$$'!U139 -> 1677356.5 | C24: =+'$$$$$'!T139 -> 6005.16 | D24: =+B24/C24 -> 279.31921 | E24: =+'VULPES PAPAS'!L35 -> 1353.18
A25: Frjalisco | B25: =+'$$$$$'!U112 -> 666908.8 | C25: =+'$$$$$'!T112 -> 2464 | D25: =+B25/C25 -> 270.66104 | E25: =+FRIJALISCO!O28 -> 1745
A26: Alfrimex | B26: =+'$$$$$'!U175 -> 11733.04 | C26: =+'$$$$$'!T175 -> 44 | D26: =+B26/C26 -> 266.66 | E26: 44
A27: Vulpes | B27: =+'$$$$$'!U167 -> 177402.69 | C27: =+'$$$$$'!T167 -> 641.32 | D27: =+B27/C27 -> 276.62118 | E27: 0
A28: Importe Total | B28: =SUM(B22:B27) -> 6208773.7 | C28: =SUM(C22:C27) -> 20607.08 | D28: =SUM(D22:D27) -> 1734.5556 | E28: =SUM(E22:E27) -> 6338.93
B30: MARZO . 2026
A31: Cliente / Bodega | B31: Valo invent | C31: Cajas invent | D31: costo prom | E31: vta cajas mes | G31: Llegadas | H31: Ventas estimadas | I31: Inv actual + llegadas | J31: Inv - ventas estimadas
A32: Abastos logicos | B32: =+'$$$$$'!W22 -> 911559.38 | C32: =+'$$$$$'!V22 -> 2875.25 | D32: =+B32/C32 -> 317.03656 | E32: =+CANCÚN!T26 -> 2764.75
A33: CDMX: Arcosa | Fresco | Frigarsa | Canbelt | B33: =+'$$$$$'!W46+'$$$$$'!W70+'$$$$$'!W94+'$$$$$'!W171+'$$$$$'!W198 -> 2359652.5 | C33: =+'$$$$$'!V46+'$$$$$'!V70+'$$$$$'!V94+'$$$$$'!V171+'$$$$$'!V198 -> 6974.8 | D33: =+B33/C33 -> 338.31113 | E33: =+'RESUMEN CDMX'!T26+FRIGARSA!Q24+FRESCO!Q25+MEXIDELI!Q24+CANBELT!Q8 -> 1722
A34: Bajo Cero | B34: =+'$$$$$'!W139 -> 1401514.9 | C34: =+'$$$$$'!V139 -> 4955.16 | D34: =+B34/C34 -> 282.83949 | E34: =+'VULPES PAPAS'!Q35 -> 1424.08
A35: Frjalisco | B35: =+'$$$$$'!W112 -> 1084783.8 | C35: =+'$$$$$'!V112 -> 3930 | D35: =+B35/C35 -> 276.02642 | E35: =+FRIJALISCO!T28 -> 2227
A36: Alfrimex | D36: =+B36/C36 -> #DIV/0!
A37: Vulpes | B37: =+'$$$$$'!W167 -> 649082.81 | C37: =+'$$$$$'!V167 -> 2433.07 | D37: =+B37/C37 -> 266.77523
A38: Importe Total | B38: =SUM(B32:B37) -> 6406593.4 | C38: =SUM(C32:C37) -> 21168.28 | E38: =SUM(E32:E37) -> 8137.83
B40: ABRIL . 2026
A41: Cliente / Bodega | B41: Valo invent | C41: Cajas invent | D41: costo prom | E41: vta cajas mes | G41: Llegadas | H41: Ventas estimadas | I41: Inv actual + llegadas | J41: Inv - ventas estimadas
A42: Abastos logicos | B42: =+'$$$$$'!Y22 -> 869367.52 | C42: =+'$$$$$'!X22 -> 3176.25 | D42: =+B42/C42 -> 273.70878 | E42: =+CANCÚN!Y26 -> 2058 | G42: =+CANCÚN!BX24+CANCÚN!BY24 -> 4644 | H42: =+CANCÚN!BR24 -> 2284.0625 | I42: =+G42+C42 -> 7820.25 | J42: =+I42-H42 -> 5536.1875 | K42: =+J42/H42 -> 2.4238336
A43: CDMX: Arcosa | Fresco | Frigarsa | Canbelt | B43: =+'$$$$$'!Y46+'$$$$$'!Y70+'$$$$$'!Y94+'$$$$$'!Y171+'$$$$$'!Y198 -> 2102810.1 | C43: =+'$$$$$'!X46+'$$$$$'!X70+'$$$$$'!X94+'$$$$$'!X171+'$$$$$'!X198 -> 6095.8 | D43: =+B43/C43 -> 344.96048 | E43: =+FRIGARSA!V24+FRESCO!BO25+MEXIDELI!V24+CANBELT!V8 -> 1756 | G43: =+'RESUMEN CDMX'!AI26 -> 1476 | H43: 1200 | I43: =+G43+C43 -> 7571.8 | J43: =+I43-H43 -> 6371.8 | K43: =+J43/H43 -> 5.3098333
A44: Bajo Cero | B44: =+'$$$$$'!Y139 -> 1376959.8 | C44: =+'$$$$$'!X139 -> 4971.16 | D44: =+B44/C44 -> 276.98964 | E44: =+'VULPES PAPAS'!V35 -> 2477.44 | G44: =+'RESUMEN LEÓN'!T17 -> 720 | H44: 1000 | I44: =+G44+C44+C45 -> 7625.79 | J44: =+I44-H44 -> 6625.79 | K44: =+J44/H44 -> 6.62579
A45: Vulpes | B45: =+'$$$$$'!Y167 -> 529960.35 | C45: =+'$$$$$'!X167 -> 1934.63 | D45: =+B45/C45 -> 273.9337 | G45: 0 | H45: 0 | I45: 0 | J45: 0
A46: Frjalisco | B46: =+'$$$$$'!Y112 -> 1231167.7 | C46: =+'$$$$$'!X112 -> 4584 | D46: =+B46/C46 -> 268.57935 | E46: =+FRIJALISCO!Y28 -> 3410 | G46: =+FRIJALISCO!AN14 -> 1185 | H46: 2800 | I46: =+G46+C46 -> 5769 | J46: =+I46-H46 -> 2969 | K46: =+J46/H46 -> 1.0603571
A47: Alfrimex | D47: =+B47/C47 -> #DIV/0! | I47: =+G47+C47 -> 0 | J47: =+I47-H47 -> 0 | K47: =+J47/H47 -> #DIV/0!
A48: Importe Total | B48: =SUM(B42:B47) -> 6110265.5 | C48: =SUM(C42:C47) -> 20761.84 | E48: =SUM(E42:E47) -> 9701.44 | G48: =SUM(G42:G47) -> 8025 | H48: =SUM(H42:H47) -> 7284.0625 | I48: =SUM(I42:I47) -> 28786.84 | J48: =SUM(J42:J47) -> 21502.778
E49: =+C48/E38 -> 2.5512747
B51: MAYO . 2026
A52: Cliente / Bodega | B52: Valo invent | C52: Cajas invent | D52: costo prom | E52: vta cajas mes | G52: Llegadas | H52: Ventas estimadas | I52: Inv actual + llegadas | J52: Inv - ventas estimadas
A53: Abastos logicos | B53: =+'$$$$$'!AA22 -> 743039.46 | C53: =+'$$$$$'!Z22 -> 2692 | D53: =+B53/C53 -> 276.01763 | E53: =+CANCÚN!AD26 -> 493.25 | G53: =+CANCÚN!BX24+CANCÚN!BY24 -> 4644 | H53: 2000 | I53: =+G53+C53 -> 7336 | J53: =+I53-H53 -> 5336 | K53: =+J53/H53 -> 2.668
A54: CDMX: Arcosa | Fresco | Frigarsa | Canbelt | B54: =+'$$$$$'!AA70+'$$$$$'!AA94+'$$$$$'!AA171+'$$$$$'!AA198 -> 2089695.2 | C54: =+'$$$$$'!Z198+'$$$$$'!Z171+'$$$$$'!Z94+'$$$$$'!Z70 -> 5625.8 | D54: =+B54/C54 -> 371.44855 | E54: =+'RESUMEN CDMX'!AC26 -> 411 | G54: =+'RESUMEN CDMX'!AI26+'RESUMEN CDMX'!AJ26 -> 3024 | H54: 1200 | I54: =+G54+C54 -> 8649.8 | J54: =+I54-H54 -> 7449.8 | K54: =+J54/H54 -> 6.2081667
A55: Bajo Cero | B55: =+'$$$$$'!AA139 -> 1358075.6 | C55: =+'$$$$$'!Z139 -> 4926.16 | D55: =+B55/C55 -> 275.68646 | E55: =+'VULPES PAPAS'!V46 -> 0 | G55: =+'RESUMEN LEÓN'!T32+'RESUMEN LEÓN'!T17+'RESUMEN LEÓN'!U17 -> 2622 | H55: 1000 | I55: =+G55+C55+C56 -> 8933.79 | J55: =+I55-H55 -> 7933.79 | K55: =+J55/H55 -> 7.93379
A56: Vulpes | B56: =+'$$$$$'!AA167 -> 396285.99 | C56: =+'$$$$$'!Z167 -> 1385.63 | D56: =+B56/C56 -> 285.99697 | E56: =+'RESUMEN LEÓN'!I37 -> 913 | G56: 0 | H56: 0 | I56: 0 | J56: 0
A57: Frjalisco | B57: =+'$$$$$'!AA112 -> 1993600 | C57: =+'$$$$$'!Z112 -> 7351 | D57: =+B57/C57 -> 271.20119 | E57: =+FRIJALISCO!AD28 -> 858 | G57: =+FRIJALISCO!AN14 -> 1185 | H57: 2800 | I57: =+G57+C57 -> 8536 | J57: =+I57-H57 -> 5736 | K57: =+J57/H57 -> 2.0485714
A58: Alfrimex | D58: =+B58/C58 -> #DIV/0! | I58: =+G58+C58 -> 0 | J58: =+I58-H58 -> 0 | K58: =+J58/H58 -> #DIV/0!
A59: Importe Total | B59: =SUM(B53:B58) -> 6580696.3 | C59: =SUM(C53:C58) -> 21980.59 | E59: =SUM(E53:E58) -> 2675.25 | G59: =SUM(G53:G58) -> 11475 | H59: =SUM(H53:H58) -> 7000 | I59: =SUM(I53:I58) -> 33455.59 | J59: =SUM(J53:J58) -> 26455.59
E60: =+C59/E48 -> 2.2657039

Sheet $$$$$
C2: ULTIMO COSTO 2025 | D2: COSTO ENE | E2: COSTO FEB. | F2: COSTO MAR | G2: COSTO ABR | H2: COSTO MAY | I2: COSTO JUN | J2: COSTO JUL | K2: COSTO AGO | L2: COSTO SEP | M2: COSTO OCT | N2: COSTO NOV | O2: COSTO DIC | P2: COSTO PROMEDIO | R2: INV ENERO | S2: COSTO TOTAL | T2: INV FEBRERO | U2: COSTO TOTAL | V2: INV MARZO | W2: COSTO TOTAL | X2: INV ABRIL | Y2: COSTO TOTAL | Z2: INV MAYO | AA2: COSTO TOTAL | AB2: INV JUNIO | AC2: COSTO TOTAL | AD2: INV JULIO | AE2: COSTO TOTAL | AF2: INV AGOSTO | AG2: COSTO TOTAL | AH2: INV SEPTIEMBRE | AI2: COSTO TOTAL | AJ2: INV OCTUBRE | AK2: COSTO TOTAL | AL2: INV NOVIEMBRE | AM2: COSTO TOTAL | AN2: INV DICIEMBRE | AO2: COSTO TOTAL | AP2: INV DICIEMBRE | AQ2: COSTO TOTAL
A3: ALMACEN ABASTOS LOGICOS (CANCÚN)
A4: CÓDIGO | B4: DESCRIPCIÓN
A5: 804104 | B5: TRIANGLE HASHBROW 63G/40PZ BAG APPROX) 4 X 2.5KG | C5: 404.86 | D5: =+C5 -> 404.86 | E5: =+D5 -> 404.86 | F5: =+E5 -> 404.86 | G5: =+F5 -> 404.86 | H5: =+G5 -> 404.86 | I5: =+H5 -> 404.86 | J5: =+I5 -> 404.86 | K5: =+J5 -> 404.86 | ... O5: =+N5 -> 404.86 | P5: =+AVERAGE(D5:O5) -> 404.86 | R5: =+CANCÚN!K3 -> 493.25 | S5: =+R5*D5 -> 199697.2 | T5: =+CANCÚN!P3 -> 259 | U5: =+T5*E5 -> 104858.74 | V5: =+CANCÚN!U3 -> 103.25 | W5: =+V5*F5 -> 41801.795 | X5: =+CANCÚN!Z3 -> 59.25 | Y5: =+X5*G5 -> 23987.955 | Z5: =+CANCÚN!AE3 -> 35 | AA5: =+Z5*H5 -> 14170.1
A6: 805567 | B6: HASBROWNS ROUNDS - FRYER 4X2500G | C6: 406.79 | D6: =+C6 -> 406.79 | E6: =+D6 -> 406.79 | F6: =+E6 -> 406.79 | G6: =+F6 -> 406.79 | H6: =+G6 -> 406.79 | I6: =+H6 -> 406.79 | J6: =+I6 -> 406.79 | K6: =+J6 -> 406.79 | ... O6: =+N6 -> 406.79 | P6: =+AVERAGE(D6:O6) -> 406.79 | R6: =+CANCÚN!K4 -> 743.5 | S6: =+R6*D6 -> 302448.36 | T6: =+CANCÚN!P4 -> 743.5 | U6: =+T6*E6 -> 302448.36 | V6: =+CANCÚN!U4 -> 466.25 | W6: =+V6*F6 -> 189665.84 | X6: =+CANCÚN!Z4 -> 148.25 | Y6: =+X6*G6 -> 60306.618 | Z6: =+CANCÚN!AE4 -> 111.25 | AA6: =+Z6*H6 -> 45255.388
A7: 803528 | B7: Aviko H Pommes Frites 11mm 7/16 4x2500g | C7: 264.35 | D7: =+C7 -> 264.35 | E7: =+D7 -> 264.35 | F7: =+E7 -> 264.35 | G7: =+F7 -> 264.35 | H7: =+G7 -> 264.35 | I7: =+H7 -> 264.35 | J7: =+I7 -> 264.35 | K7: =+J7 -> 264.35 | ... O7: =+N7 -> 264.35 | P7: =+AVERAGE(D7:O7) -> 264.35 | R7: =+CANCÚN!K5 -> 0 | S7: =+R7*D7 -> 0 | T7: =+CANCÚN!P5 -> 0 | U7: =+T7*E7 -> 0 | V7: =+CANCÚN!U5 -> 0 | W7: =+V7*F7 -> 0 | X7: =+CANCÚN!Z5 -> 0 | Y7: =+X7*G7 -> 0 | Z7: =+CANCÚN!AE5 -> 0 | AA7: =+Z7*H7 -> 0
A8: 806685 | B8: AVIKO H PREM.CRUNCH SHOESTRING 7MM 4X2270G | C8: 360.49 | D8: =+C8 -> 360.49 | E8: =+D8 -> 360.49 | F8: =+E8 -> 360.49 | G8: =+F8 -> 360.49 | H8: =+G8 -> 360.49 | I8: =+H8 -> 360.49 | J8: =+I8 -> 360.49 | K8: =+J8 -> 360.49 | ... O8: =+N8 -> 360.49 | P8: =+AVERAGE(D8:O8) -> 360.49 | R8: =+CANCÚN!K6 -> 0.25 | S8: =+R8*D8 -> 90.1225 | T8: =+CANCÚN!P6 -> 0 | U8: =+T8*E8 -> 0 | V8: =+CANCÚN!U6 -> 0 | W8: =+V8*F8 -> 0 | X8: =+CANCÚN!Z6 -> 0 | Y8: =+X8*G8 -> 0 | Z8: =+CANCÚN!AE6 -> 0 | AA8: =+Z8*H8 -> 0
D9: =+C9 -> 0 | E9: =+D9 -> 0 | F9: =+E9 -> 0 | G9: =+F9 -> 0 | H9: =+G9 -> 0 | I9: =+H9 -> 0 | J9: =+I9 -> 0 | K9: =+J9 -> 0 | ... O9: =+N9 -> 0 | P9: =+AVERAGE(D9:O9) -> 0 | S9: =+R9*D9 -> 0 | U9: =+T9*E9 -> 0 | W9: =+V9*F9 -> 0 | Y9: =+X9*G9 -> 0 | AA9: =+Z9*H9 -> 0
D10: =+C10 -> 0 | E10: =+D10 -> 0 | F10: =+E10 -> 0 | G10: =+F10 -> 0 | H10: =+G10 -> 0 | I10: =+H10 -> 0 | J10: =+I10 -> 0 | K10: =+J10 -> 0 | ... O10: =+N10 -> 0 | P10: =+AVERAGE(D10:O10) -> 0 | S10: =+R10*D10 -> 0 | U10: =+T10*E10 -> 0 | W10: =+V10*F10 -> 0 | Y10: =+X10*G10 -> 0 | AA10: =+Z10*H10 -> 0
D11: =+C11 -> 0 | E11: =+D11 -> 0 | F11: =+E11 -> 0 | G11: =+F11 -> 0 | H11: =+G11 -> 0 | I11: =+H11 -> 0 | J11: =+I11 -> 0 | K11: =+J11 -> 0 | ... O11: =+N11 -> 0 | P11: =+AVERAGE(D11:O11) -> 0 | S11: =+R11*D11 -> 0 | U11: =+T11*E11 -> 0 | W11: =+V11*F11 -> 0 | Y11: =+X11*G11 -> 0 | AA11: =+Z11*H11 -> 0
A12: 105632 | B12: 10 MM NATURAL | C12: 280.75 | D12: 258.94 | E12: =+D12 -> 258.94 | F12: =+E12 -> 258.94 | G12: =+F12 -> 258.94 | H12: =+G12 -> 258.94 | I12: =+H12 -> 258.94 | J12: =+I12 -> 258.94 | K12: =+J12 -> 258.94 | L12: =+K12 -> 258.94 | ... O12: =+N12 -> 258.94 | P12: =+AVERAGE(D12:O12) -> 258.94 | R12: =+CANCÚN!K13 -> 3287.75 | S12: =+R12*D12 -> 851329.98 | T12: =+CANCÚN!P13 -> 2368 | U12: =+T12*E12 -> 613169.92 | V12: =+CANCÚN!U13 -> 746.75 | W12: =+V12*F12 -> 193363.45 | X12: =+CANCÚN!Z13 -> 0 | Y12: =+X12*G12 -> 0 | Z12: =+CANCÚN!AE13 -> 0 | AA12: =+Z12*H12 -> 0
A13: 102341 | B13: 10 MM CON COBERTURA | D13: 290.71 | E13: =+D13 -> 290.71 | F13: =+E13 -> 290.71 | G13: =+F13 -> 290.71 | H13: =+G13 -> 290.71 | I13: =+H13 -> 290.71 | J13: =+I13 -> 290.71 | K13: =+J13 -> 290.71 | L13: =+K13 -> 290.71 | ... O13: =+N13 -> 290.71 | P13: =+AVERAGE(D13:O13) -> 290.71 | R13: =+CANCÚN!K15 -> 2144.5 | S13: =+R13*D13 -> 623427.59 | T13: =+CANCÚN!P15 -> 1630.5 | U13: =+T13*E13 -> 474002.65 | V13: =+CANCÚN!U15 -> 1020.25 | W13: =+V13*F13 -> 296596.88 | X13: =+CANCÚN!Z15 -> 576.25 | Y13: =+X13*G13 -> 167521.64 | Z13: =+CANCÚN!AE15 -> 550.25 | AA13: =+Z13*H13 -> 159963.18
A14: 102310 | B14: 7 MM CON COBERTURA | C14: 361.11 | D14: =+C14 -> 361.11 | E14: =+D14 -> 361.11 | F14: =+E14 -> 361.11 | G14: 282.79 | H14: =+G14 -> 282.79 | I14: =+H14 -> 282.79 | J14: =+I14 -> 282.79 | K14: =+J14 -> 282.79 | L14: =+K14 -> 282.79 | M14: =+L14 -> 282.79 | N14: =+M14 -> 282.79 | O14: =+N14 -> 282.79 | P14: =+AVERAGE(D14:O14) -> 302.37 | R14: =+CANCÚN!K16 -> 99 | S14: =+R14*D14 -> 35749.89 | T14: =+CANCÚN!P16 -> 66.5 | U14: =+T14*E14 -> 24013.815 | V14: =+CANCÚN!U16 -> 38.75 | W14: =+V14*F14 -> 13993.013 | X14: =+CANCÚN!Z16 -> 134.75 | Y14: =+X14*G14 -> 38105.952 | Z14: =+CANCÚN!AE16 -> 123.75 | AA14: =+Z14*H14 -> 34995.263
A15: 102211 | B15: 7 MM NATURAL | C15: 360.56 | D15: =+C15 -> 360.56 | E15: =+D15 -> 360.56 | F15: =+E15 -> 360.56 | G15: =+F15 -> 360.56 | H15: =+G15 -> 360.56 | I15: =+H15 -> 360.56 | J15: =+I15 -> 360.56 | K15: =+J15 -> 360.56 | ... O15: =+N15 -> 360.56 | P15: =+AVERAGE(D15:O15) -> 360.56 | R15: =+CANCÚN!K17 -> 0 | S15: =+R15*D15 -> 0 | T15: =+CANCÚN!P17 -> 0 | U15: =+T15*E15 -> 0 | V15: =+CANCÚN!U17 -> 0 | W15: =+V15*F15 -> 0 | X15: =+CANCÚN!Z17 -> 0 | Y15: =+X15*G15 -> 0 | Z15: =+CANCÚN!AE17 -> 0 | AA15: =+Z15*H15 -> 0
A16: 104215 | B16: 10 MM CON COBERTURA Y CASCARA | C16: 393.15 | D16: 393.15 | E16: =+D16 -> 393.15 | F16: =+E16 -> 393.15 | G16: =+F16 -> 393.15 | H16: =+G16 -> 393.15 | I16: =+H16 -> 393.15 | J16: =+I16 -> 393.15 | K16: =+J16 -> 393.15 | L16: =+K16 -> 393.15 | ... O16: =+N16 -> 393.15 | P16: =+AVERAGE(D16:O16) -> 393.15 | R16: =+CANCÚN!K18 -> 0 | S16: =+R16*D16 -> 0 | T16: =+CANCÚN!P18 -> 0 | U16: =+T16*E16 -> 0 | V16: =+CANCÚN!U18 -> 0 | W16: =+V16*F16 -> 0 | X16: =+CANCÚN!Z18 -> 0 | Y16: =+X16*G16 -> 0 | Z16: =+CANCÚN!AE18 -> 0 | AA16: =+Z16*H16 -> 0
A17: 114054 | B17: GAJOS SAZONADOS | C17: 370.2 | D17: =+C17 -> 370.2 | E17: =+D17 -> 370.2 | F17: =+E17 -> 370.2 | G17: =+F17 -> 370.2 | H17: =+G17 -> 370.2 | I17: =+H17 -> 370.2 | J17: =+I17 -> 370.2 | K17: =+J17 -> 370.2 | ... O17: =+N17 -> 370.2 | P17: =+AVERAGE(D17:O17) -> 370.2 | R17: =+CANCÚN!K19 -> 486.25 | S17: =+R17*D17 -> 180009.75 | T17: =+CANCÚN!P19 -> 447.75 | U17: =+T17*E17 -> 165757.05 | V17: =+CANCÚN!U19 -> 420.75 | W17: =+V17*F17 -> 155761.65 | X17: =+CANCÚN!Z19 -> 391.5 | Y17: =+X17*G17 -> 144933.3 | Z17: =+CANCÚN!AE19 -> 384.5 | AA17: =+Z17*H17 -> 142341.9
A18: 102419 | B18: ONDULADA | C18: 311.91 | D18: 257.12 | E18: =+D18 -> 257.12 | F18: =+E18 -> 257.12 | G18: 234.64 | H18: =+G18 -> 234.64 | I18: =+H18 -> 234.64 | J18: =+I18 -> 234.64 | K18: =+J18 -> 234.64 | L18: =+K18 -> 234.64 | M18: =+L18 -> 234.64 | N18: =+M18 -> 234.64 | O18: =+N18 -> 234.64 | P18: =+AVERAGE(D18:O18) -> 240.26 | R18: =+CANCÚN!K20 -> 149 | S18: =+R18*D18 -> 38310.88 | T18: =+CANCÚN!P20 -> 114.75 | U18: =+T18*E18 -> 29504.52 | V18: =+CANCÚN!U20 -> 79.25 | W18: =+V18*F18 -> 20376.76 | X18: =+CANCÚN!Z20 -> 182.25 | Y18: =+X18*G18 -> 42763.14 | Z18: =+CANCÚN!AE20 -> 166.5 | AA18: =+Z18*H18 -> 39067.56
A19: 1000440 | B19: 3/8 VIMA FOODS | C19: 330 | D19: =+C19 -> 330 | E19: =+D19 -> 330 | F19: =+E19 -> 330 | G19: =+F19 -> 330 | H19: =+G19 -> 330 | I19: =+H19 -> 330 | J19: =+I19 -> 330 | K19: =+J19 -> 330 | ... O19: =+N19 -> 330 | P19: =+AVERAGE(D19:O19) -> 330 | R19: =+CANCÚN!K21 -> 3.25 | S19: =+R19*D19 -> 1072.5 | T19: =+CANCÚN!P21 -> 0 | U19: =+T19*E19 -> 0 | V19: =+CANCÚN!U21 -> 0 | W19: =+V19*F19 -> 0 | X19: =+CANCÚN!Z21 -> 0 | Y19: =+X19*G19 -> 0 | Z19: =+CANCÚN!AE21 -> 0 | AA19: =+Z19*H19 -> 0
A20: 102013 | B20: 10 MM NATURAL | C20: 318.12 | D20: =+C20 -> 318.12 | E20: =+D20 -> 318.12 | F20: =+E20 -> 318.12 | G20: 232.63 | H20: =+G20 -> 232.63 | I20: =+H20 -> 232.63 | J20: =+I20 -> 232.63 | K20: =+J20 -> 232.63 | L20: =+K20 -> 232.63 | M20: =+L20 -> 232.63 | N20: =+M20 -> 232.63 | O20: =+N20 -> 232.63 | P20: =+AVERAGE(D20:O20) -> 254.0025 | R20: =+CANCÚN!K14 -> 0 | S20: =+R20*D20 -> 0 | T20: =+CANCÚN!P14 -> 0 | U20: =+T20*E20 -> 0 | V20: =+CANCÚN!U14 -> 0 | W20: =+V20*F20 -> 0 | X20: =+CANCÚN!Z14 -> 1684 | Y20: =+X20*G20 -> 391748.92 | Z20: =+CANCÚN!AE14 -> 1320.75 | AA20: =+Z20*H20 -> 307246.07
D21: =+C21 -> 0 | E21: =+D21 -> 0 | F21: =+E21 -> 0 | G21: =+F21 -> 0 | H21: =+G21 -> 0 | I21: =+H21 -> 0 | J21: =+I21 -> 0 | K21: =+J21 -> 0 | ... O21: =+N21 -> 0 | P21: =+AVERAGE(D21:O21) -> 0 | S21: =+R21*D21 -> 0 | W21: =+V21*F21 -> 0 | AA21: =+Z21*H21 -> 0
A22: TOTAL CANCUN | R22: =+SUM(R5:R21) -> 7406.75 | S22: =+SUM(S5:S21) -> 2232136.3 | T22: =+SUM(T5:T21) -> 5630 | U22: =+SUM(U5:U21) -> 1713755.1 | V22: =+SUM(V5:V21) -> 2875.25 | W22: =+SUM(W5:W21) -> 911559.38 | X22: =+SUM(X5:X21) -> 3176.25 | Y22: =+SUM(Y5:Y21) -> 869367.52 | ... AA22: =+SUM(AA5:AA21) -> 743039.46
A24: ALMACEN ARCOSA
A25: 806685 | B25: AVIKO H PREM.CRUNCH SHOESTRING 7MM 4X2270G | C25: 344.32 | D25: 305.47 | E25: 297.01 | F25: 318.2 | G25: =+F25 -> 318.2 | H25: =+G25 -> 318.2 | I25: =+H25 -> 318.2 | J25: =+I25 -> 318.2 | K25: =+J25 -> 318.2 | L25: =+K25 -> 318.2 | M25: =+L25 -> 318.2 | N25: =+M25 -> 318.2 | O25: =+N25 -> 318.2 | P25: =+AVERAGE(D25:O25) -> 315.37333 | R25: =+'RESUMEN CDMX'!K4 -> 0 | S25: =+R25*D25 -> 0 | T25: =+'RESUMEN CDMX'!P4 -> 0 | U25: =+T25*E25 -> 0 | V25: 0 | W25: =+V25*F25 -> 0 | X25: 0 | Y25: =+X25*H25 -> 0
A26: 806939 | B26: AVIKO CRINKLE CUT 12MM 4 X 2.5 KG | C26: 326.49 | D26: =+C26 -> 326.49 | E26: 287.31 | F26: 308.53 | G26: =+F26 -> 308.53 | H26: =+G26 -> 308.53 | I26: =+H26 -> 308.53 | J26: =+I26 -> 308.53 | K26: =+J26 -> 308.53 | L26: =+K26 -> 308.53 | M26: =+L26 -> 308.53 | N26: =+M26 -> 308.53 | O26: =+N26 -> 308.53 | P26: =+AVERAGE(D26:O26) -> 308.25833 | R26: =+'RESUMEN CDMX'!K5 -> 0 | S26: =+R26*D26 -> 0 | T26: =+'RESUMEN CDMX'!P5 -> 0 | U26: =+T26*E26 -> 0 | V26: 0 | W26: =+V26*F26 -> 0 | X26: 0 | Y26: =+X26*H26 -> 0
A27: 806694 | B27: AVIKO SUPER CRUNCH 9.5mm 3/8 4x2500g | C27: 382.98 | D27: =+C27 -> 382.98 | E27: 325.08 | F27: 366.07 | G27: =+F27 -> 366.07 | H27: =+G27 -> 366.07 | I27: =+H27 -> 366.07 | J27: =+I27 -> 366.07 | K27: =+J27 -> 366.07 | L27: =+K27 -> 366.07 | M27: =+L27 -> 366.07 | N27: =+M27 -> 366.07 | O27: =+N27 -> 366.07 | P27: =+AVERAGE(D27:O27) -> 364.06333 | R27: =+'RESUMEN CDMX'!K6 -> 0 | S27: =+R27*D27 -> 0 | T27: =+'RESUMEN CDMX'!P6 -> 0 | U27: =+T27*E27 -> 0 | V27: 0 | W27: =+V27*F27 -> 0 | X27: 0 | Y27: =+X27*H27 -> 0
A28: 804104 | B28: HASHBROWN TRIANG | C28: 369.36 | D28: =+C28 -> 369.36 | E28: =+D28 -> 369.36 | F28: =+E28 -> 369.36 | G28: =+F28 -> 369.36 | H28: =+G28 -> 369.36 | I28: =+H28 -> 369.36 | J28: =+I28 -> 369.36 | K28: =+J28 -> 369.36 | ... O28: =+N28 -> 369.36 | P28: =+AVERAGE(D28:O28) -> 369.36 | R28: =+'RESUMEN CDMX'!K7 -> 0 | S28: =+R28*D28 -> 0 | T28: =+'RESUMEN CDMX'!P7 -> 0 | U28: =+T28*E28 -> 0 | V28: 0 | W28: =+V28*F28 -> 0 | X28: 0 | Y28: =+X28*H28 -> 0
A29: 806686 | B29: AVIKO H PREM CRUNCH 9.5 mm 3/8 4x2270g | C29: 320.48 | D29: =+C29 -> 320.48 | E29: 297.01 | F29: =+E29 -> 297.01 | G29: =+F29 -> 297.01 | H29: =+G29 -> 297.01 | I29: =+H29 -> 297.01 | J29: =+I29 -> 297.01 | K29: =+J29 -> 297.01 | L29: =+K29 -> 297.01 | M29: =+L29 -> 297.01 | ... O29: =+N29 -> 297.01 | P29: =+AVERAGE(D29:O29) -> 298.96583 | R29: =+'RESUMEN CDMX'!K8 -> 161 | S29: =+R29*D29 -> 51597.28 | T29: =+'RESUMEN CDMX'!P8 -> 112 | U29: =+T29*E29 -> 33265.12 | V29: 0 | W29: =+V29*F29 -> 0 | X29: 0 | Y29: =+X29*H29 -> 0
A30: 804109 | B30: AVIKO SHOESTRING 5x2500g | C30: 424.92 | D30: =+C30 -> 424.92 | E30: 361.2 | F30: 370.16 | G30: =+F30 -> 370.16 | H30: =+G30 -> 370.16 | I30: =+H30 -> 370.16 | J30: =+I30 -> 370.16 | K30: =+J30 -> 370.16 | L30: =+K30 -> 370.16 | M30: =+L30 -> 370.16 | N30: =+M30 -> 370.16 | O30: =+N30 -> 370.16 | P30: =+AVERAGE(D30:O30) -> 373.97667 | R30: =+'RESUMEN CDMX'!K9 -> 1 | S30: =+R30*D30 -> 424.92 | T30: =+'RESUMEN CDMX'!P9 -> 1 | U30: =+T30*E30 -> 361.2 | V30: 0 | W30: =+V30*F30 -> 0 | X30: 0 | Y30: =+X30*H30 -> 0
A31: 806980 | B31: AVIKO SPICY JACKET WEDGES 4x2500g | C31: 371.47 | D31: =+C31 -> 371.47 | E31: 314.14 | F31: =+E31 -> 314.14 | G31: =+F31 -> 314.14 | H31: =+G31 -> 314.14 | I31: =+H31 -> 314.14 | J31: =+I31 -> 314.14 | K31: =+J31 -> 314.14 | L31: =+K31 -> 314.14 | M31: =+L31 -> 314.14 | ... O31: =+N31 -> 314.14 | P31: =+AVERAGE(D31:O31) -> 318.9175 | R31: =+'RESUMEN CDMX'!K10 -> 25 | S31: =+R31*D31 -> 9286.75 | T31: =+'RESUMEN CDMX'!P10 -> 25 | U31: =+T31*E31 -> 7853.5 | V31: 0 | W31: =+V31*F31 -> 0 | X31: 0 | Y31: =+X31*H31 -> 0
A32: 806982 | B32: AROS DE CEBOLLA 1X1000g | C32: 346.77 | D32: =+C32 -> 346.77 | E32: =+D32 -> 346.77 | F32: 337.55 | G32: =+F32 -> 337.55 | H32: =+G32 -> 337.55 | I32: =+H32 -> 337.55 | J32: =+I32 -> 337.55 | K32: =+J32 -> 337.55 | L32: =+K32 -> 337.55 | M32: =+L32 -> 337.55 | N32: =+M32 -> 337.55 | O32: =+N32 -> 337.55 | P32: =+AVERAGE(D32:O32) -> 339.08667 | R32: =+'RESUMEN CDMX'!K11 -> 50 | S32: =+R32*D32 -> 17338.5 | T32: =+'RESUMEN CDMX'!P11 -> 50 | U32: =+T32*E32 -> 17338.5 | V32: 0 | W32: =+V32*F32 -> 0 | X32: 0 | Y32: =+X32*H32 -> 0
A33: 260612 | B33: CASTEL STRAIGHT CUT FRIES 4X2500g | C33: 298.86 | D33: =+C33 -> 298.86 | E33: =+D33 -> 298.86 | F33: =+E33 -> 298.86 | G33: =+F33 -> 298.86 | H33: =+G33 -> 298.86 | I33: =+H33 -> 298.86 | J33: =+I33 -> 298.86 | K33: =+J33 -> 298.86 | ... O33: =+N33 -> 298.86 | P33: =+AVERAGE(D33:O33) -> 298.86 | R33: =+'RESUMEN CDMX'!K12 -> 66 | S33: =+R33*D33 -> 19724.76 | T33: =+'RESUMEN CDMX'!P12 -> 66 | U33: =+T33*E33 -> 19724.76 | V33: 0 | W33: =+V33*F33 -> 0 | X33: 0 | Y33: =+X33*H33 -> 0
A34: 804661 | B34: AVIKO STEAK FRIES 4X2500G 4X5.5 LBS | C34: 329.94 | D34: =+C34 -> 329.94 | E34: =+D34 -> 329.94 | F34: =+E34 -> 329.94 | G34: =+F34 -> 329.94 | H34: =+G34 -> 329.94 | I34: =+H34 -> 329.94 | J34: =+I34 -> 329.94 | K34: =+J34 -> 329.94 | ... O34: =+N34 -> 329.94 | P34: =+AVERAGE(D34:O34) -> 329.94 | R34: =+'RESUMEN CDMX'!K13 -> 0 | S34: =+R34*D34 -> 0 | T34: =+'RESUMEN CDMX'!P13 -> 0 | U34: =+T34*E34 -> 0 | V34: 0 | W34: =+V34*F34 -> 0 | X34: 0 | Y34: =+X34*H34 -> 0
A35: 806702 | B35: AVIKO H SUPER CRUNCH 15mm 6x2500g | C35: 554.39 | D35: 432.95 | E35: =+D35 -> 432.95 | F35: =+E35 -> 432.95 | G35: =+F35 -> 432.95 | H35: =+G35 -> 432.95 | I35: =+H35 -> 432.95 | J35: =+I35 -> 432.95 | K35: =+J35 -> 432.95 | L35: =+K35 -> 432.95 | ... O35: =+N35 -> 432.95 | P35: =+AVERAGE(D35:O35) -> 432.95 | R35: =+'RESUMEN CDMX'!K14 -> 0 | S35: =+R35*D35 -> 0 | T35: =+'RESUMEN CDMX'!P14 -> 0 | U35: =+T35*E35 -> 0 | V35: 0 | W35: =+V35*F35 -> 0 | X35: 0 | Y35: =+X35*H35 -> 0
A36: 807769 | B36: PAPAS FRITAS CORTE REG 10 X 1000G | C36: 346.43 | D36: =+C36 -> 346.43 | E36: =+D36 -> 346.43 | F36: =+E36 -> 346.43 | G36: =+F36 -> 346.43 | H36: =+G36 -> 346.43 | I36: =+H36 -> 346.43 | J36: =+I36 -> 346.43 | K36: =+J36 -> 346.43 | ... O36: =+N36 -> 346.43 | P36: =+AVERAGE(D36:O36) -> 346.43 | R36: =+'RESUMEN CDMX'!K15 -> 0 | S36: =+R36*D36 -> 0 | T36: =+'RESUMEN CDMX'!P15 -> 0 | U36: =+T36*E36 -> 0 | V36: 0 | W36: =+V36*F36 -> 0 | X36: 0 | Y36: =+X36*H36 -> 0
A37: 807329 | B37: AVIKO ORIGINAL 20X450G | C37: 356.34 | D37: =+C37 -> 356.34 | E37: =+D37 -> 356.34 | F37: =+E37 -> 356.34 | G37: =+F37 -> 356.34 | H37: =+G37 -> 356.34 | I37: =+H37 -> 356.34 | J37: =+I37 -> 356.34 | K37: =+J37 -> 356.34 | ... O37: =+N37 -> 356.34 | P37: =+AVERAGE(D37:O37) -> 356.34 | R37: =+'RESUMEN CDMX'!K16 -> 0 | S37: =+R37*D37 -> 0 | T37: =+'RESUMEN CDMX'!P16 -> 0 | U37: =+T37*E37 -> 0 | V37: 0 | W37: =+V37*F37 -> 0 | X37: 0 | Y37: =+X37*H37 -> 0
A38: 805411 | B38: PAPAS FRITAS ZIGZAG 12/750GRS | C38: 340.91 | D38: =+C38 -> 340.91 | E38: 306.5 | F38: =+E38 -> 306.5 | G38: =+F38 -> 306.5 | H38: =+G38 -> 306.5 | I38: =+H38 -> 306.5 | J38: =+I38 -> 306.5 | K38: =+J38 -> 306.5 | L38: =+K38 -> 306.5 | M38: =+L38 -> 306.5 | ... O38: =+N38 -> 306.5 | P38: =+AVERAGE(D38:O38) -> 309.3675 | R38: =+'RESUMEN CDMX'!K17 -> 89.8 | S38: =+R38*D38 -> 30613.718 | T38: =+'RESUMEN CDMX'!P17 -> 55.8 | U38: =+T38*E38 -> 17102.7 | V38: 0 | W38: =+V38*F38 -> 0 | X38: 0 | Y38: =+X38*H38 -> 0
A39: 807679 | B39: AVIKO SPICY WEDGES 20X500G | C39: 388.31 | D39: =+C39 -> 388.31 | E39: 363.68 | F39: 386.98 | G39: =+F39 -> 386.98 | H39: =+G39 -> 386.98 | I39: =+H39 -> 386.98 | J39: =+I39 -> 386.98 | K39: =+J39 -> 386.98 | L39: =+K39 -> 386.98 | M39: =+L39 -> 386.98 | N39: =+M39 -> 386.98 | O39: =+N39 -> 386.98 | P39: =+AVERAGE(D39:O39) -> 385.14917 | R39: =+'RESUMEN CDMX'!K18 -> 393 | S39: =+R39*D39 -> 152605.83 | T39: =+'RESUMEN CDMX'!P18 -> 322 | U39: =+T39*E39 -> 117104.96 | V39: 0 | W39: =+V39*F39 -> 0 | X39: 0 | Y39: =+X39*H39 -> 0
A40: 805168 | B40: AVIKO AROS DE CEBOLLA PREFRITOS 25/400g | C40: 608.68 | D40: =+C40 -> 608.68 | E40: =+D40 -> 608.68 | F40: =+E40 -> 608.68 | G40: =+F40 -> 608.68 | H40: =+G40 -> 608.68 | I40: =+H40 -> 608.68 | J40: =+I40 -> 608.68 | K40: =+J40 -> 608.68 | ... O40: =+N40 -> 608.68 | P40: =+AVERAGE(D40:O40) -> 608.68 | R40: =+'RESUMEN CDMX'!K19 -> 277 | S40: =+R40*D40 -> 168604.36 | T40: =+'RESUMEN CDMX'!P19 -> 200 | U40: =+T40*E40 -> 121736 | V40: 0 | W40: =+V40*F40 -> 0 | X40: 0 | Y40: =+X40*H40 -> 0
A41: 807363 | B41: Aviko H Super Crunch 14x600g | C41: 357.28 | D41: =+C41 -> 357.28 | E41: =+D41 -> 357.28 | F41: =+E41 -> 357.28 | G41: =+F41 -> 357.28 | H41: =+G41 -> 357.28 | I41: =+H41 -> 357.28 | J41: =+I41 -> 357.28 | K41: =+J41 -> 357.28 | ... O41: =+N41 -> 357.28 | P41: =+AVERAGE(D41:O41) -> 357.28 | R41: =+'RESUMEN CDMX'!K20 -> 26 | S41: =+R41*D41 -> 9289.28 | T41: =+'RESUMEN CDMX'!P20 -> 17 | U41: =+T41*E41 -> 6073.76 | V41: 0 | W41: =+V41*F41 -> 0 | X41: 0 | Y41: =+X41*H41 -> 0
A42: 809529 | B42: Aviko SC Airfr. PommesFrites 10x750 | C42: 353.79 | D42: =+C42 -> 353.79 | E42: =+D42 -> 353.79 | F42: =+E42 -> 353.79 | G42: =+F42 -> 353.79 | H42: =+G42 -> 353.79 | I42: =+H42 -> 353.79 | J42: =+I42 -> 353.79 | K42: =+J42 -> 353.79 | ... O42: =+N42 -> 353.79 | P42: =+AVERAGE(D42:O42) -> 353.79 | R42: =+'RESUMEN CDMX'!K21 -> 397 | S42: =+R42*D42 -> 140454.63 | T42: =+'RESUMEN CDMX'!P21 -> 397 | U42: =+T42*E42 -> 140454.63 | V42: 0 | W42: =+V42*F42 -> 0 | X42: 0 | Y42: =+X42*H42 -> 0
D43: =+C43 -> 0 | E43: =+D43 -> 0 | F43: =+E43 -> 0 | G43: =+F43 -> 0 | H43: =+G43 -> 0 | I43: =+H43 -> 0 | J43: =+I43 -> 0 | K43: =+J43 -> 0 | ... O43: =+N43 -> 0 | P43: =+AVERAGE(D43:O43) -> 0
D44: =+C44 -> 0 | E44: =+D44 -> 0 | F44: =+E44 -> 0 | G44: =+F44 -> 0 | H44: =+G44 -> 0 | I44: =+H44 -> 0 | J44: =+I44 -> 0 | K44: =+J44 -> 0 | ... O44: =+N44 -> 0 | P44: =+AVERAGE(D44:O44) -> 0
D45: =+C45 -> 0 | E45: =+D45 -> 0 | F45: =+E45 -> 0 | G45: =+F45 -> 0 | H45: =+G45 -> 0 | I45: =+H45 -> 0 | J45: =+I45 -> 0 | K45: =+J45 -> 0 | ... O45: =+N45 -> 0 | P45: =+AVERAGE(D45:O45) -> 0
A46: TOTAL ARCOSA | R46: =+SUM(R25:R45) -> 1485.8 | S46: =+SUM(S25:S45) -> 599940.03 | T46: =+SUM(T25:T45) -> 1245.8 | U46: =+SUM(U25:U45) -> 481015.13 | V46: =+SUM(V25:V45) -> 0 | W46: =+SUM(W25:W45) -> 0 | X46: =+SUM(X25:X45) -> 0 | Y46: =+SUM(Y25:Y45) -> 0
A48: ALMACEN FRESCO
A49: 806685 | B49: AVIKO H PREM.CRUNCH SHOESTRING 7MM 4X2270G | C49: 344.32 | D49: =+D25 -> 305.47 | E49: =+E25 -> 297.01 | F49: =+F25 -> 318.2 | G49: =+F49 -> 318.2 | H49: =+G49 -> 318.2 | I49: =+H49 -> 318.2 | J49: =+I49 -> 318.2 | K49: =+J49 -> 318.2 | L49: =+K49 -> 318.2 | M49: =+L49 -> 318.2 | N49: =+M49 -> 318.2 | O49: =+N49 -> 318.2 | P49: =+AVERAGE(D49:O49) -> 315.37333 | R49: 0 | S49: =+R49*D49 -> 0 | U49: =+T49*E49 -> 0
A50: 806939 | B50: AVIKO CRINKLE CUT 12MM 4 X 2.5 KG | C50: 326.49 | D50: =+C50 -> 326.49 | E50: =+E26 -> 287.31 | F50: =+F26 -> 308.53 | G50: =+F50 -> 308.53 | H50: =+G50 -> 308.53 | I50: =+H50 -> 308.53 | J50: =+I50 -> 308.53 | K50: =+J50 -> 308.53 | L50: =+K50 -> 308.53 | M50: =+L50 -> 308.53 | N50: =+M50 -> 308.53 | O50: =+N50 -> 308.53 | P50: =+AVERAGE(D50:O50) -> 308.25833 | R50: =+FRESCO!H4 -> 2 | S50: =+R50*D50 -> 652.98 | T50: =+FRESCO!M4 -> 2 | U50: =+T50*E50 -> 574.62 | V50: =+FRESCO!R4 -> 2 | W50: =+V50*F50 -> 617.06 | X50: =+FRESCO!BP4 -> 2 | Y50: =+X50*G50 -> 617.06 | Z50: =+FRESCO!BU4 -> 2 | AA50: =+Z50*N49 -> 636.4
A51: 806694 | B51: AVIKO SUPER CRUNCH 9.5mm 3/8 4x2500g | C51: 382.98 | D51: =+C51 -> 382.98 | E51: =+E27 -> 325.08 | F51: =+F27 -> 366.07 | G51: =+F51 -> 366.07 | H51: =+G51 -> 366.07 | I51: =+H51 -> 366.07 | J51: =+I51 -> 366.07 | K51: =+J51 -> 366.07 | L51: =+K51 -> 366.07 | M51: =+L51 -> 366.07 | N51: =+M51 -> 366.07 | O51: =+N51 -> 366.07 | P51: =+AVERAGE(D51:O51) -> 364.06333 | R51: =+'RESUMEN CDMX'!W6 -> 0 | S51: =+R51*D51 -> 0 | U51: =+T51*E51 -> 0 | W51: =+V51*F51 -> 0 | Y51: =+X51*G51 -> 0 | AA51: =+Z51*N50 -> 0
A52: 804104 | B52: HASHBROWN TRIANG | C52: 369.36 | D52: =+C52 -> 369.36 | E52: =+E28 -> 369.36 | F52: =+F28 -> 369.36 | G52: =+F52 -> 369.36 | H52: =+G52 -> 369.36 | I52: =+H52 -> 369.36 | J52: =+I52 -> 369.36 | K52: =+J52 -> 369.36 | L52: =+K52 -> 369.36 | M52: =+L52 -> 369.36 | N52: =+M52 -> 369.36 | O52: =+N52 -> 369.36 | P52: =+AVERAGE(D52:O52) -> 369.36 | R52: =+'RESUMEN CDMX'!W7 -> 0 | S52: =+R52*D52 -> 0 | U52: =+T52*E52 -> 0 | W52: =+V52*F52 -> 0 | Y52: =+X52*G52 -> 0 | AA52: =+Z52*N51 -> 0
A53: 806686 | B53: AVIKO H PREM CRUNCH 9.5 mm 3/8 4x2270g | C53: 320.48 | D53: =+C53 -> 320.48 | E53: =+E29 -> 297.01 | F53: =+F29 -> 297.01 | G53: =+F53 -> 297.01 | H53: =+G53 -> 297.01 | I53: =+H53 -> 297.01 | J53: =+I53 -> 297.01 | K53: =+J53 -> 297.01 | L53: =+K53 -> 297.01 | M53: =+L53 -> 297.01 | N53: =+M53 -> 297.01 | O53: =+N53 -> 297.01 | P53: =+AVERAGE(D53:O53) -> 298.96583 | R53: =+FRESCO!H7 -> 12 | S53: =+R53*D53 -> 3845.76 | T53: =+FRESCO!M7 -> 12 | U53: =+T53*E53 -> 3564.12 | V53: =+FRESCO!R7 -> 12 | W53: =+V53*F53 -> 3564.12 | X53: =+FRESCO!BP7 -> 12 | Y53: =+X53*G53 -> 3564.12 | Z53: =+FRESCO!BU7 -> 12 | AA53: =+Z53*N52 -> 4432.32
A54: 804109 | B54: AVIKO SHOESTRING 5x2500g | C54: 424.92 | D54: =+C54 -> 424.92 | E54: =+E30 -> 361.2 | F54: =+F30 -> 370.16 | G54: =+F54 -> 370.16 | H54: =+G54 -> 370.16 | I54: =+H54 -> 370.16 | J54: =+I54 -> 370.16 | K54: =+J54 -> 370.16 | L54: =+K54 -> 370.16 | M54: =+L54 -> 370.16 | N54: =+M54 -> 370.16 | O54: =+N54 -> 370.16 | P54: =+AVERAGE(D54:O54) -> 373.97667 | R54: =+'RESUMEN CDMX'!W9 -> 0 | S54: =+R54*D54 -> 0 | U54: =+T54*E54 -> 0 | W54: =+V54*F54 -> 0 | Y54: =+X54*G54 -> 0 | AA54: =+Z54*N53 -> 0
A55: 806980 | B55: AVIKO SPICY JACKET WEDGES 4x2500g | C55: 371.47 | D55: =+C55 -> 371.47 | E55: =+E31 -> 314.14 | F55: =+F31 -> 314.14 | G55: =+F55 -> 314.14 | H55: =+G55 -> 314.14 | I55: =+H55 -> 314.14 | J55: =+I55 -> 314.14 | K55: =+J55 -> 314.14 | L55: =+K55 -> 314.14 | M55: =+L55 -> 314.14 | N55: =+M55 -> 314.14 | O55: =+N55 -> 314.14 | P55: =+AVERAGE(D55:O55) -> 318.9175 | R55: =+'RESUMEN CDMX'!W10 -> 0 | S55: =+R55*D55 -> 0 | U55: =+T55*E55 -> 0 | W55: =+V55*F55 -> 0 | Y55: =+X55*G55 -> 0 | AA55: =+Z55*N54 -> 0
A56: 806982 | B56: AROS DE CEBOLLA 1X1000g | C56: 346.77 | D56: =+C56 -> 346.77 | E56: =+E32 -> 346.77 | F56: =+F32 -> 337.55 | G56: =+F56 -> 337.55 | H56: =+G56 -> 337.55 | I56: =+H56 -> 337.55 | J56: =+I56 -> 337.55 | K56: =+J56 -> 337.55 | L56: =+K56 -> 337.55 | M56: =+L56 -> 337.55 | N56: =+M56 -> 337.55 | O56: =+N56 -> 337.55 | P56: =+AVERAGE(D56:O56) -> 339.08667 | R56: =+'RESUMEN CDMX'!W11 -> 0 | S56: =+R56*D56 -> 0 | U56: =+T56*E56 -> 0 | W56: =+V56*F56 -> 0 | Y56: =+X56*G56 -> 0 | AA56: =+Z56*N55 -> 0
A57: 260612 | B57: CASTEL STRAIGHT CUT FRIES 4X2500g | C57: 298.86 | D57: =+C57 -> 298.86 | E57: =+E33 -> 298.86 | F57: =+F33 -> 298.86 | G57: =+F57 -> 298.86 | H57: =+G57 -> 298.86 | I57: =+H57 -> 298.86 | J57: =+I57 -> 298.86 | K57: =+J57 -> 298.86 | L57: =+K57 -> 298.86 | M57: =+L57 -> 298.86 | N57: =+M57 -> 298.86 | O57: =+N57 -> 298.86 | P57: =+AVERAGE(D57:O57) -> 298.86 | R57: =+'RESUMEN CDMX'!W12 -> 0 | S57: =+R57*D57 -> 0 | U57: =+T57*E57 -> 0 | W57: =+V57*F57 -> 0 | Y57: =+X57*G57 -> 0 | AA57: =+Z57*N56 -> 0
A58: 804661 | B58: AVIKO STEAK FRIES 4X2500G 4X5.5 LBS | C58: 329.94 | D58: =+C58 -> 329.94 | E58: =+E34 -> 329.94 | F58: =+F34 -> 329.94 | G58: =+F58 -> 329.94 | H58: =+G58 -> 329.94 | I58: =+H58 -> 329.94 | J58: =+I58 -> 329.94 | K58: =+J58 -> 329.94 | L58: =+K58 -> 329.94 | M58: =+L58 -> 329.94 | N58: =+M58 -> 329.94 | O58: =+N58 -> 329.94 | P58: =+AVERAGE(D58:O58) -> 329.94 | R58: =+'RESUMEN CDMX'!W13 -> 0 | S58: =+R58*D58 -> 0 | U58: =+T58*E58 -> 0 | W58: =+V58*F58 -> 0 | Y58: =+X58*G58 -> 0 | AA58: =+Z58*N57 -> 0
A59: 806702 | B59: AVIKO H SUPER CRUNCH 15mm 6x2500g | C59: 554.39 | D59: =+D35 -> 432.95 | E59: =+E35 -> 432.95 | F59: =+F35 -> 432.95 | G59: =+F59 -> 432.95 | H59: =+G59 -> 432.95 | I59: =+H59 -> 432.95 | J59: =+I59 -> 432.95 | K59: =+J59 -> 432.95 | L59: =+K59 -> 432.95 | M59: =+L59 -> 432.95 | N59: =+M59 -> 432.95 | O59: =+N59 -> 432.95 | P59: =+AVERAGE(D59:O59) -> 432.95 | R59: =+'RESUMEN CDMX'!W14 -> 0 | S59: =+R59*D59 -> 0 | U59: =+T59*E59 -> 0 | W59: =+V59*F59 -> 0 | Y59: =+X59*G59 -> 0 | AA59: =+Z59*N58 -> 0
A60: 807769 | B60: PAPAS FRITAS CORTE REG 10 X 1000G | C60: 346.43 | D60: =+C60 -> 346.43 | E60: =+E36 -> 346.43 | F60: =+F36 -> 346.43 | G60: =+F60 -> 346.43 | H60: =+G60 -> 346.43 | I60: =+H60 -> 346.43 | J60: =+I60 -> 346.43 | K60: =+J60 -> 346.43 | L60: =+K60 -> 346.43 | M60: =+L60 -> 346.43 | N60: =+M60 -> 346.43 | O60: =+N60 -> 346.43 | P60: =+AVERAGE(D60:O60) -> 346.43 | R60: =+FRESCO!H15 -> 165 | S60: =+R60*D60 -> 57160.95 | T60: =+FRESCO!M15 -> 165 | U60: =+T60*E60 -> 57160.95 | V60: =+FRESCO!R15 -> 118 | W60: =+V60*F60 -> 40878.74 | X60: =+FRESCO!BP15 -> 737 | Y60: =+X60*G60 -> 255318.91 | Z60: =+FRESCO!BU15 -> 737 | AA60: =+Z60*N59 -> 319084.15
A61: 807329 | B61: AVIKO ORIGINAL 20X450G | C61: 356.34 | D61: =+C61 -> 356.34 | E61: =+E37 -> 356.34 | F61: =+F37 -> 356.34 | G61: =+F61 -> 356.34 | H61: =+G61 -> 356.34 | I61: =+H61 -> 356.34 | J61: =+I61 -> 356.34 | K61: =+J61 -> 356.34 | L61: =+K61 -> 356.34 | M61: =+L61 -> 356.34 | N61: =+M61 -> 356.34 | O61: =+N61 -> 356.34 | P61: =+AVERAGE(D61:O61) -> 356.34 | R61: =+FRESCO!H16 -> 0 | S61: =+R61*D61 -> 0 | T61: =+FRESCO!M16 -> 0 | U61: =+T61*E61 -> 0 | V61: =+FRESCO!R16 -> 103 | W61: =+V61*F61 -> 36703.02 | X61: =+FRESCO!BP16 -> 179 | Y61: =+X61*G61 -> 63784.86 | Z61: =+FRESCO!BU16 -> 179 | AA61: =+Z61*N60 -> 62010.97
A62: 805411 | B62: PAPAS FRITAS ZIGZAG 12/750GRS | C62: 340.91 | D62: =+C62 -> 340.91 | E62: =+E38 -> 306.5 | F62: =+F38 -> 306.5 | G62: =+F62 -> 306.5 | H62: =+G62 -> 306.5 | I62: =+H62 -> 306.5 | J62: =+I62 -> 306.5 | K62: =+J62 -> 306.5 | L62: =+K62 -> 306.5 | M62: =+L62 -> 306.5 | N62: =+M62 -> 306.5 | O62: =+N62 -> 306.5 | P62: =+AVERAGE(D62:O62) -> 309.3675 | R62: =+FRESCO!H17 -> 41 | S62: =+R62*D62 -> 13977.31 | T62: =+FRESCO!M17 -> 41 | U62: =+T62*E62 -> 12566.5 | V62: =+FRESCO!R17 -> 173 | W62: =+V62*F62 -> 53024.5 | X62: =+FRESCO!BP17 -> 164 | Y62: =+X62*G62 -> 50266 | Z62: =+FRESCO!BU17 -> 164 | AA62: =+Z62*N61 -> 58439.76
A63: 807679 | B63: AVIKO SPICY WEDGES 20X500G | C63: 388.31 | D63: =+C63 -> 388.31 | E63: =+E39 -> 363.68 | F63: =+F39 -> 386.98 | G63: =+F63 -> 386.98 | H63: =+G63 -> 386.98 | I63: =+H63 -> 386.98 | J63: =+I63 -> 386.98 | K63: =+J63 -> 386.98 | L63: =+K63 -> 386.98 | M63: =+L63 -> 386.98 | N63: =+M63 -> 386.98 | O63: =+N63 -> 386.98 | P63: =+AVERAGE(D63:O63) -> 385.14917 | R63: =+FRESCO!H18 -> 0 | S63: =+R63*D63 -> 0 | T63: =+FRESCO!M18 -> 99 | U63: =+T63*E63 -> 36004.32 | V63: =+FRESCO!R18 -> 51 | W63: =+V63*F63 -> 19735.98 | X63: =+FRESCO!BP18 -> 33 | Y63: =+X63*G63 -> 12770.34 | Z63: =+FRESCO!BU18 -> 33 | AA63: =+Z63*N62 -> 10114.5
A64: 805168 | B64: AVIKO AROS DE CEBOLLA PREFRITOS 25/400g | C64: 608.68 | D64: =+C64 -> 608.68 | E64: =+E40 -> 608.68 | F64: =+F40 -> 608.68 | G64: =+F64 -> 608.68 | H64: =+G64 -> 608.68 | I64: =+H64 -> 608.68 | J64: =+I64 -> 608.68 | K64: =+J64 -> 608.68 | L64: =+K64 -> 608.68 | M64: =+L64 -> 608.68 | N64: =+M64 -> 608.68 | O64: =+N64 -> 608.68 | P64: =+AVERAGE(D64:O64) -> 608.68 | R64: =+FRESCO!H19 -> 8 | S64: =+R64*D64 -> 4869.44 | T64: =+FRESCO!M19 -> 8 | U64: =+T64*E64 -> 4869.44 | V64: =+FRESCO!R19 -> 96 | W64: =+V64*F64 -> 58433.28 | X64: =+FRESCO!BP19 -> 96 | Y64: =+X64*G64 -> 58433.28 | Z64: =+FRESCO!BU19 -> 96 | AA64: =+Z64*N63 -> 37150.08
A65: 807363 | B65: Aviko H Super Crunch 14x600g | C65: 357.28 | D65: =+C65 -> 357.28 | E65: =+E41 -> 357.28 | F65: =+F41 -> 357.28 | G65: =+F65 -> 357.28 | H65: =+G65 -> 357.28 | I65: =+H65 -> 357.28 | J65: =+I65 -> 357.28 | K65: =+J65 -> 357.28 | L65: =+K65 -> 357.28 | M65: =+L65 -> 357.28 | N65: =+M65 -> 357.28 | O65: =+N65 -> 357.28 | P65: =+AVERAGE(D65:O65) -> 357.28 | R65: =+FRESCO!H21 -> 392 | S65: =+R65*D65 -> 140053.76 | T65: =+FRESCO!M21 -> 392 | U65: =+T65*E65 -> 140053.76 | V65: =+FRESCO!R21 -> 391 | W65: =+V65*F65 -> 139696.48 | X65: =+FRESCO!BP21 -> 391 | Y65: =+X65*G65 -> 139696.48 | Z65: =+FRESCO!BU21 -> 391 | AA65: =+Z65*N64 -> 237993.88
A66: 809529 | B66: Aviko SC Airfr. PommesFrites 10x750 | C66: 353.79 | D66: =+C66 -> 353.79 | E66: =+D66 -> 353.79 | F66: =+F42 -> 353.79 | G66: =+F66 -> 353.79 | H66: =+G66 -> 353.79 | I66: =+H66 -> 353.79 | J66: =+I66 -> 353.79 | K66: =+J66 -> 353.79 | L66: =+K66 -> 353.79 | M66: =+L66 -> 353.79 | N66: =+M66 -> 353.79 | O66: =+N66 -> 353.79 | P66: =+AVERAGE(D66:O66) -> 353.79 | S66: =+R66*D66 -> 0 | W66: =+V66*F66 -> 0 | Y66: =+X66*G66 -> 0 | AA66: =+Z66*N65 -> 0
D67: =+C67 -> 0 | E67: =+D67 -> 0 | F67: =+F43 -> 0 | G67: =+F67 -> 0 | H67: =+G67 -> 0 | I67: =+H67 -> 0 | J67: =+I67 -> 0 | K67: =+J67 -> 0 | L67: =+K67 -> 0 | M67: =+L67 -> 0 | N67: =+M67 -> 0 | O67: =+N67 -> 0 | P67: =+AVERAGE(D67:O67) -> 0
D68: =+C68 -> 0 | E68: =+D68 -> 0 | F68: =+F44 -> 0 | G68: =+F68 -> 0 | H68: =+G68 -> 0 | I68: =+H68 -> 0 | J68: =+I68 -> 0 | K68: =+J68 -> 0 | L68: =+K68 -> 0 | M68: =+L68 -> 0 | N68: =+M68 -> 0 | O68: =+N68 -> 0 | P68: =+AVERAGE(D68:O68) -> 0
D69: =+C69 -> 0 | E69: =+D69 -> 0 | F69: =+F45 -> 0 | G69: =+F69 -> 0 | H69: =+G69 -> 0 | I69: =+H69 -> 0 | J69: =+I69 -> 0 | K69: =+J69 -> 0 | L69: =+K69 -> 0 | M69: =+L69 -> 0 | N69: =+M69 -> 0 | O69: =+N69 -> 0 | P69: =+AVERAGE(D69:O69) -> 0
A70: TOTAL FRESCO | R70: =+SUM(R49:R69) -> 620 | S70: =+SUM(S49:S69) -> 220560.2 | T70: =+SUM(T49:T69) -> 719 | U70: =+SUM(U49:U69) -> 254793.71 | V70: =+SUM(V49:V69) -> 946 | W70: =+SUM(W49:W69) -> 352653.18 | X70: =+SUM(X49:X69) -> 1614 | Y70: =+SUM(Y49:Y69) -> 584451.05 | ... AA70: =+SUM(AA49:AA69) -> 729862.06
A72: ALMACEN FRIGARSA
A73: 806685 | B73: AVIKO H PREM.CRUNCH SHOESTRING 7MM 4X2270G | C73: 344.32 | D73: =+D49 -> 305.47 | E73: =+E49 -> 297.01 | F73: =+F49 -> 318.2 | G73: =+F73 -> 318.2 | H73: =+G73 -> 318.2 | I73: =+H73 -> 318.2 | J73: =+I73 -> 318.2 | K73: =+J73 -> 318.2 | L73: =+K73 -> 318.2 | M73: =+L73 -> 318.2 | N73: =+M73 -> 318.2 | O73: =+N73 -> 318.2 | P73: =+AVERAGE(D73:O73) -> 315.37333 | R73: =+FRIGARSA!H3 -> 1442.3 | S73: =+R73*D73 -> 440579.38 | T73: =+FRIGARSA!M3 -> 689.3 | U73: =+T73*E73 -> 204728.99 | V73: =+FRIGARSA!R3 -> 27.3 | W73: =+V73*F73 -> 8686.86 | X73: =+FRIGARSA!W3 -> 2.3 | Y73: =+X73*G73 -> 731.86 | Z73: =+FRIGARSA!AB3 -> 2.3 | AA73: =+Z73*N73 -> 731.86
A74: 806939 | B74: AVIKO CRINKLE CUT 12MM 4 X 2.5 KG | C74: 326.49 | D74: =+C74 -> 326.49 | E74: =+E50 -> 287.31 | F74: =+F50 -> 308.53 | G74: =+F74 -> 308.53 | H74: =+G74 -> 308.53 | I74: =+H74 -> 308.53 | J74: =+I74 -> 308.53 | K74: =+J74 -> 308.53 | L74: =+K74 -> 308.53 | M74: =+L74 -> 308.53 | N74: =+M74 -> 308.53 | O74: =+N74 -> 308.53 | P74: =+AVERAGE(D74:O74) -> 308.25833 | R74: =+FRIGARSA!H4 -> 14 | S74: =+R74*D74 -> 4570.86 | T74: =+FRIGARSA!M4 -> 9 | U74: =+T74*E74 -> 2585.79 | V74: =+FRIGARSA!R4 -> 9 | W74: =+V74*F74 -> 2776.77 | X74: =+FRIGARSA!W4 -> 9 | Y74: =+X74*G74 -> 2776.77 | Z74: =+FRIGARSA!AB4 -> 9 | AA74: =+Z74*N74 -> 2776.77
A75: 806694 | B75: AVIKO SUPER CRUNCH 9.5mm 3/8 4x2500g | C75: 382.98 | D75: =+C75 -> 382.98 | E75: =+E51 -> 325.08 | F75: =+F51 -> 366.07 | G75: =+F75 -> 366.07 | H75: =+G75 -> 366.07 | I75: =+H75 -> 366.07 | J75: =+I75 -> 366.07 | K75: =+J75 -> 366.07 | L75: =+K75 -> 366.07 | M75: =+L75 -> 366.07 | N75: =+M75 -> 366.07 | O75: =+N75 -> 366.07 | P75: =+AVERAGE(D75:O75) -> 364.06333 | R75: 0 | S75: =+R75*D75 -> 0 | T75: 0 | U75: =+T75*E75 -> 0 | V75: 0 | W75: =+V75*F75 -> 0 | X75: 0 | Y75: =+X75*G75 -> 0 | Z75: =+FRIGARSA!AB5 -> 0 | AA75: =+Z75*N75 -> 0
A76: 804104 | B76: HASHBROWN TRIANG | C76: 369.36 | D76: =+C76 -> 369.36 | E76: =+E52 -> 369.36 | F76: =+F52 -> 369.36 | G76: =+F76 -> 369.36 | H76: =+G76 -> 369.36 | I76: =+H76 -> 369.36 | J76: =+I76 -> 369.36 | K76: =+J76 -> 369.36 | L76: =+K76 -> 369.36 | M76: =+L76 -> 369.36 | N76: =+M76 -> 369.36 | O76: =+N76 -> 369.36 | P76: =+AVERAGE(D76:O76) -> 369.36 | R76: =+FRIGARSA!H6 -> 21 | S76: =+R76*D76 -> 7756.56 | T76: =+FRIGARSA!M6 -> 19 | U76: =+T76*E76 -> 7017.84 | V76: =+FRIGARSA!R6 -> 7 | W76: =+V76*F76 -> 2585.52 | X76: =+FRIGARSA!W6 -> 7 | Y76: =+X76*G76 -> 2585.52 | Z76: =+FRIGARSA!AB6 -> 7 | AA76: =+Z76*N76 -> 2585.52
A77: 806686 | B77: AVIKO H PREM CRUNCH 9.5 mm 3/8 4x2270g | C77: 320.48 | D77: =+C77 -> 320.48 | E77: =+E53 -> 297.01 | F77: =+F53 -> 297.01 | G77: =+F77 -> 297.01 | H77: =+G77 -> 297.01 | I77: =+H77 -> 297.01 | J77: =+I77 -> 297.01 | K77: =+J77 -> 297.01 | L77: =+K77 -> 297.01 | M77: =+L77 -> 297.01 | N77: =+M77 -> 297.01 | O77: =+N77 -> 297.01 | P77: =+AVERAGE(D77:O77) -> 298.96583 | R77: =+FRIGARSA!H7 -> 47 | S77: =+R77*D77 -> 15062.56 | T77: =+FRIGARSA!M7 -> 47 | U77: =+T77*E77 -> 13959.47 | V77: =+FRIGARSA!R7 -> 47 | W77: =+V77*F77 -> 13959.47 | X77: =+FRIGARSA!W7 -> 47 | Y77: =+X77*G77 -> 13959.47 | Z77: =+FRIGARSA!AB7 -> 47 | AA77: =+Z77*N77 -> 13959.47
A78: 804109 | B78: AVIKO SHOESTRING 5x2500g | C78: 424.92 | D78: =+C78 -> 424.92 | E78: =+E54 -> 361.2 | F78: =+F54 -> 370.16 | G78: =+F78 -> 370.16 | H78: =+G78 -> 370.16 | I78: =+H78 -> 370.16 | J78: =+I78 -> 370.16 | K78: =+J78 -> 370.16 | L78: =+K78 -> 370.16 | M78: =+L78 -> 370.16 | N78: =+M78 -> 370.16 | O78: =+N78 -> 370.16 | P78: =+AVERAGE(D78:O78) -> 373.97667 | R78: =+FRIGARSA!H8 -> 67.5 | S78: =+R78*D78 -> 28682.1 | T78: =+FRIGARSA!M8 -> 6.5 | U78: =+T78*E78 -> 2347.8 | V78: =+FRIGARSA!R8 -> 6.5 | W78: =+V78*F78 -> 2406.04 | X78: =+FRIGARSA!W8 -> 6.5 | Y78: =+X78*G78 -> 2406.04 | Z78: =+FRIGARSA!AB8 -> 6.5 | AA78: =+Z78*N78 -> 2406.04
A79: 806980 | B79: AVIKO SPICY JACKET WEDGES 4x2500g | C79: 371.47 | D79: =+C79 -> 371.47 | E79: =+E55 -> 314.14 | F79: =+F55 -> 314.14 | G79: =+F79 -> 314.14 | H79: =+G79 -> 314.14 | I79: =+H79 -> 314.14 | J79: =+I79 -> 314.14 | K79: =+J79 -> 314.14 | L79: =+K79 -> 314.14 | M79: =+L79 -> 314.14 | N79: =+M79 -> 314.14 | O79: =+N79 -> 314.14 | P79: =+AVERAGE(D79:O79) -> 318.9175 | R79: =+FRIGARSA!H9 -> 69 | S79: =+R79*D79 -> 25631.43 | T79: =+FRIGARSA!M9 -> 9 | U79: =+T79*E79 -> 2827.26 | V79: =+FRIGARSA!R9 -> 2 | W79: =+V79*F79 -> 628.28 | X79: =+FRIGARSA!W9 -> 2 | Y79: =+X79*G79 -> 628.28 | Z79: =+FRIGARSA!AB9 -> 2 | AA79: =+Z79*N79 -> 628.28
A80: 806982 | B80: AROS DE CEBOLLA 1X1000g | C80: 346.77 | D80: =+C80 -> 346.77 | E80: =+E56 -> 346.77 | F80: =+F56 -> 337.55 | G80: =+F80 -> 337.55 | H80: =+G80 -> 337.55 | I80: =+H80 -> 337.55 | J80: =+I80 -> 337.55 | K80: =+J80 -> 337.55 | L80: =+K80 -> 337.55 | M80: =+L80 -> 337.55 | N80: =+M80 -> 337.55 | O80: =+N80 -> 337.55 | P80: =+AVERAGE(D80:O80) -> 339.08667 | R80: =+FRIGARSA!H10 -> 95 | S80: =+R80*D80 -> 32943.15 | T80: =+FRIGARSA!M10 -> 45 | U80: =+T80*E80 -> 15604.65 | V80: =+FRIGARSA!R10 -> 37 | W80: =+V80*F80 -> 12489.35 | X80: =+FRIGARSA!W10 -> 37 | Y80: =+X80*G80 -> 12489.35 | Z80: =+FRIGARSA!AB10 -> 37 | AA80: =+Z80*N80 -> 12489.35
A81: 260612 | B81: CASTEL STRAIGHT CUT FRIES 4X2500g | C81: 298.86 | D81: =+C81 -> 298.86 | E81: =+E57 -> 298.86 | F81: =+F57 -> 298.86 | G81: =+F81 -> 298.86 | H81: =+G81 -> 298.86 | I81: =+H81 -> 298.86 | J81: =+I81 -> 298.86 | K81: =+J81 -> 298.86 | L81: =+K81 -> 298.86 | M81: =+L81 -> 298.86 | N81: =+M81 -> 298.86 | O81: =+N81 -> 298.86 | P81: =+AVERAGE(D81:O81) -> 298.86 | R81: =+FRIGARSA!H11 -> 67 | S81: =+R81*D81 -> 20023.62 | T81: =+FRIGARSA!M11 -> 4 | U81: =+T81*E81 -> 1195.44 | V81: =+FRIGARSA!R11 -> 4 | W81: =+V81*F81 -> 1195.44 | X81: =+FRIGARSA!W11 -> 4 | Y81: =+X81*G81 -> 1195.44 | Z81: =+FRIGARSA!AB11 -> 4 | AA81: =+Z81*N81 -> 1195.44
A82: 804661 | B82: AVIKO STEAK FRIES 4X2500G 4X5.5 LBS | C82: 329.94 | D82: =+C82 -> 329.94 | E82: =+E58 -> 329.94 | F82: =+F58 -> 329.94 | G82: =+F82 -> 329.94 | H82: =+G82 -> 329.94 | I82: =+H82 -> 329.94 | J82: =+I82 -> 329.94 | K82: =+J82 -> 329.94 | L82: =+K82 -> 329.94 | M82: =+L82 -> 329.94 | N82: =+M82 -> 329.94 | O82: =+N82 -> 329.94 | P82: =+AVERAGE(D82:O82) -> 329.94 | R82: =+FRIGARSA!H12 -> 613 | S82: =+R82*D82 -> 202253.22 | T82: =+FRIGARSA!M12 -> 583 | U82: =+T82*E82 -> 192355.02 | V82: =+FRIGARSA!R12 -> 550 | W82: =+V82*F82 -> 181467 | X82: =+FRIGARSA!W12 -> 530 | Y82: =+X82*G82 -> 174868.2 | Z82: =+FRIGARSA!AB12 -> 510 | AA82: =+Z82*N82 -> 168269.4
A83: 806702 | B83: AVIKO H SUPER CRUNCH 15mm 6x2500g | C83: 554.39 | D83: =+D59 -> 432.95 | E83: =+E59 -> 432.95 | F83: =+F59 -> 432.95 | G83: =+F83 -> 432.95 | H83: =+G83 -> 432.95 | I83: =+H83 -> 432.95 | J83: =+I83 -> 432.95 | K83: =+J83 -> 432.95 | L83: =+K83 -> 432.95 | M83: =+L83 -> 432.95 | N83: =+M83 -> 432.95 | O83: =+N83 -> 432.95 | P83: =+AVERAGE(D83:O83) -> 432.95 | R83: =+FRIGARSA!H13 -> 216 | S83: =+R83*D83 -> 93517.2 | T83: =+FRIGARSA!M13 -> 162 | U83: =+T83*E83 -> 70137.9 | V83: =+FRIGARSA!R13 -> 105 | W83: =+V83*F83 -> 45459.75 | X83: =+FRIGARSA!W13 -> 87 | Y83: =+X83*G83 -> 37666.65 | Z83: =+FRIGARSA!AB13 -> 87 | AA83: =+Z83*N83 -> 37666.65
A84: 807769 | B84: PAPAS FRITAS CORTE REG 10 X 1000G | C84: 346.43 | D84: =+C84 -> 346.43 | E84: =+E60 -> 346.43 | F84: =+F60 -> 346.43 | G84: =+F84 -> 346.43 | H84: =+G84 -> 346.43 | I84: =+H84 -> 346.43 | J84: =+I84 -> 346.43 | K84: =+J84 -> 346.43 | L84: =+K84 -> 346.43 | M84: =+L84 -> 346.43 | N84: =+M84 -> 346.43 | O84: =+N84 -> 346.43 | P84: =+AVERAGE(D84:O84) -> 346.43 | R84: =+FRIGARSA!H14 -> 229 | S84: =+R84*D84 -> 79332.47 | T84: =+FRIGARSA!M14 -> 227 | U84: =+T84*E84 -> 78639.61 | V84: =+FRIGARSA!R14 -> 221 | W84: =+V84*F84 -> 76561.03 | X84: =+FRIGARSA!W14 -> 219 | Y84: =+X84*G84 -> 75868.17 | Z84: =+FRIGARSA!AB14 -> 219 | AA84: =+Z84*N84 -> 75868.17
A85: 807329 | B85: AVIKO ORIGINAL 20X450G | C85: 356.34 | D85: =+C85 -> 356.34 | E85: =+E61 -> 356.34 | F85: =+F61 -> 356.34 | G85: =+F85 -> 356.34 | H85: =+G85 -> 356.34 | I85: =+H85 -> 356.34 | J85: =+I85 -> 356.34 | K85: =+J85 -> 356.34 | L85: =+K85 -> 356.34 | M85: =+L85 -> 356.34 | N85: =+M85 -> 356.34 | O85: =+N85 -> 356.34 | P85: =+AVERAGE(D85:O85) -> 356.34 | R85: =+FRIGARSA!H15 -> 0 | S85: =+R85*D85 -> 0 | T85: =+FRIGARSA!M15 -> 0 | U85: =+T85*E85 -> 0 | V85: =+FRIGARSA!R15 -> 0 | W85: =+V85*F85 -> 0 | X85: =+FRIGARSA!W15 -> 0 | Y85: =+X85*G85 -> 0 | Z85: =+FRIGARSA!AB15 -> 0 | AA85: =+Z85*N85 -> 0
A86: 805411 | B86: PAPAS FRITAS ZIGZAG 12/750GRS | C86: 340.91 | D86: =+C86 -> 340.91 | E86: =+E62 -> 306.5 | F86: =+F62 -> 306.5 | G86: =+F86 -> 306.5 | H86: =+G86 -> 306.5 | I86: =+H86 -> 306.5 | J86: =+I86 -> 306.5 | K86: =+J86 -> 306.5 | L86: =+K86 -> 306.5 | M86: =+L86 -> 306.5 | N86: =+M86 -> 306.5 | O86: =+N86 -> 306.5 | P86: =+AVERAGE(D86:O86) -> 309.3675 | R86: =+FRIGARSA!H16 -> 0 | S86: =+R86*D86 -> 0 | T86: =+FRIGARSA!M16 -> 0 | U86: =+T86*E86 -> 0 | V86: =+FRIGARSA!R16 -> 0 | W86: =+V86*F86 -> 0 | X86: =+FRIGARSA!W16 -> 0 | Y86: =+X86*G86 -> 0 | Z86: =+FRIGARSA!AB16 -> 0 | AA86: =+Z86*N86 -> 0
A87: 807679 | B87: AVIKO SPICY WEDGES 20X500G | C87: 388.31 | D87: =+C87 -> 388.31 | E87: =+E63 -> 363.68 | F87: =+F63 -> 386.98 | G87: =+F87 -> 386.98 | H87: =+G87 -> 386.98 | I87: =+H87 -> 386.98 | J87: =+I87 -> 386.98 | K87: =+J87 -> 386.98 | L87: =+K87 -> 386.98 | M87: =+L87 -> 386.98 | N87: =+M87 -> 386.98 | O87: =+N87 -> 386.98 | P87: =+AVERAGE(D87:O87) -> 385.14917 | R87: =+FRIGARSA!H17 -> 0 | S87: =+R87*D87 -> 0 | T87: =+FRIGARSA!M17 -> 0 | U87: =+T87*E87 -> 0 | V87: =+FRIGARSA!R17 -> 0 | W87: =+V87*F87 -> 0 | X87: =+FRIGARSA!W17 -> 0 | Y87: =+X87*G87 -> 0 | Z87: =+FRIGARSA!AB17 -> 0 | AA87: =+Z87*N87 -> 0
A88: 805168 | B88: AVIKO AROS DE CEBOLLA PREFRITOS 25/400g | C88: 608.68 | D88: =+C88 -> 608.68 | E88: =+E64 -> 608.68 | F88: =+F64 -> 608.68 | G88: =+F88 -> 608.68 | H88: =+G88 -> 608.68 | I88: =+H88 -> 608.68 | J88: =+I88 -> 608.68 | K88: =+J88 -> 608.68 | L88: =+K88 -> 608.68 | M88: =+L88 -> 608.68 | N88: =+M88 -> 608.68 | O88: =+N88 -> 608.68 | P88: =+AVERAGE(D88:O88) -> 608.68 | R88: =+FRIGARSA!H18 -> 0 | S88: =+R88*D88 -> 0 | T88: =+FRIGARSA!M18 -> 0 | U88: =+T88*E88 -> 0 | V88: =+FRIGARSA!R18 -> 0 | W88: =+V88*F88 -> 0 | X88: =+FRIGARSA!W18 -> 0 | Y88: =+X88*G88 -> 0 | Z88: =+FRIGARSA!AB18 -> 0 | AA88: =+Z88*N88 -> 0
A89: 807363 | B89: Aviko H Super Crunch 14x600g | C89: 357.28 | D89: =+C89 -> 357.28 | E89: =+E65 -> 357.28 | F89: =+F65 -> 357.28 | G89: =+F89 -> 357.28 | H89: =+G89 -> 357.28 | I89: =+H89 -> 357.28 | J89: =+I89 -> 357.28 | K89: =+J89 -> 357.28 | L89: =+K89 -> 357.28 | M89: =+L89 -> 357.28 | N89: =+M89 -> 357.28 | O89: =+N89 -> 357.28 | P89: =+AVERAGE(D89:O89) -> 357.28 | R89: =+FRIGARSA!H19 -> 0 | S89: =+R89*D89 -> 0 | T89: =+FRIGARSA!M19 -> 0 | U89: =+T89*E89 -> 0 | V89: =+FRIGARSA!R19 -> 0 | W89: =+V89*F89 -> 0 | X89: =+FRIGARSA!W19 -> 0 | Y89: =+X89*G89 -> 0 | Z89: =+FRIGARSA!AB19 -> 0 | AA89: =+Z89*N89 -> 0
A90: 809529 | B90: Aviko SC Airfr. PommesFrites 10x750 | C90: 353.79 | D90: =+C90 -> 353.79 | E90: =+E66 -> 353.79 | F90: =+F66 -> 353.79 | G90: =+F90 -> 353.79 | H90: =+G90 -> 353.79 | I90: =+H90 -> 353.79 | J90: =+I90 -> 353.79 | K90: =+J90 -> 353.79 | L90: =+K90 -> 353.79 | M90: =+L90 -> 353.79 | N90: =+M90 -> 353.79 | O90: =+N90 -> 353.79 | P90: =+AVERAGE(D90:O90) -> 353.79 | R90: =+FRIGARSA!H20 -> 0 | S90: =+R90*D90 -> 0 | T90: =+FRIGARSA!M20 -> 0 | U90: =+T90*E90 -> 0 | V90: =+FRIGARSA!R20 -> 0 | W90: =+V90*F90 -> 0 | X90: =+FRIGARSA!W20 -> 0 | Y90: =+X90*G90 -> 0 | Z90: =+FRIGARSA!AB20 -> 0 | AA90: =+Z90*N90 -> 0
D91: =+C91 -> 0 | E91: =+E67 -> 0 | F91: =+F67 -> 0 | G91: =+F91 -> 0 | H91: =+G91 -> 0 | I91: =+H91 -> 0 | J91: =+I91 -> 0 | K91: =+J91 -> 0 | L91: =+K91 -> 0 | M91: =+L91 -> 0 | N91: =+M91 -> 0 | O91: =+N91 -> 0 | P91: =+AVERAGE(D91:O91) -> 0
D92: =+C92 -> 0 | E92: =+E68 -> 0 | F92: =+F68 -> 0 | G92: =+F92 -> 0 | H92: =+G92 -> 0 | I92: =+H92 -> 0 | J92: =+I92 -> 0 | K92: =+J92 -> 0 | L92: =+K92 -> 0 | M92: =+L92 -> 0 | N92: =+M92 -> 0 | O92: =+N92 -> 0 | P92: =+AVERAGE(D92:O92) -> 0
D93: =+C93 -> 0 | E93: =+E69 -> 0 | F93: =+F69 -> 0 | G93: =+F93 -> 0 | H93: =+G93 -> 0 | I93: =+H93 -> 0 | J93: =+I93 -> 0 | K93: =+J93 -> 0 | L93: =+K93 -> 0 | M93: =+L93 -> 0 | N93: =+M93 -> 0 | O93: =+N93 -> 0 | P93: =+AVERAGE(D93:O93) -> 0
A94: TOTAL FRIGARSA | R94: =+SUM(R73:R93) -> 2880.8 | S94: =+SUM(S73:S93) -> 950352.55 | T94: =+SUM(T73:T93) -> 1800.8 | U94: =+SUM(U73:U93) -> 591399.77 | V94: =+SUM(V73:V93) -> 1015.8 | W94: =+SUM(W73:W93) -> 348215.51 | X94: =+SUM(X73:X93) -> 950.8 | Y94: =+SUM(Y73:Y93) -> 325175.75 | ... AA94: =+SUM(AA73:AA93) -> 318576.95
A96: ALMACEN FRIJALISCO
A97: 105632 | B97: 10 MM NATURAL | C97: 281.47 | D97: =+C97 -> 281.47 | E97: =+D97 -> 281.47 | F97: =+E97 -> 281.47 | G97: =+F97 -> 281.47 | H97: =+G97 -> 281.47 | I97: =+H97 -> 281.47 | J97: =+I97 -> 281.47 | K97: =+J97 -> 281.47 | ... O97: =+N97 -> 281.47 | P97: =+AVERAGE(D97:O97) -> 281.47 | R97: =+FRIJALISCO!K4 -> 43 | S97: =+R97*D97 -> 12103.21 | T97: =+FRIJALISCO!P4 -> 0 | U97: =+T97*E97 -> 0 | V97: =+FRIJALISCO!U4 -> 3 | W97: =+V97*F97 -> 844.41 | X97: =+FRIJALISCO!Z4 -> 147 | Y97: =+X97*G97 -> 41376.09 | Z97: =+FRIJALISCO!AE4 -> 1755 | AA97: =+Z97*H97 -> 493979.85
A98: 102341 | B98: 10 MM CON COBERTURA | C98: 277.21 | D98: =+C98 -> 277.21 | E98: =+D98 -> 277.21 | F98: 301.54 | G98: =+F98 -> 301.54 | H98: =+G98 -> 301.54 | I98: =+H98 -> 301.54 | J98: =+I98 -> 301.54 | K98: =+J98 -> 301.54 | L98: =+K98 -> 301.54 | M98: =+L98 -> 301.54 | N98: =+M98 -> 301.54 | O98: =+N98 -> 301.54 | P98: =+AVERAGE(D98:O98) -> 297.485 | R98: =+FRIJALISCO!K5 -> 473 | S98: =+R98*D98 -> 131120.33 | T98: =+FRIJALISCO!P5 -> 128 | U98: =+T98*E98 -> 35482.88 | V98: =+FRIJALISCO!U5 -> 23 | W98: =+V98*F98 -> 6935.42 | X98: =+FRIJALISCO!Z5 -> 35 | Y98: =+X98*G98 -> 10553.9 | Z98: =+FRIJALISCO!AE5 -> 465 | AA98: =+Z98*H98 -> 140216.1
A99: 102310 | B99: 7 MM CON COBERTURA | C99: 363.33 | D99: =+C99 -> 363.33 | E99: =+D99 -> 363.33 | F99: 309.39 | G99: =+F99 -> 309.39 | H99: =+G99 -> 309.39 | I99: =+H99 -> 309.39 | J99: =+I99 -> 309.39 | K99: =+J99 -> 309.39 | L99: =+K99 -> 309.39 | M99: =+L99 -> 309.39 | N99: =+M99 -> 309.39 | O99: =+N99 -> 309.39 | P99: =+AVERAGE(D99:O99) -> 318.38 | R99: =+FRIJALISCO!K6 -> 45 | S99: =+R99*D99 -> 16349.85 | T99: =+FRIJALISCO!P6 -> 0 | U99: =+T99*E99 -> 0 | V99: =+FRIJALISCO!U6 -> 395 | W99: =+V99*F99 -> 122209.05 | X99: =+FRIJALISCO!Z6 -> 165 | Y99: =+X99*G99 -> 51049.35 | Z99: =+FRIJALISCO!AE6 -> 99 | AA99: =+Z99*H99 -> 30629.61
A100: 102211 | B100: 7 MM NATURAL | C100: 297.89 | D100: =+C100 -> 297.89 | E100: =+D100 -> 297.89 | F100: 261.42 | G100: =+F100 -> 261.42 | H100: =+G100 -> 261.42 | I100: =+H100 -> 261.42 | J100: =+I100 -> 261.42 | K100: =+J100 -> 261.42 | L100: =+K100 -> 261.42 | M100: =+L100 -> 261.42 | N100: =+M100 -> 261.42 | O100: =+N100 -> 261.42 | P100: =+AVERAGE(D100:O100) -> 267.49833 | R100: =+FRIJALISCO!K7 -> 2 | S100: =+R100*D100 -> 595.78 | T100: =+FRIJALISCO!P7 -> 1 | U100: =+T100*E100 -> 297.89 | V100: =+FRIJALISCO!U7 -> 676 | W100: =+V100*F100 -> 176719.92 | X100: =+FRIJALISCO!Z7 -> 502 | Y100: =+X100*G100 -> 131232.84 | Z100: =+FRIJALISCO!AE7 -> 466 | AA100: =+Z100*H100 -> 121821.72
A101: 104215 | B101: 10 MM CON COBERTURA Y CASCARA | C101: 357.86 | D101: =+C101 -> 357.86 | E101: =+D101 -> 357.86 | F101: =+E101 -> 357.86 | G101: =+F101 -> 357.86 | H101: =+G101 -> 357.86 | I101: =+H101 -> 357.86 | J101: =+I101 -> 357.86 | K101: =+J101 -> 357.86 | ... O101: =+N101 -> 357.86 | P101: =+AVERAGE(D101:O101) -> 357.86 | R101: =+FRIJALISCO!K8 -> 368 | S101: =+R101*D101 -> 131692.48 | T101: =+FRIJALISCO!P8 -> 264 | U101: =+T101*E101 -> 94475.04 | V101: =+FRIJALISCO!U8 -> 118 | W101: =+V101*F101 -> 42227.48 | X101: =+FRIJALISCO!Z8 -> 0 | Y101: =+X101*G101 -> 0 | Z101: =+FRIJALISCO!AE8 -> 24 | AA101: =+Z101*H101 -> 8588.64
A102: 114054 | B102: GAJOS SAZONADOS | C102: 359.94 | D102: =+C102 -> 359.94 | E102: =+D102 -> 359.94 | F102: 330.25 | G102: =+F102 -> 330.25 | H102: =+G102 -> 330.25 | I102: =+H102 -> 330.25 | J102: =+I102 -> 330.25 | K102: =+J102 -> 330.25 | L102: =+K102 -> 330.25 | M102: =+L102 -> 330.25 | N102: =+M102 -> 330.25 | O102: =+N102 -> 330.25 | P102: =+AVERAGE(D102:O102) -> 335.19833 | R102: =+FRIJALISCO!K9 -> 427 | S102: =+R102*D102 -> 153694.38 | T102: =+FRIJALISCO!P9 -> 46 | U102: =+T102*E102 -> 16557.24 | V102: =+FRIJALISCO!U9 -> 521 | W102: =+V102*F102 -> 172060.25 | X102: =+FRIJALISCO!Z9 -> 530 | Y102: =+X102*G102 -> 175032.5 | Z102: =+FRIJALISCO!AE9 -> 461 | AA102: =+Z102*H102 -> 152245.25
A103: 102419 | B103: ONDULADA | C103: 293.8 | D103: =+C103 -> 293.8 | E103: =+D103 -> 293.8 | F103: 257.25 | G103: =+F103 -> 257.25 | H103: =+G103 -> 257.25 | I103: =+H103 -> 257.25 | J103: =+I103 -> 257.25 | K103: =+J103 -> 257.25 | L103: =+K103 -> 257.25 | M103: =+L103 -> 257.25 | N103: =+M103 -> 257.25 | O103: =+N103 -> 257.25 | P103: =+AVERAGE(D103:O103) -> 263.34167 | R103: =+FRIJALISCO!K10 -> 6 | S103: =+R103*D103 -> 1762.8 | T103: =+FRIJALISCO!P10 -> 0 | U103: =+T103*E103 -> 0 | V103: =+FRIJALISCO!U10 -> 425 | W103: =+V103*F103 -> 109331.25 | X103: =+FRIJALISCO!Z10 -> 357 | Y103: =+X103*G103 -> 91838.25 | Z103: =+FRIJALISCO!AE10 -> 337 | AA103: =+Z103*H103 -> 86693.25
A104: 505015 | B104: 10 MM NATURAL-KAIDA | D104: =+C104 -> 0 | E104: 256.35 | F104: =+E104 -> 256.35 | G104: =+F104 -> 256.35 | H104: =+G104 -> 256.35 | I104: =+H104 -> 256.35 | J104: =+I104 -> 256.35 | K104: =+J104 -> 256.35 | L104: =+K104 -> 256.35 | M104: =+L104 -> 256.35 | ... O104: =+N104 -> 256.35 | P104: =+AVERAGE(D104:O104) -> 234.9875 | S104: =+R104*D104 -> 0 | T104: =+FRIJALISCO!P25 -> 1955 | U104: =+T104*E104 -> 501164.25 | V104: =+FRIJALISCO!U25 -> 1700 | W104: =+V104*F104 -> 435795 | X104: =+FRIJALISCO!Z25 -> 2848 | Y104: =+X104*G104 -> 730084.8 | Z104: =+FRIJALISCO!AE25 -> 3636 | AA104: =+Z104*H104 -> 932088.6
A105: 102013 | B105: 10 MM NATURAL | D105: =+C105 -> 0 | E105: 281.47 | F105: 253.12 | G105: =+F105 -> 253.12 | H105: =+G105 -> 253.12 | I105: =+H105 -> 253.12 | J105: =+I105 -> 253.12 | K105: =+J105 -> 253.12 | L105: =+K105 -> 253.12 | M105: =+L105 -> 253.12 | N105: =+M105 -> 253.12 | O105: =+N105 -> 253.12 | P105: =+AVERAGE(D105:O105) -> 234.38917 | R105: 0 | S105: =+R105*D105 -> 0 | Z105: =+FRIJALISCO!AE11+FRIJALISCO!AE12+FRIJALISCO!AE13 -> 108 | AA105: =+Z105*H105 -> 27336.96
...

Sheet Resumen Ventas
A1: VENTAS x ALMACÉN | D1: DICIEMBRE | E1: ENERO | F1: FEBRERO | G1: MARZO | H1: ABRIL | I1: MAYO | J1: JUNIO | K1: JULIO | M1: PROMEDIO | O1: %
A2: ABASTOS LOGICOS | B2: CÓDIGO | C2: DESCRIPCIÓN | I2: =+CANCÚN!#REF! -> #REF! | J2: =+CANCÚN!#REF! -> #REF! | K2: =+CANCÚN!#REF! -> #REF!
B3: 802142 | C3: STRAIGHT CUT 3/8 4X2500 | D3: 0.75 | E3: =+CANCÚN!#REF! -> #REF! | F3: =+CANCÚN!#REF! -> #REF! | G3: =+CANCÚN!#REF! -> #REF! | H3: =+CANCÚN!#REF! -> #REF! | I3: =+CANCÚN!#REF! -> #REF! | J3: =+CANCÚN!#REF! -> #REF! | K3: =+CANCÚN!#REF! -> #REF! | M3: =+AVERAGE(J3,I3,K3) -> #REF! | O3: =+M3/$M$24 -> #REF!
B4: 806686 | C4: H PREMIUM CRUNCH 9.5MM 3/8 4X2500G | E4: =+CANCÚN!#REF! -> #REF! | F4: =+CANCÚN!#REF! -> #REF! | G4: =+CANCÚN!#REF! -> #REF! | H4: =+CANCÚN!#REF! -> #REF! | I4: =+CANCÚN!#REF! -> #REF! | J4: =+CANCÚN!#REF! -> #REF! | K4: =+CANCÚN!#REF! -> #REF! | M4: =+AVERAGE(J4,I4,K4) -> #REF! | O4: =+M4/$M$24 -> #REF!
B5: 806980 | C5: SPICY JACKET WEDGES 4X2500G | E5: =+CANCÚN!#REF! -> #REF! | F5: =+CANCÚN!#REF! -> #REF! | G5: =+CANCÚN!#REF! -> #REF! | H5: =+CANCÚN!#REF! -> #REF! | I5: =+CANCÚN!#REF! -> #REF! | J5: =+CANCÚN!#REF! -> #REF! | K5: =+CANCÚN!#REF! -> #REF! | M5: =+AVERAGE(J5,I5,K5) -> #REF! | O5: =+M5/$M$24 -> #REF!
B6: 804104 | C6: TRIANGLE HASHBROW 63G/40PZ BAG APPROX) 4 X 2.5KG | D6: 147 | E6: =+CANCÚN!J3 -> 56.25 | F6: =+CANCÚN!#REF! -> #REF! | G6: =+CANCÚN!#REF! -> #REF! | H6: =+CANCÚN!#REF! -> #REF! | I6: =+CANCÚN!#REF! -> #REF! | J6: =+CANCÚN!#REF! -> #REF! | K6: =+CANCÚN!#REF! -> #REF! | M6: =+AVERAGE(J6,I6,K6) -> #REF! | O6: =+M6/$M$24 -> #REF!
B7: 805567 | C7: HASBROWNS ROUNDS - FRYER 4X2500G | D7: 1 | E7: =+CANCÚN!J4 -> 0 | F7: =+CANCÚN!#REF! -> #REF! | G7: =+CANCÚN!#REF! -> #REF! | H7: =+CANCÚN!#REF! -> #REF! | I7: =+CANCÚN!#REF! -> #REF! | J7: =+CANCÚN!#REF! -> #REF! | K7: =+CANCÚN!#REF! -> #REF! | M7: =+AVERAGE(J7,I7,K7) -> #REF! | O7: =+M7/$M$24 -> #REF!
B8: 806982 | C8: ONION RINGS BREADED EXTRUDED (60 PZ BAG APROXX) 6X1KG | D8: 20 | E8: =+CANCÚN!#REF! -> #REF! | F8: =+CANCÚN!#REF! -> #REF! | G8: =+CANCÚN!#REF! -> #REF! | H8: =+CANCÚN!#REF! -> #REF! | I8: =+CANCÚN!#REF! -> #REF! | J8: =+CANCÚN!#REF! -> #REF! | K8: =+CANCÚN!#REF! -> #REF! | M8: =+AVERAGE(J8,I8,K8) -> #REF! | O8: =+M8/$M$24 -> #REF!
B9: 803572 | C9: MEGA WEDGES (8CUT) SKIN ON 4X2.5 KG | E9: =+CANCÚN!#REF! -> #REF! | F9: =+CANCÚN!#REF! -> #REF! | G9: =+CANCÚN!#REF! -> #REF! | H9: =+CANCÚN!#REF! -> #REF! | I9: =+CANCÚN!#REF! -> #REF! | J9: =+CANCÚN!#REF! -> #REF! | K9: =+CANCÚN!#REF! -> #REF! | M9: =+AVERAGE(J9,I9,K9) -> #REF! | O9: =+M9/$M$24 -> #REF!
B10: 260612 | C10: CASTEL STRAIGHT CUT FRIES 4X2500G 9.5MM | D10: 2 | E10: =+CANCÚN!#REF! -> #REF! | F10: =+CANCÚN!#REF! -> #REF! | G10: =+CANCÚN!#REF! -> #REF! | H10: =+CANCÚN!#REF! -> #REF! | I10: =+CANCÚN!#REF! -> #REF! | J10: =+CANCÚN!#REF! -> #REF! | K10: =+CANCÚN!#REF! -> #REF! | M10: =+AVERAGE(J10,I10,K10) -> #REF! | O10: =+M10/$M$24 -> #REF!
B11: 803528 | C11: Aviko H Pommes Frites 11mm 7/16 4x2500g | E11: =+CANCÚN!J5 -> 0 | F11: =+CANCÚN!#REF! -> #REF! | G11: =+CANCÚN!#REF! -> #REF! | H11: =+CANCÚN!#REF! -> #REF! | I11: =+CANCÚN!#REF! -> #REF! | J11: =+CANCÚN!#REF! -> #REF! | K11: =+CANCÚN!#REF! -> #REF! | M11: =+AVERAGE(J11,I11,K11) -> #REF! | O11: =+M11/$M$24 -> #REF!
B12: 806685 | C12: AVIKO H PREM.CRUNCH SHOESTRING 7MM 4X2270G | D12: 37 | E12: =+CANCÚN!J6 -> 51 | F12: =+CANCÚN!#REF! -> #REF! | G12: =+CANCÚN!#REF! -> #REF! | H12: =+CANCÚN!#REF! -> #REF! | I12: =+CANCÚN!#REF! -> #REF! | J12: =+CANCÚN!#REF! -> #REF! | K12: =+CANCÚN!#REF! -> #REF! | M12: =+AVERAGE(J12,I12,K12) -> #REF! | O12: =+M12/$M$24 -> #REF!
B13: TOTAL AVIKO | D13: =+SUM(D3:D12) -> 207.75 | E13: =+SUM(E3:E12) -> #REF! | F13: =+SUM(F3:F12) -> #REF! | G13: =+SUM(G3:G12) -> #REF! | H13: =+SUM(H3:H12) -> #REF! | I13: =+SUM(I3:I12) -> #REF! | J13: =+SUM(J3:J12) -> #REF! | K13: =+SUM(K3:K12) -> #REF! | M13: =+SUM(M3:M12) -> #REF! | O13: =SUM(O3:O12) -> #REF!
B14: 102013 | C14: straight cut 10 mm 4/2500 | D14: 1754.5 | E14: =+CANCÚN!J13 -> 1083.25 | F14: =+CANCÚN!#REF! -> #REF! | G14: =+CANCÚN!#REF! -> #REF! | H14: =+CANCÚN!#REF! -> #REF! | I14: =+CANCÚN!#REF! -> #REF! | J14: =+CANCÚN!#REF! -> #REF! | K14: =+CANCÚN!#REF! -> #REF! | M14: =+AVERAGE(J14,I14,K14) -> #REF! | O14: =+M14/$M$24 -> #REF!
B15: 102211 | C15: straight cut 7 mm 4/2500 | E15: =+CANCÚN!#REF! -> #REF! | F15: =+CANCÚN!#REF! -> #REF! | G15: =+CANCÚN!#REF! -> #REF! | H15: =+CANCÚN!#REF! -> #REF! | I15: =+CANCÚN!#REF! -> #REF! | J15: =+CANCÚN!#REF! -> #REF! | K15: =+CANCÚN!#REF! -> #REF! | M15: =+AVERAGE(J15,I15,K15) -> #REF! | O15: =+M15/$M$24 -> #REF!
B16: 102341 | C16: Coated 10mm 4/2500 | D16: 275 | E16: =+CANCÚN!J15 -> 412.25 | F16: =+CANCÚN!#REF! -> #REF! | G16: =+CANCÚN!#REF! -> #REF! | H16: =+CANCÚN!#REF! -> #REF! | I16: =+CANCÚN!#REF! -> #REF! | J16: =+CANCÚN!#REF! -> #REF! | K16: =+CANCÚN!#REF! -> #REF! | M16: =+AVERAGE(J16,I16,K16) -> #REF! | O16: =+M16/$M$24 -> #REF!
B17: 102310 | C17: Coated Julienne 7 mm 4/2500 | E17: =+CANCÚN!J16 -> 25 | F17: =+CANCÚN!#REF! -> #REF! | G17: =+CANCÚN!#REF! -> #REF! | H17: =+CANCÚN!#REF! -> #REF! | I17: =+CANCÚN!#REF! -> #REF! | J17: =+CANCÚN!#REF! -> #REF! | K17: =+CANCÚN!#REF! -> #REF! | M17: =+AVERAGE(J17,I17,K17) -> #REF! | O17: =+M17/$M$24 -> #REF!
B18: 114054 | C18: Seasonned (spicy) wedges | D18: 35.75 | E18: =+CANCÚN!J17 -> 0 | F18: =+CANCÚN!#REF! -> #REF! | G18: =+CANCÚN!#REF! -> #REF! | H18: =+CANCÚN!#REF! -> #REF! | I18: =+CANCÚN!#REF! -> #REF! | J18: =+CANCÚN!#REF! -> #REF! | K18: =+CANCÚN!#REF! -> #REF! | M18: =+AVERAGE(J18,I18,K18) -> #REF! | O18: =+M18/$M$24 -> #REF!
B19: 111435 | C19: Hashbrown triangles 14x600 | E19: =+CANCÚN!#REF! -> #REF! | F19: =+CANCÚN!#REF! -> #REF! | G19: =+CANCÚN!#REF! -> #REF! | H19: =+CANCÚN!#REF! -> #REF! | I19: =+CANCÚN!#REF! -> #REF! | J19: =+CANCÚN!#REF! -> #REF! | K19: =+CANCÚN!#REF! -> #REF! | M19: =+AVERAGE(J19,I19,K19) -> #REF! | O19: =+M19/$M$24 -> #REF!
B20: 118700 | C20: Potato with cream cheese & herbs | E20: =+CANCÚN!#REF! -> #REF! | F20: =+CANCÚN!#REF! -> #REF! | G20: =+CANCÚN!#REF! -> #REF! | H20: =+CANCÚN!#REF! -> #REF! | I20: =+CANCÚN!#REF! -> #REF! | J20: =+CANCÚN!#REF! -> #REF! | K20: =+CANCÚN!#REF! -> #REF! | M20: =+AVERAGE(J20,I20,K20) -> #REF! | O20: =+M20/$M$24 -> #REF!
B21: 102419 | C21: CRINKLE CUT PREMIER GOLD 12MM 4X2.5KG | D21: 64 | E21: =+CANCÚN!J18 -> 0 | F21: =+CANCÚN!#REF! -> #REF! | G21: =+CANCÚN!#REF! -> #REF! | H21: =+CANCÚN!#REF! -> #REF! | I21: =+CANCÚN!#REF! -> #REF! | J21: =+CANCÚN!#REF! -> #REF! | K21: =+CANCÚN!#REF! -> #REF! | M21: =+AVERAGE(J21,I21,K21) -> #REF! | O21: =+M21/$M$24 -> #REF!
B22: 105632 | C22: straight cut 10 mm 4/2500 PRMOCIÓN | E22: =+CANCÚN!J19 -> 33 | F22: =+CANCÚN!#REF! -> #REF! | G22: =+CANCÚN!#REF! -> #REF! | H22: =+CANCÚN!#REF! -> #REF! | I22: =+CANCÚN!#REF! -> #REF! | J22: =+CANCÚN!#REF! -> #REF! | K22: =+CANCÚN!#REF! -> #REF! | M22: =+AVERAGE(J22,I22,K22) -> #REF! | O22: =+M22/$M$24 -> #REF!
B23: TOTAL WERNSING | D23: =+SUM(D14:D22) -> 2129.25 | E23: =+SUM(E14:E22) -> #REF! | F23: =+SUM(F14:F22) -> #REF! | G23: =+SUM(G14:G22) -> #REF! | H23: =+SUM(H14:H22) -> #REF! | I23: =+SUM(I14:I22) -> #REF! | J23: =+SUM(J14:J22) -> #REF! | K23: =+SUM(K14:K22) -> #REF! | M23: =+SUM(M14:M22) -> #REF! | O23: =SUM(O14:O22) -> #REF!
B24: TOTAL ABASTOS LOGICOS | D24: =+D23+D13 -> 2337 | E24: =+E23+E13 -> #REF! | F24: =+F23+F13 -> #REF! | G24: =+G23+G13 -> #REF! | H24: =+H23+H13 -> #REF! | I24: =+I23+I13 -> #REF! | J24: =+J23+J13 -> #REF! | K24: =+K23+K13 -> #REF! | M24: =+M23+M13 -> #REF! | O24: =+O23+O13 -> #REF!
A25: MEXIDELI | FRIGARSA | CANBELT | B25: CÓDIGO | C25: DESCRIPCIÓN
B26: 806685 | C26: AVIKO H PREM.CRUNCH SHOESTRING 7MM 4X2270G | D26: 1362 | E26: =+'RESUMEN CDMX'!#REF!+#REF! -> #REF! | F26: =+'RESUMEN CDMX'!#REF!+#REF! -> #REF! | G26: =+'RESUMEN CDMX'!#REF!+#REF! -> #REF! | H26: =+'RESUMEN CDMX'!#REF!+#REF! -> #REF! | I26: =+'RESUMEN CDMX'!#REF!+#REF! -> #REF! | J26: =+'RESUMEN CDMX'!#REF!+#REF! -> #REF! | K26: =+'RESUMEN CDMX'!#REF!+#REF! -> #REF! | M26: =+AVERAGE(J26,I26,K26) -> #REF! | O26: =+M26/$M$44 -> #REF!
B27: 806939 | C27: AVIKO CRINKLE CUT 12MM 4 X 2.5 KG | D27: 179 | E27: =+'RESUMEN CDMX'!#REF!+#REF!+#REF! -> #REF! | F27: =+'RESUMEN CDMX'!#REF!+#REF!+#REF! -> #REF! | G27: =+'RESUMEN CDMX'!#REF!+#REF!+#REF! -> #REF! | H27: =+'RESUMEN CDMX'!#REF!+#REF!+#REF! -> #REF! | I27: =+'RESUMEN CDMX'!#REF!+#REF!+#REF! -> #REF! | J27: =+'RESUMEN CDMX'!#REF!+#REF!+#REF! -> #REF! | K27: =+'RESUMEN CDMX'!#REF!+#REF!+#REF! -> #REF! | M27: =+AVERAGE(J27,I27,K27) -> #REF! | O27: =+M27/$M$44 -> #REF!
B28: 806694 | C28: AVIKO SUPER CRUNCH 9.5mm 3/8 4x2500g | E28: =+'RESUMEN CDMX'!#REF!+#REF! -> #REF! | F28: =+'RESUMEN CDMX'!#REF!+#REF! -> #REF! | G28: =+'RESUMEN CDMX'!#REF!+#REF! -> #REF! | H28: =+'RESUMEN CDMX'!#REF!+#REF! -> #REF! | I28: =+'RESUMEN CDMX'!#REF!+#REF! -> #REF! | J28: =+'RESUMEN CDMX'!#REF!+#REF! -> #REF! | K28: =+'RESUMEN CDMX'!#REF!+#REF! -> #REF! | M28: =+AVERAGE(J28,I28,K28) -> #REF! | O28: =+M28/$M$44 -> #REF!
B29: 802142 | C29: AVIKO STRAIGHT CUT 3/8 | E29: =+'RESUMEN CDMX'!#REF!+#REF! -> #REF! | F29: =+'RESUMEN CDMX'!#REF!+#REF! -> #REF! | G29: =+'RESUMEN CDMX'!#REF!+#REF! -> #REF! | H29: =+'RESUMEN CDMX'!#REF!+#REF! -> #REF! | I29: =+'RESUMEN CDMX'!#REF!+#REF! -> #REF! | J29: =+'RESUMEN CDMX'!#REF!+#REF! -> #REF! | K29: =+'RESUMEN CDMX'!#REF!+#REF! -> #REF! | M29: =+AVERAGE(J29,I29,K29) -> #REF! | O29: =+M29/$M$44 -> #REF!
B30: 804104 | C30: HASHBROWN TRIANGULOS | E30: =+'RESUMEN CDMX'!#REF!+#REF! -> #REF! | F30: =+'RESUMEN CDMX'!#REF!+#REF! -> #REF! | G30: =+'RESUMEN CDMX'!#REF!+#REF! -> #REF! | H30: =+'RESUMEN CDMX'!#REF!+#REF! -> #REF! | I30: =+'RESUMEN CDMX'!#REF!+#REF! -> #REF! | J30: =+'RESUMEN CDMX'!#REF!+#REF! -> #REF! | K30: =+'RESUMEN CDMX'!#REF!+#REF! -> #REF! | M30: =+AVERAGE(J30,I30,K30) -> #REF! | O30: =+M30/$M$44 -> #REF!
B31: 801754 | C31: AVIKO GRATINS MUSHROONS | E31: =+'RESUMEN CDMX'!#REF!+#REF! -> #REF! | F31: =+'RESUMEN CDMX'!#REF!+#REF! -> #REF! | G31: =+'RESUMEN CDMX'!#REF!+#REF! -> #REF! | H31: =+'RESUMEN CDMX'!#REF!+#REF! -> #REF! | I31: =+'RESUMEN CDMX'!#REF!+#REF! -> #REF! | J31: =+'RESUMEN CDMX'!#REF!+#REF! -> #REF! | K31: =+'RESUMEN CDMX'!#REF!+#REF! -> #REF! | M31: =+AVERAGE(J31,I31,K31) -> #REF! | O31: =+M31/$M$44 -> #REF!
B32: 807057 | C32: AVIKO MINI GRATINS | E32: =+'RESUMEN CDMX'!#REF!+#REF! -> #REF! | F32: =+'RESUMEN CDMX'!#REF!+#REF! -> #REF! | G32: =+'RESUMEN CDMX'!#REF!+#REF! -> #REF! | H32: =+'RESUMEN CDMX'!#REF!+#REF! -> #REF! | I32: =+'RESUMEN CDMX'!#REF!+#REF! -> #REF! | J32: =+'RESUMEN CDMX'!#REF!+#REF! -> #REF! | K32: =+'RESUMEN CDMX'!#REF!+#REF! -> #REF! | M32: =+AVERAGE(J32,I32,K32) -> #REF! | O32: =+M32/$M$44 -> #REF!
B33: 807677 | C33: AVIKO WAFFLE CUT 5X1500G | E33: =+'RESUMEN CDMX'!#REF!+#REF! -> #REF! | F33: =+'RESUMEN CDMX'!#REF!+#REF! -> #REF! | G33: =+'RESUMEN CDMX'!#REF!+#REF! -> #REF! | H33: =+'RESUMEN CDMX'!#REF!+#REF! -> #REF! | I33: =+'RESUMEN CDMX'!#REF!+#REF! -> #REF! | J33: =+'RESUMEN CDMX'!#REF!+#REF! -> #REF! | K33: =+'RESUMEN CDMX'!#REF!+#REF! -> #REF! | M33: =+AVERAGE(J33,I33,K33) -> #REF! | O33: =+M33/$M$44 -> #REF!
B34: 806686 | C34: AVIKO H PREM CRUNCH 9.5 mm 3/8 4x2270g | D34: 18 | E34: =+'RESUMEN CDMX'!#REF!+#REF! -> #REF! | F34: =+'RESUMEN CDMX'!#REF!+#REF! -> #REF! | G34: =+'RESUMEN CDMX'!#REF!+#REF! -> #REF! | H34: =+'RESUMEN CDMX'!#REF!+#REF! -> #REF! | I34: =+'RESUMEN CDMX'!#REF!+#REF! -> #REF! | J34: =+'RESUMEN CDMX'!#REF!+#REF! -> #REF! | K34: =+'RESUMEN CDMX'!#REF!+#REF! -> #REF! | M34: =+AVERAGE(J34,I34,K34) -> #REF! | O34: =+M34/$M$44 -> #REF!
B35: 804109 | C35: AVIKO SHOESTRING 5x2500g | D35: 35 | E35: =+'RESUMEN CDMX'!#REF!+#REF! -> #REF! | F35: =+'RESUMEN CDMX'!#REF!+#REF! -> #REF! | G35: =+'RESUMEN CDMX'!#REF!+#REF! -> #REF! | H35: =+'RESUMEN CDMX'!#REF!+#REF! -> #REF! | I35: =+'RESUMEN CDMX'!#REF!+#REF! -> #REF! | J35: =+'RESUMEN CDMX'!#REF!+#REF! -> #REF! | K35: =+'RESUMEN CDMX'!#REF!+#REF! -> #REF! | M35: =+AVERAGE(J35,I35,K35) -> #REF! | O35: =+M35/$M$44 -> #REF!
B36: 806982 | C36: AVIKO BREADED ONION RINGS 6x1000g | E36: =+'RESUMEN CDMX'!#REF!+#REF! -> #REF! | F36: =+'RESUMEN CDMX'!#REF!+#REF! -> #REF! | G36: =+'RESUMEN CDMX'!#REF!+#REF! -> #REF! | H36: =+'RESUMEN CDMX'!#REF!+#REF! -> #REF! | I36: =+'RESUMEN CDMX'!#REF!+#REF! -> #REF! | J36: =+'RESUMEN CDMX'!#REF!+#REF! -> #REF! | K36: =+'RESUMEN CDMX'!#REF!+#REF! -> #REF! | M36: =+AVERAGE(J36,I36,K36) -> #REF! | O36: =+M36/$M$44 -> #REF!
B37: 806980 | C37: AVIKO SPICY JACKET WEDGES 4x2500g | D37: 99 | E37: =+'RESUMEN CDMX'!#REF!+#REF! -> #REF! | F37: =+'RESUMEN CDMX'!#REF!+#REF! -> #REF! | G37: =+'RESUMEN CDMX'!#REF!+#REF! -> #REF! | H37: =+'RESUMEN CDMX'!#REF!+#REF! -> #REF! | I37: =+'RESUMEN CDMX'!#REF!+#REF! -> #REF! | J37: =+'RESUMEN CDMX'!#REF!+#REF! -> #REF! | K37: =+'RESUMEN CDMX'!#REF!+#REF! -> #REF! | M37: =+AVERAGE(J37,I37,K37) -> #REF! | O37: =+M37/$M$44 -> #REF!
B38: 807366 | C38: AVIKO STRAIGHT CHURROS 6x1000g | E38: =+'RESUMEN CDMX'!#REF!+#REF! -> #REF! | F38: =+'RESUMEN CDMX'!#REF!+#REF! -> #REF! | G38: =+'RESUMEN CDMX'!#REF!+#REF! -> #REF! | H38: =+'RESUMEN CDMX'!#REF!+#REF! -> #REF! | I38: =+'RESUMEN CDMX'!#REF!+#REF! -> #REF! | J38: =+'RESUMEN CDMX'!#REF!+#REF! -> #REF! | K38: =+'RESUMEN CDMX'!#REF!+#REF! -> #REF! | M38: =+AVERAGE(J38,I38,K38) -> #REF! | O38: =+M38/$M$44 -> #REF!
B39: 260612 | C39: CASTEL STRAIGHT CUT FRIES 4X2500g | D39: 755 | E39: =+'RESUMEN CDMX'!#REF!+#REF! -> #REF! | F39: =+'RESUMEN CDMX'!#REF!+#REF! -> #REF! | G39: =+'RESUMEN CDMX'!#REF!+#REF! -> #REF! | H39: =+'RESUMEN CDMX'!#REF!+#REF! -> #REF! | I39: =+'RESUMEN CDMX'!#REF!+#REF! -> #REF! | J39: =+'RESUMEN CDMX'!#REF!+#REF! -> #REF! | K39: =+'RESUMEN CDMX'!#REF!+#REF! -> #REF! | M39: =+AVERAGE(J39,I39,K39) -> #REF! | O39: =+M39/$M$44 -> #REF!
B40: 804661 | C40: AVIKO STEAK FRIES 4X2500G 4X5.5 LBS | D40: 167 | E40: =+'RESUMEN CDMX'!#REF!+#REF! -> #REF! | F40: =+'RESUMEN CDMX'!#REF!+#REF! -> #REF! | G40: =+'RESUMEN CDMX'!#REF!+#REF! -> #REF! | H40: =+'RESUMEN CDMX'!#REF!+#REF! -> #REF! | I40: =+'RESUMEN CDMX'!#REF!+#REF! -> #REF! | J40: =+'RESUMEN CDMX'!#REF!+#REF! -> #REF! | K40: =+'RESUMEN CDMX'!#REF!+#REF! -> #REF! | M40: =+AVERAGE(J40,I40,K40) -> #REF! | O40: =+M40/$M$44 -> #REF!
B41: 806702 | C41: AVIKO H SUPER CRUNCH 15mm 6x2500g | D41: 20 | E41: =+'RESUMEN CDMX'!#REF!+#REF! -> #REF! | F41: =+'RESUMEN CDMX'!#REF!+#REF! -> #REF! | G41: =+'RESUMEN CDMX'!#REF!+#REF! -> #REF! | H41: =+'RESUMEN CDMX'!#REF!+#REF! -> #REF! | I41: =+'RESUMEN CDMX'!#REF!+#REF! -> #REF! | J41: =+'RESUMEN CDMX'!#REF!+#REF! -> #REF! | K41: =+'RESUMEN CDMX'!#REF!+#REF! -> #REF! | M41: =+AVERAGE(J41,I41,K41) -> #REF! | O41: =+M41/$M$44 -> #REF!
B42: 805567 | C42: AVIKO ROSTIKO ROUNDS 4X2500 | E42: =+'RESUMEN CDMX'!#REF!+#REF! -> #REF! | F42: =+'RESUMEN CDMX'!#REF!+#REF! -> #REF! | G42: =+'RESUMEN CDMX'!#REF!+#REF! -> #REF! | H42: =+'RESUMEN CDMX'!#REF!+#REF! -> #REF! | I42: =+'RESUMEN CDMX'!#REF!+#REF! -> #REF! | J42: =+'RESUMEN CDMX'!#REF!+#REF! -> #REF! | K42: =+'RESUMEN CDMX'!#REF!+#REF! -> #REF! | M42: =+AVERAGE(J42,I42,K42) -> #REF! | O42: =+M42/$M$44 -> #REF!
B43: TOTAL AVIKO | D43: =+SUM(D26:D42) -> 2635 | E43: =+SUM(E26:E42) -> #REF! | F43: =+SUM(F26:F42) -> #REF! | G43: =+SUM(G26:G42) -> #REF! | H43: =+SUM(H26:H42) -> #REF! | I43: =+SUM(I26:I42) -> #REF! | J43: =+SUM(J26:J42) -> #REF! | K43: =+SUM(K26:K42) -> #REF! | M43: =+SUM(M26:M42) -> #REF!
B44: TOTAL CDMX | D44: =+D43 -> 2635 | E44: =+E43 -> #REF! | F44: =+F43 -> #REF! | G44: =+G43 -> #REF! | H44: =+H43 -> #REF! | I44: =+I43 -> #REF! | J44: =+J43 -> #REF! | K44: =+K43 -> #REF! | M44: =+M43 -> #REF! | O44: =SUM(O26:O43) -> #REF!
A45: FRESCO | B45: CÓDIGO | C45: DESCRIPCIÓN
B46: 807769 | C46: PAPAS FRITAS CORTE REG 10 X 1000G | D46: 44 | E46: =+#REF! -> #REF! | F46: =+#REF! -> #REF! | G46: =+#REF! -> #REF! | H46: =+#REF! -> #REF! | I46: =+#REF! -> #REF! | J46: =+#REF! -> #REF! | K46: =+#REF! -> #REF! | M46: =+AVERAGE(J46,I46,K46) -> #REF! | O46: =+M46/$M$56 -> #REF!
B47: 807329 | C47: AVIKO ORIGINAL 20X450G | D47: 60 | E47: =+#REF! -> #REF! | F47: =+#REF! -> #REF! | G47: =+#REF! -> #REF! | H47: =+#REF! -> #REF! | I47: =+#REF! -> #REF! | J47: =+#REF! -> #REF! | K47: =+#REF! -> #REF! | M47: =+AVERAGE(J47,I47,K47) -> #REF! | O47: =+M47/$M$56 -> #REF!
B48: 805411 | C48: PAPAS FRITAS ZIGZAG 12/750GRS | D48: 129 | E48: =+#REF! -> #REF! | F48: =+#REF! -> #REF! | G48: =+#REF! -> #REF! | H48: =+#REF! -> #REF! | I48: =+#REF! -> #REF! | J48: =+#REF! -> #REF! | K48: =+#REF! -> #REF! | M48: =+AVERAGE(J48,I48,K48) -> #REF! | O48: =+M48/$M$56 -> #REF!
B49: 807679 | C49: AVIKO SPICY WEDGES 20X500G | D49: 101 | E49: =+#REF! -> #REF! | F49: =+#REF! -> #REF! | G49: =+#REF! -> #REF! | H49: =+#REF! -> #REF! | I49: =+#REF! -> #REF! | J49: =+#REF! -> #REF! | K49: =+#REF! -> #REF! | M49: =+AVERAGE(J49,I49,K49) -> #REF! | O49: =+M49/$M$56 -> #REF!
B50: 805168 | C50: AVIKO AROS DE CEBOLLA PREFRITOS 25/400g | D50: 70 | E50: =+#REF! -> #REF! | F50: =+#REF! -> #REF! | G50: =+#REF! -> #REF! | H50: =+#REF! -> #REF! | I50: =+#REF! -> #REF! | J50: =+#REF! -> #REF! | K50: =+#REF! -> #REF! | M50: =+AVERAGE(J50,I50,K50) -> #REF! | O50: =+M50/$M$56 -> #REF!
B51: 807363 | C51: Aviko H Super Crunch 14x600g | E51: =+#REF! -> #REF! | F51: =+#REF! -> #REF! | G51: =+#REF! -> #REF! | H51: =+#REF! -> #REF! | I51: =+#REF! -> #REF! | J51: =+#REF! -> #REF! | K51: =+#REF! -> #REF! | M51: =+AVERAGE(J51,I51,K51) -> #REF! | O51: =+M51/$M$56 -> #REF!
B52: 809529 | C52: Aviko SC Airfr. PommesFrites 10x750
B53: 806698 | C53: AVIKO H SUPER CRUNCH 9-5 mmdkin on 4x2 boog
B54: 803566 | C54: AROS EMPANADOS DE CEBOLLA CON CERVEZA
B55: TOTAL AVIKO | D55: =+SUM(D46:D54) -> 404 | E55: =+SUM(E46:E54) -> #REF! | F55: =+SUM(F46:F54) -> #REF! | G55: =+SUM(G46:G54) -> #REF! | H55: =+SUM(H46:H54) -> #REF! | I55: =+SUM(I46:I54) -> #REF! | J55: =+SUM(J46:J54) -> #REF! | K55: =+SUM(K46:K54) -> #REF! | M55: =+SUM(M46:M54) -> #REF!
B56: TOTAL FRESCO | D56: =+D55 -> 404 | E56: =+E55 -> #REF! | F56: =+F55 -> #REF! | G56: =+G55 -> #REF! | H56: =+H55 -> #REF! | I56: =+I55 -> #REF! | J56: =+J55 -> #REF! | K56: =+K55 -> #REF! | M56: =+M55 -> #REF! | O56: =SUM(O46:O55) -> #REF!
A57: FRIJALISCO | B57: CÓDIGO | C57: DESCRIPCIÓN
B58: 102013 | C58: 10 MM STRAIGHT CUT 4x2.5kg | D58: 144 | E58: =+FRIJALISCO!#REF! -> #REF! | F58: =+FRIJALISCO!#REF! -> #REF! | G58: =+FRIJALISCO!#REF! -> #REF! | H58: =+FRIJALISCO!#REF! -> #REF! | I58: =+FRIJALISCO!#REF! -> #REF! | J58: =+FRIJALISCO!#REF! -> #REF! | K58: =+FRIJALISCO!#REF! -> #REF! | M58: =+AVERAGE(J58,I58,K58) -> #REF! | O58: =+M58/$M$73 -> #REF!
B59: 102341 | C59: 10 MM STRAIGHT CUT COATED 4x2.5kg | D59: 73 | E59: =+FRIJALISCO!#REF! -> #REF! | F59: =+FRIJALISCO!#REF! -> #REF! | G59: =+FRIJALISCO!#REF! -> #REF! | H59: =+FRIJALISCO!#REF! -> #REF! | I59: =+FRIJALISCO!#REF! -> #REF! | J59: =+FRIJALISCO!#REF! -> #REF! | K59: =+FRIJALISCO!#REF! -> #REF! | M59: =+AVERAGE(J59,I59,K59) -> #REF! | O59: =+M59/$M$73 -> #REF!
B60: 102310 | C60: FROZEN FRENCH FRIES 4X2.5KG 8X8MM COATED JULIENNE PREMIER GOLD | D60: 94 | E60: =+FRIJALISCO!#REF! -> #REF! | F60: =+FRIJALISCO!#REF! -> #REF! | G60: =+FRIJALISCO!#REF! -> #REF! | H60: =+FRIJALISCO!#REF! -> #REF! | I60: =+FRIJALISCO!#REF! -> #REF! | J60: =+FRIJALISCO!#REF! -> #REF! | K60: =+FRIJALISCO!#REF! -> #REF! | M60: =+AVERAGE(J60,I60,K60) -> #REF! | O60: =+M60/$M$73 -> #REF!
B61: 102211 | C61: FROZEN FRENCH FRIES 4X2.5KG 7.5X7.5MM JULIENNE PREMIER GOLD | D61: 182 | E61: =+FRIJALISCO!#REF! -> #REF! | F61: =+FRIJALISCO!#REF! -> #REF! | G61: =+FRIJALISCO!#REF! -> #REF! | H61: =+FRIJALISCO!#REF! -> #REF! | I61: =+FRIJALISCO!#REF! -> #REF! | J61: =+FRIJALISCO!#REF! -> #REF! | K61: =+FRIJALISCO!#REF! -> #REF! | M61: =+AVERAGE(J61,I61,K61) -> #REF! | O61: =+M61/$M$73 -> #REF!
B62: 104215 | C62: FROZEN FRENCH FRIES 4X2.5KG COATED 10MM SKIN-ON PREMIER GOLD | D62: 145 | E62: =+FRIJALISCO!#REF! -> #REF! | F62: =+FRIJALISCO!#REF! -> #REF! | G62: =+FRIJALISCO!#REF! -> #REF! | H62: =+FRIJALISCO!#REF! -> #REF! | I62: =+FRIJALISCO!#REF! -> #REF! | J62: =+FRIJALISCO!#REF! -> #REF! | K62: =+FRIJALISCO!#REF! -> #REF! | M62: =+AVERAGE(J62,I62,K62) -> #REF! | O62: =+M62/$M$73 -> #REF!
B63: 114054 | C63: Spicy wedges | D63: 231 | E63: =+FRIJALISCO!#REF! -> #REF! | F63: =+FRIJALISCO!#REF! -> #REF! | G63: =+FRIJALISCO!#REF! -> #REF! | H63: =+FRIJALISCO!#REF! -> #REF! | I63: =+FRIJALISCO!#REF! -> #REF! | J63: =+FRIJALISCO!#REF! -> #REF! | K63: =+FRIJALISCO!#REF! -> #REF! | M63: =+AVERAGE(J63,I63,K63) -> #REF! | O63: =+M63/$M$73 -> #REF!
B64: 102419 | C64: PREMIER GOLD CRINKLE 12MM 4X2.5KG | D64: 30 | E64: =+FRIJALISCO!#REF! -> #REF! | F64: =+FRIJALISCO!#REF! -> #REF! | G64: =+FRIJALISCO!#REF! -> #REF! | H64: =+FRIJALISCO!#REF! -> #REF! | I64: =+FRIJALISCO!#REF! -> #REF! | J64: =+FRIJALISCO!#REF! -> #REF! | K64: =+FRIJALISCO!#REF! -> #REF! | M64: =+AVERAGE(J64,I64,K64) -> #REF! | O64: =+M64/$M$73 -> #REF!
B65: 105632 | C65: 10 MM STRAIGHT CUT 4x2.5kg PROMOCIÓN | E65: =+FRIJALISCO!#REF! -> #REF! | F65: =+FRIJALISCO!#REF! -> #REF! | G65: =+FRIJALISCO!#REF! -> #REF! | H65: =+FRIJALISCO!#REF! -> #REF! | I65: =+FRIJALISCO!#REF! -> #REF! | J65: =+FRIJALISCO!#REF! -> #REF! | K65: =+FRIJALISCO!#REF! -> #REF! | M65: =+AVERAGE(J65,I65,K65) -> #REF! | O65: =+M65/$M$73 -> #REF!
B66: TOTAL WERNSING | D66: =+SUM(D58:D65) -> 899 | E66: =+SUM(E58:E65) -> #REF! | F66: =+SUM(F58:F65) -> #REF! | G66: =+SUM(G58:G65) -> #REF! | H66: =+SUM(H58:H65) -> #REF! | I66: =+SUM(I58:I65) -> #REF! | J66: =+SUM(J58:J65) -> #REF! | K66: =+SUM(K58:K65) -> #REF! | M66: =+SUM(M58:M65) -> #REF! | O66: =SUM(O58:O65) -> #REF!
B67: CÓDIGO | C67: DESCRIPCIÓN
B68: 260612 | C68: CASTEL STRAIGTH CUT FRIES 4x2500g | D68: 1501 | E68: =+FRIJALISCO!#REF! -> #REF! | F68: =+FRIJALISCO!#REF! -> #REF! | G68: =+FRIJALISCO!#REF! -> #REF! | H68: =+FRIJALISCO!#REF! -> #REF! | I68: =+FRIJALISCO!#REF! -> #REF! | J68: =+FRIJALISCO!#REF! -> #REF! | K68: =+FRIJALISCO!#REF! -> #REF! | M68: =+AVERAGE(J68,I68,K68) -> #REF! | O68: =+M68/$M$73 -> #REF!
B69: 803528 | C69: AVIKO H POMMES FRITES 11mm 7/16 4x2500g | E69: =+FRIJALISCO!#REF! -> #REF! | F69: =+FRIJALISCO!#REF! -> #REF! | H69: =+FRIJALISCO!#REF! -> #REF! | I69: =+FRIJALISCO!#REF! -> #REF! | J69: =+FRIJALISCO!#REF! -> #REF! | K69: =+FRIJALISCO!#REF! -> #REF! | M69: =+AVERAGE(J69,I69,K69) -> #REF! | O69: =+M69/$M$73 -> #REF!
B70: 806980 | C70: AVIKO SPICY JACKET WEDGES 4x2500g | D70: 146 | E70: =+FRIJALISCO!#REF! -> #REF! | F70: =+FRIJALISCO!#REF! -> #REF! | H70: =+FRIJALISCO!#REF! -> #REF! | I70: =+FRIJALISCO!#REF! -> #REF! | J70: =+FRIJALISCO!#REF! -> #REF! | K70: =+FRIJALISCO!#REF! -> #REF! | M70: =+AVERAGE(J70,I70,K70) -> #REF! | O70: =+M70/$M$73 -> #REF!
B71: 806918 | C71: AVIKO H SUPER LONG 9.5 MM SKIN ON 4x2500g | E71: =+FRIJALISCO!#REF! -> #REF! | F71: =+FRIJALISCO!#REF! -> #REF! | H71: =+FRIJALISCO!#REF! -> #REF! | I71: =+FRIJALISCO!#REF! -> #REF! | J71: =+FRIJALISCO!#REF! -> #REF! | K71: =+FRIJALISCO!#REF! -> #REF! | M71: =+AVERAGE(J71,I71,K71) -> #REF! | O71: =+M71/$M$73 -> #REF!
B72: TOTAL AVIKO | D72: {=+SUM(D68:D71)} -> 1647 | E72: {=+SUM(E68:E71)} -> #REF! | F72: {=+SUM(F68:F71)} -> #REF! | G72: {=+SUM(G68:G71)} -> #REF! | H72: {=+SUM(H68:H71)} -> #REF! | I72: {=+SUM(I68:I71)} -> #REF! | J72: {=+SUM(J68:J71)} -> #REF! | K72: {=+SUM(K68:K71)} -> #REF! | M72: {=+SUM(M68:M71)} -> #REF! | O72: =SUM(O68:O71) -> #REF!
B73: TOTAL FRIJALISCO | D73: =+D72+D66 -> 2546 | E73: =+E72+E66 -> #REF! | F73: =+F72+F66 -> #REF! | G73: =+G72+G66 -> #REF! | H73: =+H72+H66 -> #REF! | I73: =+I72+I66 -> #REF! | J73: =+J72+J66 -> #REF! | K73: =+K72+K66 -> #REF! | M73: =+M72+M66 -> #REF! | O73: =+O72+O66 -> #REF!
A74: LEÓN | B74: CÓDIGO | C74: DESCRIPCIÓN
B75: 807329 | C75: AVIKO ORIGINAL 20x450g | D75: 390 | E75: =+'VULPES PAPAS'!#REF! -> #REF! | F75: =+'VULPES PAPAS'!#REF! -> #REF! | G75: =+'VULPES PAPAS'!#REF! -> #REF! | H75: =+'VULPES PAPAS'!#REF! -> #REF! | I75: =+'VULPES PAPAS'!#REF! -> #REF! | J75: =+'VULPES PAPAS'!#REF! -> #REF! | K75: =+'VULPES PAPAS'!#REF! -> #REF! | M75: =+AVERAGE(J75,I75,K75) -> #REF! | O75: =+M75/$M$105 -> #REF!
B76: 807679 | C76: AVIKO SPICY JACKET WEDGES 20X500G | D76: 101 | E76: =+'VULPES PAPAS'!#REF! -> #REF! | F76: =+'VULPES PAPAS'!#REF! -> #REF! | G76: =+'VULPES PAPAS'!#REF! -> #REF! | H76: =+'VULPES PAPAS'!#REF! -> #REF! | I76: =+'VULPES PAPAS'!#REF! -> #REF! | J76: =+'VULPES PAPAS'!#REF! -> #REF! | K76: =+'VULPES PAPAS'!#REF! -> #REF! | M76: =+AVERAGE(J76,I76,K76) -> #REF! | O76: =+M76/$M$105 -> #REF!
B77: 807769 | C77: AVIKO PAPAS FRITAS CORTE RECTO 10x1000g | D77: 1213 | E77: =+'VULPES PAPAS'!#REF! -> #REF! | F77: =+'VULPES PAPAS'!#REF! -> #REF! | G77: =+'VULPES PAPAS'!#REF! -> #REF! | H77: =+'VULPES PAPAS'!#REF! -> #REF! | I77: =+'VULPES PAPAS'!#REF! -> #REF! | J77: =+'VULPES PAPAS'!#REF! -> #REF! | K77: =+'VULPES PAPAS'!#REF! -> #REF! | M77: =+AVERAGE(J77,I77,K77) -> #REF! | O77: =+M77/$M$105 -> #REF!
B78: 805411 | C78: PAPAS FRITAS ZIGZAG 12/750GRS | D78: 180 | E78: =+'VULPES PAPAS'!#REF! -> #REF! | F78: =+'VULPES PAPAS'!#REF! -> #REF! | G78: =+'VULPES PAPAS'!#REF! -> #REF! | H78: =+'VULPES PAPAS'!#REF! -> #REF! | I78: =+'VULPES PAPAS'!#REF! -> #REF! | J78: =+'VULPES PAPAS'!#REF! -> #REF! | K78: =+'VULPES PAPAS'!#REF! -> #REF! | M78: =+AVERAGE(J78,I78,K78) -> #REF! | O78: =+M78/$M$105 -> #REF!
B79: 806957 | C79: AVIKO ROSTI BITES | E79: =+'VULPES PAPAS'!#REF! -> #REF! | F79: =+'VULPES PAPAS'!#REF! -> #REF! | G79: =+'VULPES PAPAS'!#REF! -> #REF! | H79: =+'VULPES PAPAS'!#REF! -> #REF! | I79: =+'VULPES PAPAS'!#REF! -> #REF! | J79: =+'VULPES PAPAS'!#REF! -> #REF! | K79: =+'VULPES PAPAS'!#REF! -> #REF! | M79: =+AVERAGE(J79,I79,K79) -> #REF! | O79: =+M79/$M$105 -> #REF!
B80: 802142 | C80: AVIKO STRAIGHT CUT 3/8 4x2500g | D80: 5 | E80: =+'VULPES PAPAS'!#REF! -> #REF! | F80: =+'VULPES PAPAS'!#REF! -> #REF! | G80: =+'VULPES PAPAS'!#REF! -> #REF! | H80: =+'VULPES PAPAS'!#REF! -> #REF! | I80: =+'VULPES PAPAS'!#REF! -> #REF! | J80: =+'VULPES PAPAS'!#REF! -> #REF! | K80: =+'VULPES PAPAS'!#REF! -> #REF! | M80: =+AVERAGE(J80,I80,K80) -> #REF! | O80: =+M80/$M$105 -> #REF!
B81: 806982 | C81: AVIKO BREADED ONION RINGS 6x1000g | D81: 59 | E81: =+'VULPES PAPAS'!#REF! -> #REF! | F81: =+'VULPES PAPAS'!#REF! -> #REF! | G81: =+'VULPES PAPAS'!#REF! -> #REF! | H81: =+'VULPES PAPAS'!#REF! -> #REF! | I81: =+'VULPES PAPAS'!#REF! -> #REF! | J81: =+'VULPES PAPAS'!#REF! -> #REF! | K81: =+'VULPES PAPAS'!#REF! -> #REF! | M81: =+AVERAGE(J81,I81,K81) -> #REF! | O81: =+M81/$M$105 -> #REF!
B82: 260612 | C82: CASTEL STRAIGTH CUT FRIES 4x2500g | D82: 322.5 | E82: =+'VULPES PAPAS'!#REF! -> #REF! | F82: =+'VULPES PAPAS'!#REF! -> #REF! | G82: =+'VULPES PAPAS'!#REF! -> #REF! | H82: =+'VULPES PAPAS'!#REF! -> #REF! | I82: =+'VULPES PAPAS'!#REF! -> #REF! | J82: =+'VULPES PAPAS'!#REF! -> #REF! | K82: =+'VULPES PAPAS'!#REF! -> #REF! | M82: =+AVERAGE(J82,I82,K82) -> #REF! | O82: =+M82/$M$105 -> #REF!
B83: 803528 | C83: AVIKO H POMMES FRITES 11mm 7/16 4x2500g | E83: =+'VULPES PAPAS'!#REF! -> #REF! | F83: =+'VULPES PAPAS'!#REF! -> #REF! | G83: =+'VULPES PAPAS'!#REF! -> #REF! | H83: =+'VULPES PAPAS'!#REF! -> #REF! | I83: =+'VULPES PAPAS'!#REF! -> #REF! | J83: =+'VULPES PAPAS'!#REF! -> #REF! | K83: =+'VULPES PAPAS'!#REF! -> #REF! | M83: =+AVERAGE(J83,I83,K83) -> #REF! | O83: =+M83/$M$105 -> #REF!
B84: 804104 | C84: AVIKO HASHBROWNS TRIANGLES 4x2500g | E84: =+'VULPES PAPAS'!#REF! -> #REF! | F84: =+'VULPES PAPAS'!#REF! -> #REF! | G84: =+'VULPES PAPAS'!#REF! -> #REF! | H84: =+'VULPES PAPAS'!#REF! -> #REF! | I84: =+'VULPES PAPAS'!#REF! -> #REF! | J84: =+'VULPES PAPAS'!#REF! -> #REF! | K84: =+'VULPES PAPAS'!#REF! -> #REF! | M84: =+AVERAGE(J84,I84,K84) -> #REF! | O84: =+M84/$M$105 -> #REF!
B85: 809025 | C85: AVIKO CRISPY CHURROS 4x1000g | E85: =+'VULPES PAPAS'!#REF! -> #REF! | F85: =+'VULPES PAPAS'!#REF! -> #REF! | G85: =+'VULPES PAPAS'!#REF! -> #REF! | H85: =+'VULPES PAPAS'!#REF! -> #REF! | I85: =+'VULPES PAPAS'!#REF! -> #REF! | J85: =+'VULPES PAPAS'!#REF! -> #REF! | K85: =+'VULPES PAPAS'!#REF! -> #REF! | M85: =+AVERAGE(J85,I85,K85) -> #REF! | O85: =+M85/$M$105 -> #REF!
B86: 806686 | C86: AVIKO H PREM CRUNCH 9.5 mm 3/8 4x2270g | E86: =+'VULPES PAPAS'!#REF! -> #REF! | F86: =+'VULPES PAPAS'!#REF! -> #REF! | G86: =+'VULPES PAPAS'!#REF! -> #REF! | H86: =+'VULPES PAPAS'!#REF! -> #REF! | I86: =+'VULPES PAPAS'!#REF! -> #REF! | J86: =+'VULPES PAPAS'!#REF! -> #REF! | K86: =+'VULPES PAPAS'!#REF! -> #REF! | M86: =+AVERAGE(J86,I86,K86) -> #REF! | O86: =+M86/$M$105 -> #REF!
B87: 804109 | C87: AVIKO SHOESTRING 5x2500g | E87: =+'VULPES PAPAS'!#REF! -> #REF! | F87: =+'VULPES PAPAS'!#REF! -> #REF! | G87: =+'VULPES PAPAS'!#REF! -> #REF! | H87: =+'VULPES PAPAS'!#REF! -> #REF! | I87: =+'VULPES PAPAS'!#REF! -> #REF! | J87: =+'VULPES PAPAS'!#REF! -> #REF! | K87: =+'VULPES PAPAS'!#REF! -> #REF! | M87: =+AVERAGE(J87,I87,K87) -> #REF! | O87: =+M87/$M$105 -> #REF!
B88: 806918 | C88: AVIKO H SUPER LONG 9.5 MM SKIN ON 4x2500g | E88: =+'VULPES PAPAS'!#REF! -> #REF! | F88: =+'VULPES PAPAS'!#REF! -> #REF! | G88: =+'VULPES PAPAS'!#REF! -> #REF! | H88: =+'VULPES PAPAS'!#REF! -> #REF! | I88: =+'VULPES PAPAS'!#REF! -> #REF! | J88: =+'VULPES PAPAS'!#REF! -> #REF! | K88: =+'VULPES PAPAS'!#REF! -> #REF! | M88: =+AVERAGE(J88,I88,K88) -> #REF! | O88: =+M88/$M$105 -> #REF!
B89: 809013 | C89: AVIKO GRATINS CREAM&CHEESE 6x3.3lbs | E89: =+'VULPES PAPAS'!#REF! -> #REF! | F89: =+'VULPES PAPAS'!#REF! -> #REF! | G89: =+'VULPES PAPAS'!#REF! -> #REF! | H89: =+'VULPES PAPAS'!#REF! -> #REF! | I89: =+'VULPES PAPAS'!#REF! -> #REF! | J89: =+'VULPES PAPAS'!#REF! -> #REF! | K89: =+'VULPES PAPAS'!#REF! -> #REF! | M89: =+AVERAGE(J89,I89,K89) -> #REF! | O89: =+M89/$M$105 -> #REF!
B90: 01AGL01 | C90: PAPA ONDULADA 1/2 LUTOSA | E90: =+'VULPES PAPAS'!#REF! -> #REF! | F90: =+'VULPES PAPAS'!#REF! -> #REF! | O90: =+M90/$M$105 -> #REF!
B91: TOTAL AVIKO | D91: =+SUM(D75:D90) -> 2270.5 | E91: =+SUM(E75:E89) -> #REF! | F91: =+SUM(F75:F89) -> #REF! | G91: =+SUM(G75:G89) -> #REF! | H91: =+SUM(H75:H89) -> #REF! | I91: =+SUM(I75:I89) -> #REF! | J91: =+SUM(J75:J89) -> #REF! | K91: =+SUM(K75:K89) -> #REF! | M91: =+SUM(M75:M90) -> #REF! | O91: =SUM(O75:O90) -> #REF!
B92: CÓDIGO | C92: DESCRIPCIÓN
B93: 102341 | C93: 10 MM STRAIGHT CUT COATED 4x2.5kg | D93: 330 | E93: =+'VULPES PAPAS'!#REF! -> #REF! | F93: =+'VULPES PAPAS'!#REF! -> #REF! | G93: =+'VULPES PAPAS'!#REF! -> #REF! | H93: =+'VULPES PAPAS'!#REF! -> #REF! | I93: =+'VULPES PAPAS'!#REF! -> #REF! | J93: =+'VULPES PAPAS'!#REF! -> #REF! | K93: =+'VULPES PAPAS'!#REF! -> #REF! | M93: =+AVERAGE(J93,I93,K93) -> #REF! | O93: =+M93/$M$105 -> #REF!
B94: 102013 | C94: 10 MM STRAIGHT CUT 4x2.5kg | D94: 439.5 | E94: =+'VULPES PAPAS'!#REF! -> #REF! | F94: =+'VULPES PAPAS'!#REF! -> #REF! | G94: =+'VULPES PAPAS'!#REF! -> #REF! | H94: =+'VULPES PAPAS'!#REF! -> #REF! | I94: =+'VULPES PAPAS'!#REF! -> #REF! | J94: =+'VULPES PAPAS'!#REF! -> #REF! | K94: =+'VULPES PAPAS'!#REF! -> #REF! | M94: =+AVERAGE(J94,I94,K94) -> #REF! | O94: =+M94/$M$105 -> #REF!
B95: 102419 | C95: PREMIER GOLD CRINKLE 12MM 4X2.5KG | D95: 124 | E95: =+'VULPES PAPAS'!#REF! -> #REF! | F95: =+'VULPES PAPAS'!#REF! -> #REF! | G95: =+'VULPES PAPAS'!#REF! -> #REF! | H95: =+'VULPES PAPAS'!#REF! -> #REF! | I95: =+'VULPES PAPAS'!#REF! -> #REF! | J95: =+'VULPES PAPAS'!#REF! -> #REF! | K95: =+'VULPES PAPAS'!#REF! -> #REF! | M95: =+AVERAGE(J95,I95,K95) -> #REF! | O95: =+M95/$M$105 -> #REF!
B96: 114054 | C96: FROZEN SPICY COATED WEDGES 4X2.5KG PREMIER GOLD | D96: 68.5 | E96: =+'VULPES PAPAS'!#REF! -> #REF! | F96: =+'VULPES PAPAS'!#REF! -> #REF! | G96: =+'VULPES PAPAS'!#REF! -> #REF! | H96: =+'VULPES PAPAS'!#REF! -> #REF! | I96: =+'VULPES PAPAS'!#REF! -> #REF! | J96: =+'VULPES PAPAS'!#REF! -> #REF! | K96: =+'VULPES PAPAS'!#REF! -> #REF! | M96: =+AVERAGE(J96,I96,K96) -> #REF! | O96: =+M96/$M$105 -> #REF!
B97: 102310 | C97: FROZEN FRENCH FRIES 4X2.5KG 8X8MM COATED JULIENNE PREMIER GOLD | D97: 20 | E97: =+'VULPES PAPAS'!#REF! -> #REF! | F97: =+'VULPES PAPAS'!#REF! -> #REF! | G97: =+'VULPES PAPAS'!#REF! -> #REF! | H97: =+'VULPES PAPAS'!#REF! -> #REF! | I97: =+'VULPES PAPAS'!#REF! -> #REF! | J97: =+'VULPES PAPAS'!#REF! -> #REF! | K97: =+'VULPES PAPAS'!#REF! -> #REF! | M97: =+AVERAGE(J97,I97,K97) -> #REF! | O97: =+M97/$M$105 -> #REF!
B98: 102211 | C98: FROZEN FRENCH FRIES 4X2.5KG 7.5X7.5MM JULIENNE PREMIER GOLD | D98: 155.25 | E98: =+'VULPES PAPAS'!#REF! -> #REF! | F98: =+'VULPES PAPAS'!#REF! -> #REF! | G98: =+'VULPES PAPAS'!#REF! -> #REF! | H98: =+'VULPES PAPAS'!#REF! -> #REF! | I98: =+'VULPES PAPAS'!#REF! -> #REF! | J98: =+'VULPES PAPAS'!#REF! -> #REF! | K98: =+'VULPES PAPAS'!#REF! -> #REF! | M98: =+AVERAGE(J98,I98,K98) -> #REF! | O98: =+M98/$M$105 -> #REF!
B99: 104215 | C99: FROZEN FRENCH FRIES 4X2.5KG COATED 10MM SKIN-ON PREMIER GOLD | D99: 113 | E99: =+'VULPES PAPAS'!#REF! -> #REF! | F99: =+'VULPES PAPAS'!#REF! -> #REF! | G99: =+'VULPES PAPAS'!#REF! -> #REF! | H99: =+'VULPES PAPAS'!#REF! -> #REF! | I99: =+'VULPES PAPAS'!#REF! -> #REF! | J99: =+'VULPES PAPAS'!#REF! -> #REF! | K99: =+'VULPES PAPAS'!#REF! -> #REF! | M99: =+AVERAGE(J99,I99,K99) -> #REF! | O99: =+M99/$M$105 -> #REF!
B100: 111435 | C100: TRIANGLE HASH BROWNS | E100: =+'VULPES PAPAS'!#REF! -> #REF! | F100: =+'VULPES PAPAS'!#REF! -> #REF! | G100: =+'VULPES PAPAS'!#REF! -> #REF! | H100: =+'VULPES PAPAS'!#REF! -> #REF! | I100: =+'VULPES PAPAS'!#REF! -> #REF! | J100: =+'VULPES PAPAS'!#REF! -> #REF! | K100: =+'VULPES PAPAS'!#REF! -> #REF! | M100: =+AVERAGE(J100,I100,K100) -> #REF! | O100: =+M100/$M$105 -> #REF!
...

Sheet Resumen T.C.
A1: Fecha | B1: Valor USD DOF | C1: Valor EUR Banco de México | D1: Valor EUR Investing | E1: Hora | F1: prom m¿del mes | G1: prom 10 dias | H1: prom5dias
A2: 45748 | B2: 20.438 | C2: 21.9864 | D2: 21.9517 | E2: 0.54166667
A3: 45749 | B3: 20.3587 | C3: 22.0821 | D3: 22.0433 | E3: 0.58333333
A4: 45750 | B4: 20.4568 | C4: 22.0707 | D4: 22.0603 | E4: 0.625
A5: 45751 | B5: 19.9708 | C5: 22.6106 | D5: 22.3884 | E5: 0.45833333
A6: 45754 | B6: 20.501 | C6: 22.6804 | D6: 22.5624 | E6: 0.58333333
A7: 45755 | B7: 20.6947 | C7: 22.6075 | D7: 22.9315 | E7: 0.625
A8: 45756 | B8: 20.6867 | C8: 22.9072 | D8: 22.2754 | E8: 0.66666667
A9: 45757 | B9: 20.7653 | C9: 22.7041 | D9: 23.3045 | E9: 0.70833333
A10: 45758 | B10: 20.492 | C10: 23.042 | D10: 23.07 | E10: 0.62847222
A11: 45761.043 | B11: 20.3363 | C11: 22.8907 | D11: 22.8368 | E11: 12.52 pm
A12: 45762 | B12: 20.1025 | C12: 22.7092 | D12: 22.5984 | E12: 12
A13: 45763 | B13: 20.0213 | C13: 22.69313 | D13: 22.7157 | E13: 12
A14: 45764 | D14: 22.4674 | E14: 15 | F14: =AVERAGE(D2:D15) -> 22.558257 | G14: =AVERAGE(D5:D15) -> 22.705482 | H14: =AVERAGE(D10:D14) -> 22.73766 | I14: =AVERAGE(F14:H14) -> 22.667133
A15: 45768 | D15: 22.6098 | E15: 0.33333333
A16: 45769 | D16: 22.3985 | E16: 11.45 am | F16: =AVERAGE(D2:D16) -> 22.547607 | G16: =AVERAGE(D7:D16) -> 22.7208 | H16: =AVERAGE(D12:D16) -> 22.55796 | I16: =AVERAGE(F16:H16) -> 22.608789
A17: 23 | D17: 22.26 | E17: 1.40 pm | F17: =AVERAGE(D2:D17) -> 22.529631 | G17: =AVERAGE(D8:D17) -> 22.65365 | H17: =AVERAGE(D13:D17) -> 22.49028 | I17: =AVERAGE(F17:H17) -> 22.557854
F18: =AVERAGE(D2:D18) -> 22.529631 | G18: =AVERAGE(D9:D18) -> 22.695678 | H18: =AVERAGE(D14:D18) -> 22.433925 | I18: =AVERAGE(F18:H18) -> 22.553078
A20: PROMEDIOS | B20: =+AVERAGE(B2:B13) -> 20.402008 | C20: =+AVERAGE(C2:C13) -> 22.582003 | D20: =+AVERAGE(D2:D14) -> 22.554292 | E20: =+AVERAGE(E2:E10) -> 0.60223765

Sheet CANCÚN
O1: 30 | BO1: INV ACTUAL + CONTENEDORES EN TRANSITO - VENTAS | BR1: Consumo mensual, Promedio año en curso | BS1: Proyeccion de Ventas, con 10% al promedio del consumo mensual | BT1: Duracion de Inv. En Meses Considerando Inv Actual + Contenedores en Transito - Ventas | BX1: CONTENEDORES EN TRANSITO | CA1: Cjas x Tarima | CB1: SUGERENCIA DE PEDIDOS, DE CONTENEDOR A 21 PALLET
A2: PROMEDIO DÍAS DE TRANSITO | B2: PROVEEDOR | C2: ESTATUS DEL PRODUCTO | D2: CÓDIGO | E2: DESCRIPCIÓN | F2: INV DICIEMBRE 2025 | G2: COMPRAS | H2: Entradas | I2: Salidas | J2: VENTAS | K2: INV ENERO 2026 | L2: COMPRAS | M2: Entradas | N2: Salidas | O2: VENTAS | P2: INV FEBRERO 2026 | Q2: COMPRAS | R2: Entradas | S2: Salidas | T2: VENTAS | U2: INV MARZO 2026 | V2: COMPRAS | W2: Entradas | X2: Salidas | Y2: VENTAS | Z2: INV ABRIL 2026 | AA2: COMPRAS | AB2: Entradas | AC2: Salidas | AD2: VENTAS | AE2: INV MAYO 2026 | AF2: COMPRAS | AG2: Entradas | AH2: Salidas | AI2: VENTAS | AJ2: INV JUNIO 2026 | AK2: COMPRAS | AL2: Entradas | AM2: Salidas | AN2: VENTAS | AO2: INV JULIO 2026 | AP2: COMPRAS | AQ2: Entradas | AR2: Salidas | AS2: VENTAS | AT2: INV AGOSTO 2026 | AU2: COMPRAS | AV2: Entradas | AW2: Salidas | AX2: VENTAS | AY2: INV SEPTIEMBRE 2026 | AZ2: COMPRAS | BA2: Entradas | BB2: Salidas | BC2: VENTAS | BD2: INV OCTUBRE 2026 | BE2: COMPRAS | BF2: Entradas | BG2: Salidas | BH2: VENTAS | BI2: INV NOVIEMBRE 2026 | BJ2: COMPRAS | BK2: Entradas | BL2: Salidas | BM2: VENTAS | BN2: INV DICIEMBRE 2026 | BT2: ACTUAL | CB2: PALLET | CC2: CAJAS
A3: 60 | B3: AVIKO | C3: OPORTUNIDAD | D3: 804104 | E3: TRIANGLE HASHBROW 63G/40PZ BAG APPROX) 4 X 2.5KG | F3: 549.5 | J3: 56.25 | K3: =+F3+G3+H3-I3-J3 -> 493.25 | O3: 234.25 | P3: =+K3+L3+M3-N3-O3 -> 259 | T3: 155.75 | U3: =+P3+Q3+R3-S3-T3 -> 103.25 | Y3: 44 | Z3: =+U3+V3+W3-X3-Y3 -> 59.25 | AD3: 24.25 | AE3: =+Z3+AA3+AB3-AC3-AD3 -> 35 | BO3: =IF((AE3-($BR3*(NETWORKDAYS(TODAY(),$BX$12)/$O$1))+BX3)<=0,0,AE3-($BR3*(NETWORKDAYS(TODAY(),$BX$12)/$O$1))+BX3) -> 20.475 | BR3: =AVERAGE(J3,O3) -> 145.25 | BS3: =+BR3*1.1 -> 159.775 | BT3: =+Z3/BR3 -> 0.40791738 | CA3: 108 | CC3: =+CB3*CA3 -> 0
A4: 60 | B4: AVIKO | C4: OPORTUNIDAD | D4: 805567 | E4: HASBROWNS ROUNDS - FRYER 4X2500G | F4: 743.5 | K4: =+F4+G4+H4-I4-J4 -> 743.5 | P4: =+K4+L4+M4-N4-O4 -> 743.5 | R4: 10 | T4: 287.25 | U4: =+P4+Q4+R4-S4-T4 -> 466.25 | W4: 1 | Y4: 319 | Z4: =+U4+V4+W4-X4-Y4 -> 148.25 | AB4: 9 | AD4: 46 | AE4: =+Z4+AA4+AB4-AC4-AD4 -> 111.25 | BO4: =IF((AE4-($BR4*(NETWORKDAYS(TODAY(),$BX$12)/$O$1))+BX4)<=0,0,AE4-($BR4*(NETWORKDAYS(TODAY(),$BX$12)/$O$1))+BX4) -> 86.25 | BR4: 250 | BS4: =+BR4*1.1 -> 275 | BT4: =+Z4/BR4 -> 0.593 | CA4: 108 | CC4: =+CB4*CA4 -> 0
A5: 60 | B5: AVIKO | C5: INACTIVO | D5: 803528 | E5: Aviko H Pommes Frites 11mm 7/16 4x2500g | F5: 0 | K5: =+F5+G5+H5-I5-J5 -> 0 | P5: =+K5+L5+M5-N5-O5 -> 0 | AE5: =+Z5+AA5+AB5-AC5-AD5 -> 0 | BO5: =IF((AE5-($BR5*(NETWORKDAYS(TODAY(),$BX$12)/$O$1))+BX5)<=0,0,AE5-($BR5*(NETWORKDAYS(TODAY(),$BX$12)/$O$1))+BX5) -> 0 | CA5: 108 | CC5: =+CB5*CA5 -> 0
A6: 60 | B6: AVIKO | C6: INACTIVO | D6: 806685 | E6: AVIKO H PREM.CRUNCH SHOESTRING 7MM 4X2270G | F6: 51.25 | J6: 51 | K6: =+F6+G6+H6-I6-J6 -> 0.25 | O6: 0.25 | P6: =+K6+L6+M6-N6-O6 -> 0 | AE6: =+Z6+AA6+AB6-AC6-AD6 -> 0 | BO6: =IF((AE6-($BR6*(NETWORKDAYS(TODAY(),$BX$12)/$O$1))+BX6)<=0,0,AE6-($BR6*(NETWORKDAYS(TODAY(),$BX$12)/$O$1))+BX6) -> 0 | BR6: 2.25 | BT6: =+P6/BR6 -> 0 | CA6: 108 | CC6: =+CB6*CA6 -> 0
K7: =+F7+G7+H7-I7-J7 -> 0
K8: =+F8+G8+H8-I8-J8 -> 0
K9: =+F9+G9+H9-I9-J9 -> 0
D10: TOTAL AVIKO | F10: =+SUM(F3:F9) -> 1344.25 | G10: =+SUM(G3:G9) -> 0 | H10: =+SUM(H3:H9) -> 0 | I10: =+SUM(I3:I9) -> 0 | J10: =+SUM(J3:J9) -> 107.25 | K10: =+SUM(K3:K9) -> 1237 | L10: =+SUM(L3:L9) -> 0 | M10: =+SUM(M3:M9) -> 0 | ... S10: =+SUM(S3:S9) -> 0 | T10: =SUM(T3:T5) -> 443 | U10: =+SUM(U3:U9) -> 569.5 | V10: =+SUM(V3:V9) -> 0 | W10: =+SUM(W3:W9) -> 1 | X10: =+SUM(X3:X9) -> 0 | Y10: =+SUM(Y3:Y9) -> 363 | Z10: =+SUM(Z3:Z9) -> 207.5 | AA10: =+SUM(AA3:AA9) -> 0 | AB10: =+SUM(AB3:AB9) -> 9 | ... BN10: =+SUM(BN3:BN9) -> 0 | BR10: =SUM(BR3:BR6) -> 397.5 | BS10: =SUM(BS3:BS6) -> 434.775 | BX10: =+SUM(BX3:BX6) -> 0 | CB10: =+SUM(CB3:CB6) -> 0 | CC10: =+SUM(CC3:CC6) -> 0
BO11: INV ACTUAL + CONTENEDORES EN TRANSITO - VENTAS | BR11: Consumo mensual, Promedio año en curso | BS11: Proyeccion de Ventas, con 10% al promedio del consumo mensual | BT11: Duracion de Inv. En Meses Considerando Inv Actual + Contenedores en Transito - Ventas | BX11: C-112 PTO 13-05 | BY11: C-114 PTO 13-05 | BZ11: SUGERIDO | CB11: SUGERENCIA DE PEDIDOS, DE CONTENEDOR A 21 PALLET
A12: PROMEDIO DÍAS DE TRANSITO | B12: PROVEEDOR | C12: ESTATUS DEL PRODUCTO | D12: CÓDIGO | E12: DESCRIPCIÓN | F12: INV DICIEMBRE 2025 | G12: COMPRAS | H12: Entradas | I12: Salidas | J12: VENTAS | K12: INV ENERO 2026 | L12: COMPRAS | M12: Entradas | N12: Salidas | O12: VENTAS | P12: INV FEBRERO 2026 | Q12: COMPRAS | R12: Entradas | S12: Salidas | T12: VENTAS | U12: INV MARZO 2026 | V12: COMPRAS | W12: Entradas | X12: Salidas | Y12: VENTAS | Z12: INV ABRIL 2026 | AA12: COMPRAS | AB12: Entradas | AC12: Salidas | AD12: VENTAS | AE12: INV MAYO 2026 | AF12: COMPRAS | AG12: Entradas | AH12: Salidas | AI12: VENTAS | AJ12: INV JUNIO 2026 | AK12: COMPRAS | AL12: Entradas | AM12: Salidas | AN12: VENTAS | AO12: INV JULIO 2026 | AP12: COMPRAS | AQ12: Entradas | AR12: Salidas | AS12: VENTAS | AT12: INV AGOSTO 2026 | AU12: COMPRAS | AV12: Entradas | AW12: Salidas | AX12: VENTAS | AY12: INV SEPTIEMBRE 2026 | AZ12: COMPRAS | BA12: Entradas | BB12: Salidas | BC12: VENTAS | BD12: INV OCTUBRE 2026 | BE12: COMPRAS | BF12: Entradas | BG12: Salidas | BH12: VENTAS | BI12: INV NOVIEMBRE 2026 | BJ12: COMPRAS | BK12: Entradas | BL12: Salidas | BM12: VENTAS | BN12: INV DICIEMBRE 2026 | BO12: C-112 | BP12: C-114 | BT12: ACTUAL | BU12: 112 | BV12: 114 | BW12: SUGERIDO | BX12: 46158 | BY12: 46158 | BZ12: 46192 | CB12: PALLET | CC12: CAJAS
A13: 60 | B13: WERSING | C13: ACTIVO | D13: 105632 | E13: 10 MM NATURAL, MISMO PRODUCTO 102013 | F13: 0 | H13: 4371 | J13: 1083.25 | K13: =+F13+G13+H13-I13-J13 -> 3287.75 | O13: 919.75 | P13: =+K13+L13+M13-N13-O13 -> 2368 | T13: 1621.25 | U13: =+P13+Q13+R13-S13-T13 -> 746.75 | Y13: 746.75 | Z13: =+U13+V13+W13-X13-Y13 -> 0 | AE13: =+Z13+AA13+AB13-AC13-AD13 -> 0 | BO13: =IF((AE13-($BR13*(NETWORKDAYS(TODAY(),$BX$12)/$O$1))+BX13)<=0,0,AE13-($BR13*(NETWORKDAYS(TODAY(),$BX$12)/$O$1))+BX13) -> 0 | BP13: =IF((BO13-($BR13*(NETWORKDAYS($BX$12,$BY$12)/$O$1))+BY13)<=0,0,BO13-($BR13*(NETWORKDAYS($BX$12,$BY$12)/$O$1))+BY13) -> 0 | BQ13: =IF((BP13-($BR13*(NETWORKDAYS($BY$12,$BZ$12)/$O$1))+BZ13)<=0,0,BP13-($BR13*(NETWORKDAYS($BY$12,$BZ$12)/$O$1))+BZ13) -> 0 | BR13: =AVERAGE(J13,O13,T13,Y13) -> 1092.75 | BT13: =+Z13/BR13 -> 0 | BU13: =+BO13/BR13 -> 0 | BV13: =+BP13/BR13 -> 0 | BW13: =+BQ13/BR13 -> 0 | CA13: 120 | CC13: =+CB13*CA13 -> 0
A14: 60 | B14: WERSING | C14: ACTIVO | D14: 102013 | E14: 10 MM NATURAL, MISMO PRODUCTO 105632 | F14: 1.25 | J14: 1.25 | K14: =+F14+G14+H14-I14-J14 -> 0 | P14: =+K14+L14+M14-N14-O14 -> 0 | U14: =+P14+Q14+R14-S14-T14 -> 0 | W14: 2088 | Y14: 404 | Z14: =+U14+V14+W14-X14-Y14 -> 1684 | AD14: 363.25 | AE14: =+Z14+AA14+AB14-AC14-AD14 -> 1320.75 | BO14: =IF((AE14-($BR14*(NETWORKDAYS(TODAY(),$BX$12)/$O$1))+BX14)<=0,0,AE14-($BR14*(NETWORKDAYS(TODAY(),$BX$12)/$O$1))+BX14) -> 1199.942 | BP14: =IF((BO14-($BR14*(NETWORKDAYS($BX$12,$BY$12)/$O$1))+BY14)<=0,0,BO14-($BR14*(NETWORKDAYS($BX$12,$BY$12)/$O$1))+BY14) -> 2711.942 | BQ14: =IF((BP14-($BR14*(NETWORKDAYS($BY$12,$BZ$12)/$O$1))+BZ14)<=0,0,BP14-($BR14*(NETWORKDAYS($BY$12,$BZ$12)/$O$1))+BZ14) -> 3265.2087 | BR14: 1208.08 | BS14: =+BR14*1.1 -> 1328.888 | BT14: =+AE14/BR14 -> 1.0932637 | BU14: =+BO14/BR14 -> 0.99326369 | BV14: =+BP14/BR14 -> 2.2448364 | BW14: =+BQ14/BR14 -> 2.7028083 | BY14: 1512 | BZ14: 1560 | CA14: 120 | CB14: 13 | CC14: =+CB14*CA14 -> 1560
A15: 60 | B15: WERSING | C15: ACTIVO | D15: 102341 | E15: 10 MM CON COBERTURA | F15: 2340.75 | H15: 216 | J15: 412.25 | K15: =+F15+G15+H15-I15-J15 -> 2144.5 | O15: 514 | P15: =+K15+L15+M15-N15-O15 -> 1630.5 | T15: 610.25 | U15: =+P15+Q15+R15-S15-T15 -> 1020.25 | Y15: 444 | Z15: =+U15+V15+W15-X15-Y15 -> 576.25 | AD15: 26 | AE15: =+Z15+AA15+AB15-AC15-AD15 -> 550.25 | BO15: =IF((AE15-($BR15*(NETWORKDAYS(TODAY(),$BX$12)/$O$1))+BX15)<=0,0,AE15-($BR15*(NETWORKDAYS(TODAY(),$BX$12)/$O$1))+BX15) -> 500.7375 | BP15: =IF((BO15-($BR15*(NETWORKDAYS($BX$12,$BY$12)/$O$1))+BY15)<=0,0,BO15-($BR15*(NETWORKDAYS($BX$12,$BY$12)/$O$1))+BY15) -> 500.7375 | BQ15: =IF((BP15-($BR15*(NETWORKDAYS($BY$12,$BZ$12)/$O$1))+BZ15)<=0,0,BP15-($BR15*(NETWORKDAYS($BY$12,$BZ$12)/$O$1))+BZ15) -> 88.133333 | BR15: =AVERAGE(J15,O15,T15,Y15) -> 495.125 | BS15: =+BR15*1.1 -> 544.6375 | BT15: =+AE15/BR15 -> 1.1113355 | BU15: =+BO15/BR15 -> 1.0113355 | BV15: =+BP15/BR15 -> 1.0113355 | BW15: =+BQ15/BR15 -> 0.17800219 | CA15: 108 | CC15: =+CB15*CA15 -> 0
A16: 60 | B16: WERSING | C16: ACTIVO | D16: 102310 | E16: 7 MM CON COBERTURA | F16: 124 | J16: 25 | K16: =+F16+G16+H16-I16-J16 -> 99 | O16: 32.5 | P16: =+K16+L16+M16-N16-O16 -> 66.5 | T16: 27.75 | U16: =+P16+Q16+R16-S16-T16 -> 38.75 | W16: 126 | Y16: 30 | Z16: =+U16+V16+W16-X16-Y16 -> 134.75 | AD16: 11 | AE16: =+Z16+AA16+AB16-AC16-AD16 -> 123.75 | BO16: =IF((AE16-($BR16*(NETWORKDAYS(TODAY(),$BX$12)/$O$1))+BX16)<=0,0,AE16-($BR16*(NETWORKDAYS(TODAY(),$BX$12)/$O$1))+BX16) -> 120.86875 | BP16: =IF((BO16-($BR16*(NETWORKDAYS($BX$12,$BY$12)/$O$1))+BY16)<=0,0,BO16-($BR16*(NETWORKDAYS($BX$12,$BY$12)/$O$1))+BY16) -> 120.86875 | BQ16: =IF((BP16-($BR16*(NETWORKDAYS($BY$12,$BZ$12)/$O$1))+BZ16)<=0,0,BP16-($BR16*(NETWORKDAYS($BY$12,$BZ$12)/$O$1))+BZ16) -> 96.858333 | BR16: =AVERAGE(J16,O16,T16,Y16) -> 28.8125 | BS16: =+BR16*1.1 -> 31.69375 | BT16: =+AE16/BR16 -> 4.2950108 | BU16: =+BO16/BR16 -> 4.1950108 | BV16: =+BP16/BR16 -> 4.1950108 | BW16: =+BQ16/BR16 -> 3.3616775 | CA16: 108 | CC16: =+CB16*CA16 -> 0
A17: 60 | B17: WERSING | D17: 102211 | E17: 7 MM NATURAL | F17: 0 | K17: =+F17+G17+H17-I17-J17 -> 0 | P17: =+K17+L17+M17-N17-O17 -> 0 | U17: =+P17+Q17+R17-S17-T17 -> 0 | Z17: =+U17+V17+W17-X17-Y17 -> 0 | AE17: =+Z17+AA17+AB17-AC17-AD17 -> 0 | BO17: =IF((AE17-($BR17*(NETWORKDAYS(TODAY(),$BX$12)/$O$1))+BX17)<=0,0,AE17-($BR17*(NETWORKDAYS(TODAY(),$BX$12)/$O$1))+BX17) -> #DIV/0! | BP17: =IF((BO17-($BR17*(NETWORKDAYS($BX$12,$BY$12)/$O$1))+BY17)<=0,0,BO17-($BR17*(NETWORKDAYS($BX$12,$BY$12)/$O$1))+BY17) -> #DIV/0! | BQ17: =IF((BP17-($BR17*(NETWORKDAYS($BY$12,$BZ$12)/$O$1))+BZ17)<=0,0,BP17-($BR17*(NETWORKDAYS($BY$12,$BZ$12)/$O$1))+BZ17) -> #DIV/0! | BR17: =AVERAGE(J17,O17,T17,Y17) -> #DIV/0! | BS17: =+BR17*1.1 -> #DIV/0! | BT17: =+AE17/BR17 -> #DIV/0! | BU17: =+BO17/BR17 -> #DIV/0! | BV17: =+BP17/BR17 -> #DIV/0! | BW17: =+BQ17/BR17 -> #DIV/0! | CA17: 108 | CC17: =+CB17*CA17 -> 0
A18: 60 | B18: WERSING | D18: 104215 | E18: 10 MM CON COBERTURA Y CASCARA | F18: 0 | K18: =+F18+G18+H18-I18-J18 -> 0 | P18: =+K18+L18+M18-N18-O18 -> 0 | U18: =+P18+Q18+R18-S18-T18 -> 0 | Z18: =+U18+V18+W18-X18-Y18 -> 0 | AE18: =+Z18+AA18+AB18-AC18-AD18 -> 0 | BO18: =IF((AE18-($BR18*(NETWORKDAYS(TODAY(),$BX$12)/$O$1))+BX18)<=0,0,AE18-($BR18*(NETWORKDAYS(TODAY(),$BX$12)/$O$1))+BX18) -> #DIV/0! | BP18: =IF((BO18-($BR18*(NETWORKDAYS($BX$12,$BY$12)/$O$1))+BY18)<=0,0,BO18-($BR18*(NETWORKDAYS($BX$12,$BY$12)/$O$1))+BY18) -> #DIV/0! | BQ18: =IF((BP18-($BR18*(NETWORKDAYS($BY$12,$BZ$12)/$O$1))+BZ18)<=0,0,BP18-($BR18*(NETWORKDAYS($BY$12,$BZ$12)/$O$1))+BZ18) -> #DIV/0! | BR18: =AVERAGE(J18,O18,T18,Y18) -> #DIV/0! | BS18: =+BR18*1.1 -> #DIV/0! | BT18: =+AE18/BR18 -> #DIV/0! | BU18: =+BO18/BR18 -> #DIV/0! | BV18: =+BP18/BR18 -> #DIV/0! | BW18: =+BQ18/BR18 -> #DIV/0! | CA18: 144 | CC18: =+CB18*CA18 -> 0
A19: 60 | B19: WERSING | C19: ACTIVO | D19: 114054 | E19: GAJOS SAZONADOS | F19: 519.25 | J19: 33 | K19: =+F19+G19+H19-I19-J19 -> 486.25 | O19: 38.5 | P19: =+K19+L19+M19-N19-O19 -> 447.75 | T19: 27 | U19: =+P19+Q19+R19-S19-T19 -> 420.75 | Y19: 29.25 | Z19: =+U19+V19+W19-X19-Y19 -> 391.5 | AD19: 7 | AE19: =+Z19+AA19+AB19-AC19-AD19 -> 384.5 | BO19: =IF((AE19-($BR19*(NETWORKDAYS(TODAY(),$BX$12)/$O$1))+BX19)<=0,0,AE19-($BR19*(NETWORKDAYS(TODAY(),$BX$12)/$O$1))+BX19) -> 381.30625 | BP19: =IF((BO19-($BR19*(NETWORKDAYS($BX$12,$BY$12)/$O$1))+BY19)<=0,0,BO19-($BR19*(NETWORKDAYS($BX$12,$BY$12)/$O$1))+BY19) -> 381.30625 | BQ19: =IF((BP19-($BR19*(NETWORKDAYS($BY$12,$BZ$12)/$O$1))+BZ19)<=0,0,BP19-($BR19*(NETWORKDAYS($BY$12,$BZ$12)/$O$1))+BZ19) -> 354.69167 | BR19: =AVERAGE(J19,O19,T19,Y19) -> 31.9375 | BS19: =+BR19*1.1 -> 35.13125 | BT19: =+AE19/BR19 -> 12.039139 | BU19: =+BO19/BR19 -> 11.939139 | BV19: =+BP19/BR19 -> 11.939139 | BW19: =+BQ19/BR19 -> 11.105806 | CA19: 108 | CC19: =+CB19*CA19 -> 0
A20: 60 | B20: WERSING | C20: ACTIVO | D20: 102419 | E20: ONDULADA | F20: 0 | H20: 180 | J20: 31 | K20: =+F20+G20+H20-I20-J20 -> 149 | O20: 34.25 | P20: =+K20+L20+M20-N20-O20 -> 114.75 | T20: 35.5 | U20: =+P20+Q20+R20-S20-T20 -> 79.25 | W20: 144 | Y20: 41 | Z20: =+U20+V20+W20-X20-Y20 -> 182.25 | AD20: 15.75 | AE20: =+Z20+AA20+AB20-AC20-AD20 -> 166.5 | BO20: =IF((AE20-($BR20*(NETWORKDAYS(TODAY(),$BX$12)/$O$1))+BX20)<=0,0,AE20-($BR20*(NETWORKDAYS(TODAY(),$BX$12)/$O$1))+BX20) -> 162.95625 | BP20: =IF((BO20-($BR20*(NETWORKDAYS($BX$12,$BY$12)/$O$1))+BY20)<=0,0,BO20-($BR20*(NETWORKDAYS($BX$12,$BY$12)/$O$1))+BY20) -> 162.95625 | BQ20: =IF((BP20-($BR20*(NETWORKDAYS($BY$12,$BZ$12)/$O$1))+BZ20)<=0,0,BP20-($BR20*(NETWORKDAYS($BY$12,$BZ$12)/$O$1))+BZ20) -> 133.425 | BR20: =AVERAGE(J20,O20,T20,Y20) -> 35.4375 | BS20: =+BR20*1.1 -> 38.98125 | BT20: =+AE20/BR20 -> 4.6984127 | BU20: =+BO20/BR20 -> 4.5984127 | BV20: =+BP20/BR20 -> 4.5984127 | BW20: =+BQ20/BR20 -> 3.7650794 | CA20: 108 | CC20: =+CB20*CA20 -> 0
A21: 60 | B21: WERSING | D21: 1000440 | E21: 3/8 VIMA FOODS | F21: 113.25 | J21: 110 | K21: =+F21+G21+H21-I21-J21 -> 3.25 | O21: 3.25 | P21: =+K21+L21+M21-N21-O21 -> 0 | U21: =+P21+Q21+R21-S21-T21 -> 0 | Z21: =+U21+V21+W21-X21-Y21 -> 0 | AE21: =+Z21+AA21+AB21-AC21-AD21 -> 0 | BO21: =IF((AE21-($BR21*(NETWORKDAYS(TODAY(),$BX$12)/$O$1))+BX21)<=0,0,AE21-($BR21*(NETWORKDAYS(TODAY(),$BX$12)/$O$1))+BX21) -> 0 | BQ21: =IF((BP21-($BR21*(NETWORKDAYS($BY$12,$BZ$12)/$O$1))+BZ21)<=0,0,BP21-($BR21*(NETWORKDAYS($BY$12,$BZ$12)/$O$1))+BZ21) -> 0 | BR21: =AVERAGE(J21,O21,T21) -> 56.625 | BS21: =+BR21*1.1 -> 62.2875 | BT21: =+AE21/BR21 -> 0 | BU21: =+BO21/BR21 -> 0 | BV21: =+BP21/BR21 -> 0 | BW21: =+BQ21/BR21 -> 0
A22: 60 | B22: WERSING | C22: ACTIVO | D22: 101245 | E22: 11 MM CON COBERTURA, SUSTITUTO 102341 PRODUCTO NUEVO | K22: =+F22+G22+H22-I22-J22 -> 0 | P22: =+K22+L22+M22-N22-O22 -> 0 | U22: =+P22+Q22+R22-S22-T22 -> 0 | Z22: =+U22+V22+W22-X22-Y22 -> 0 | AE22: =+Z22+AA22+AB22-AC22-AD22 -> 0 | BO22: =IF((AE22-($BR22*(NETWORKDAYS(TODAY(),$BX$12)/$O$1))+BX22)<=0,0,AE22-($BR22*(NETWORKDAYS(TODAY(),$BX$12)/$O$1))+BX22) -> 2316 | BP22: =IF((BO22-($BR22*(NETWORKDAYS($BX$12,$BY$12)/$O$1))+BY22)<=0,0,BO22-($BR22*(NETWORKDAYS($BX$12,$BY$12)/$O$1))+BY22) -> 2316 | BQ22: =IF((BP22-($BR22*(NETWORKDAYS($BY$12,$BZ$12)/$O$1))+BZ22)<=0,0,BP22-($BR22*(NETWORKDAYS($BY$12,$BZ$12)/$O$1))+BZ22) -> 1816 | BR22: 600 | BS22: =+BR22*1.1 -> 660 | BT22: =+AE22/BR22 -> 0 | BU22: =+BO22/BR22 -> 3.86 | BV22: =+BP22/BR22 -> 3.86 | BW22: =+BQ22/BR22 -> 3.0266667 | BX22: 2376
A23: 60 | B23: WERSING | C23: ACTIVO | D23: 110582 | E23: TRIANGLE HASHBROW 63G/40PZ BAG APPROX) 4 X 2.5KG, SUSTITUTO 804104 | Z23: =+U23+V23+W23-X23-Y23 -> 0 | AE23: =+Z23+AA23+AB23-AC23-AD23 -> 0 | BO23: =IF((AE23-($BR23*(NETWORKDAYS(TODAY(),$BX$12)/$O$1))+BX23)<=0,0,AE23-($BR23*(NETWORKDAYS(TODAY(),$BX$12)/$O$1))+BX23) -> 0 | BP23: =IF((BO23-($BR23*(NETWORKDAYS($BX$12,$BY$12)/$O$1))+BY23)<=0,0,BO23-($BR23*(NETWORKDAYS($BX$12,$BY$12)/$O$1))+BY23) -> 756 | BQ23: =IF((BP23-($BR23*(NETWORKDAYS($BY$12,$BZ$12)/$O$1))+BZ23)<=0,0,BP23-($BR23*(NETWORKDAYS($BY$12,$BZ$12)/$O$1))+BZ23) -> 979.66667 | BR23: 250 | BS23: =+BR23*1.1 -> 275 | BT23: =+AE23/BR23 -> 0 | BU23: =+BO23/BR23 -> 0 | BV23: =+BP23/BR23 -> 3.024 | BW23: =+BQ23/BR23 -> 3.9186667 | BY23: 756 | BZ23: 432 | CA23: 54 | CB23: 8 | CC23: =+CB23*CA23 -> 432
D24: TOTAL WERNSING | F24: =+SUM(F13:F22) -> 3098.5 | G24: =+SUM(G13:G22) -> 0 | H24: =+SUM(H13:H22) -> 4767 | I24: =+SUM(I13:I22) -> 0 | J24: =+SUM(J13:J22) -> 1695.75 | K24: =+SUM(K13:K22) -> 6169.75 | L24: =+SUM(L13:L22) -> 0 | M24: =+SUM(M13:M22) -> 0 | ... BN24: =+SUM(BN13:BN22) -> 0 | BR24: =+BR13+BR15+BR16+BR19+BR20+BR22 -> 2284.0625 | BS24: =+BS14+BS15+BS16+BS19+BS20+BS22 -> 2639.3317 | BX24: =SUM(BX13:BX22) -> 2376 | BY24: =SUM(BY13:BY23) -> 2268 | BZ24: =SUM(BZ13:BZ23) -> 1992 | CB24: =SUM(CB13:CB23) -> 21 | CC24: =SUM(CC14:CC23) -> 1992
D26: RESUMEN DEL TOTAL DE PAPAS | F26: =+F24+F10 -> 4442.75 | G26: =+G24+G10 -> 0 | H26: =+H24+H10 -> 4767 | I26: =+I24+I10 -> 0 | J26: =+J24+J10 -> 1803 | K26: =+K24+K10 -> 7406.75 | L26: =+L24+L10 -> 0 | M26: =+M24+M10 -> 0 | ... BN26: =+BN24+BN10 -> 0
F27: =+F26/50 -> 88.855 | J27: ESPACIOS | K27: =+K26/50 -> 148.135 | O27: ESPACIOS | P27: =+P26/50 -> 112.6 | T27: ESPACIOS | U27: =+U26/50 -> 57.505 | Y27: ESPACIOS | Z27: =+Z26/BR24 -> 1.3906143 | AD27: ESPACIOS | AE27: =+AE26/50 -> 53.84 | AI27: ESPACIOS | AJ27: =+AJ26/50 -> 0 | AN27: ESPACIOS | AO27: =+AO26/50 -> 0 | AS27: ESPACIOS | AT27: =+AT26/50 -> 0 | AX27: ESPACIOS | AY27: =+AY26/50 -> 0 | BC27: ESPACIOS | BD27: =+BD26/50 -> 0 | BH27: ESPACIOS | BI27: =+BI26/50 -> 0 | BM27: ESPACIOS | BN27: =+BN26/50 -> 0 | BO27: =+AE26/Y26 -> 1.3080661
K28: =+K26/BR24 -> 3.2427966

Sheet RESUMEN CDMX
AI1: CONTENEDORES EN TRANSITO | AK1: SUGERENCIA DE PEDIDOS, DE CONTENEDOR A 21 PALLET
O2: 45 | Z2: INV ACTUAL + CONTENEDORES EN TRANSITO - VENTAS | AC2: VENTAS | AD2: Consumo mensual, Promedio año en curso | AE2: Proyeccion de Ventas, con 10% al promedio del consumo mensual | AF2: Duracion de Inv. En Meses Considerando Inv Actual + Contenedores en Transito - Ventas | AI2: C-426 PTO 31/05 | AJ2: C-429 PTO 20/06 | AK2: Cjas x Tarima
A3: PROMEDIO DÍAS DE TRANSITO | B3: PROVEEDOR | C3: ESTATUS DEL PRODUCTO | D3: CÓDIGO | E3: DESCRIPCIÓN | F3: INV DICIEMBRE 2025 | G3: COMPRAS | H3: Entradas | I3: Salidas | J3: VENTAS | K3: INV ENERO 2026 | L3: COMPRAS | M3: Entradas | N3: Salidas | O3: VENTAS | P3: INV FEB 2026 | Q3: COMPRAS | R3: Entradas | S3: Salidas | T3: VENTAS | U3: INV MAYO ARCOSA 2026 | V3: FRIGARSA | W3: FRESCO | X3: MEXIDELI | Y3: TOTAL CDMX | Z3: ACTUAL | AA3: C-426 | AB3: C-429 | AC3: MAYO | AF3: ACTUAL | AG3: C-426 | AH3: C-429 | AI3: 46178 | AJ3: 46199 | AL3: PALLET | AM3: CAJAS
A4: 60 | B4: AVIKO | C4: ACTIVO | D4: 806685 | E4: AVIKO H PREM.CRUNCH SHOESTRING 7MM 4X2270G | F4: 144 | J4: 144 | K4: =+F4+G4+H4-I4-J4 -> 0 | P4: =+K4+L4+M4-N4-O4 -> 0 | U4: =+P4+Q4+R4-S4-T4 -> 0 | V4: =+FRIGARSA!AB3 -> 2.3 | W4: =+FRESCO!BU4 -> 2 | X4: =+MEXIDELI!AB3 -> 938 | Y4: =SUM(U4++V4+W4+X4) -> 942.3 | Z4: =+Y4 -> 942.3 | AA4: =IF((Z4-($AD4*(NETWORKDAYS($AI$3,$AI$3)/$O$2))+AI4)<=0,0,Z4-($AD4*(NETWORKDAYS($AI$3,$AI$3)/$O$2))+AI4) -> 1345.4111 | AB4: =IF((AA4-($AD4*(NETWORKDAYS($AI$3,$AJ$3)/$O$2))+AJ4)<=0,0,AA4-($AD4*(NETWORKDAYS($AJ$3,$AI$3)/$O$2))+AJ4) -> 2671.6333 | AC4: =+MEXIDELI!AA3+FRESCO!BTO4+FRIGARSA!AA3 -> 342 | AD4: 1300 | AF4: =+Y4/AD4 -> 0.72484615 | AG4: =+AA4/AD4 -> 1.0349316 | AH4: =+AB4/AD4 -> 2.0551026 | AI4: 432 | AJ4: 864 | AK4: 108 | AM4: =+AL4*AK4 -> 0 | AN4: =+AG4-1.4 -> -0.36506838 | AO4: 1.5 | AP4: =+AO4-AN4 -> 1.8650684 | AQ4: =+AP4*AD4 -> 2424.5889
A5: 60 | B5: AVIKO | C5: ACTIVO | D5: 806939 | E5: AVIKO CRINKLE CUT 12MM 4 X 2.5 KG | F5: 0 | K5: =+F5+G5+H5-I5-J5 -> 0 | P5: =+K5+L5+M5-N5-O5 -> 0 | U5: =+P5+Q5+R5-S5-T5 -> 0 | V5: =+FRIGARSA!AB4 -> 9 | W5: =+FRESCO!BP5 -> 0 | X5: =+MEXIDELI!AB4+CANBELT!AB3 -> 206 | Y5: =SUM(U5++V5+W5+X5) -> 215 | Z5: =+Y5 -> 215 | AA5: =IF((Z5-($AD5*(NETWORKDAYS($AI$3,$AI$3)/$O$2))+AI5)<=0,0,Z5-($AD5*(NETWORKDAYS($AI$3,$AI$3)/$O$2))+AI5) -> 212.11111 | AB5: =IF((AA5-($AD5*(NETWORKDAYS($AI$3,$AJ$3)/$O$2))+AJ5)<=0,0,AA5-($AD5*(NETWORKDAYS($AJ$3,$AI$3)/$O$2))+AJ5) -> 258.33333 | AC5: =+MEXIDELI!AA4+FRESCO!BTO5+FRIGARSA!AA4+CANBELT!AA3 -> 24 | AD5: 130 | AF5: =+Y5/AD5 -> 1.6538462 | AG5: =+AA5/AD5 -> 1.6316239 | AH5: =+AB5/AD5 -> 1.9871795 | AI5: 0 | AJ5: 0 | AK5: 108 | AM5: =+AL5*AK5 -> 0 | AN5: =+AG5-1.4 -> 0.23162393 | AO5: 1.5 | AP5: =+AO5-AN5 -> 1.2683761 | AQ5: =+AP5*AD5 -> 164.88889
A6: 60 | B6: AVIKO | C6: ACTIVO | D6: 806694 | E6: AVIKO SUPER CRUNCH 9.5mm 3/8 4x2500g | F6: 0 | K6: =+F6+G6+H6-I6-J6 -> 0 | P6: =+K6+L6+M6-N6-O6 -> 0 | U6: =+P6+Q6+R6-S6-T6 -> 0 | V6: =+FRIGARSA!W5 -> 0 | W6: =+FRESCO!BP6 -> 0 | X6: =+MEXIDELI!AB5 -> 166 | Y6: =SUM(U6++V6+W6+X6) -> 166 | Z6: =+Y6 -> 166 | AA6: =IF((Z6-($AD6*(NETWORKDAYS($AI$3,$AI$3)/$O$2))+AI6)<=0,0,Z6-($AD6*(NETWORKDAYS($AI$3,$AI$3)/$O$2))+AI6) -> 164.33333 | AB6: =IF((AA6-($AD6*(NETWORKDAYS($AI$3,$AJ$3)/$O$2))+AJ6)<=0,0,AA6-($AD6*(NETWORKDAYS($AJ$3,$AI$3)/$O$2))+AJ6) -> 275 | AC6: =+MEXIDELI!AA5+FRESCO!BTO6+FRIGARSA!AA5 -> 10 | AD6: 75 | AF6: =+Y6/AD6 -> 2.2133333 | AG6: =+AA6/AD6 -> 2.1911111 | AH6: =+AB6/AD6 -> 3.6666667 | AI6: 0 | AJ6: 84 | AK6: 84 | AM6: =+AL6*AK6 -> 0 | AN6: =+AG6-1.4 -> 0.79111111 | AO6: 1.5 | AP6: =+AO6-AN6 -> 0.70888889 | AQ6: =+AP6*AD6 -> 53.166667
A7: 60 | B7: AVIKO | C7: INACTIVO | D7: 804104 | E7: HASHBROWN TRIANG | F7: 0 | K7: =+F7+G7+H7-I7-J7 -> 0 | P7: =+K7+L7+M7-N7-O7 -> 0 | U7: =+P7+Q7+R7-S7-T7 -> 0 | V7: =+FRIGARSA!AB6 -> 7 | X7: =+MEXIDELI!W6 -> 0 | Y7: =SUM(U7++V7+W7+X7) -> 7 | Z7: =+Y7 -> 7 | AA7: =IF((Z7-($AD7*(NETWORKDAYS($AI$3,$AI$3)/$O$2))+AI7)<=0,0,Z7-($AD7*(NETWORKDAYS($AI$3,$AI$3)/$O$2))+AI7) -> 6.8444444 | AB7: =IF((AA7-($AD7*(NETWORKDAYS($AI$3,$AJ$3)/$O$2))+AJ7)<=0,0,AA7-($AD7*(NETWORKDAYS($AJ$3,$AI$3)/$O$2))+AJ7) -> 9.3333333 | AC7: =+MEXIDELI!AA6+FRESCO!BTO7+FRIGARSA!AA6 -> 0 | AD7: 7 | AG7: =+AA7/AD7 -> 0.97777778 | AH7: =+AB7/AD7 -> 1.3333333 | AI7: 0 | AJ7: 0 | AK7: 108 | AM7: =+AL7*AK7 -> 0 | AN7: =+AG7-1.4 -> -0.42222222 | AO7: 1.5 | AP7: =+AO7-AN7 -> 1.9222222 | AQ7: =+AP7*AD7 -> 13.455556
A8: 60 | B8: AVIKO | C8: ACTIVO | D8: 806686 | E8: AVIKO H PREM CRUNCH 9.5 mm 3/8 4x2270g | F8: 233 | I8: 72 | K8: =+F8+G8+H8-I8-J8 -> 161 | O8: 49 | P8: =+K8+L8+M8-N8-O8 -> 112 | S8: 112 | U8: =+P8+Q8+R8-S8-T8 -> 0 | V8: =+FRIGARSA!AB7 -> 47 | W8: 12 | X8: =+MEXIDELI!W7 -> 0 | Y8: =SUM(U8++V8+W8+X8) -> 59 | Z8: =+Y8 -> 59 | AA8: =IF((Z8-($AD8*(NETWORKDAYS($AI$3,$AI$3)/$O$2))+AI8)<=0,0,Z8-($AD8*(NETWORKDAYS($AI$3,$AI$3)/$O$2))+AI8) -> 272.77778 | AB8: =IF((AA8-($AD8*(NETWORKDAYS($AI$3,$AJ$3)/$O$2))+AJ8)<=0,0,AA8-($AD8*(NETWORKDAYS($AJ$3,$AI$3)/$O$2))+AJ8) -> 308.33333 | AC8: =+MEXIDELI!AA7+FRESCO!BTO8+FRIGARSA!AA7 -> 0 | AD8: 100 | AF8: =+Y8/AD8 -> 0.59 | AG8: =+AA8/AD8 -> 2.7277778 | AH8: =+AB8/AD8 -> 3.0833333 | AI8: 216 | AJ8: 0 | AK8: 108 | AM8: =+AL8*AK8 -> 0 | AN8: =+AG8-1.4 -> 1.3277778 | AO8: 1.5 | AP8: =+AO8-AN8 -> 0.17222222 | AQ8: =+AP8*AD8 -> 17.222222
A9: 60 | B9: AVIKO | C9: ACTIVO | D9: 804109 | E9: AVIKO SHOESTRING 5x2500g | F9: 89 | I9: 87 | J9: 1 | K9: =+F9+G9+H9-I9-J9 -> 1 | P9: =+K9+L9+M9-N9-O9 -> 1 | S9: 1 | U9: =+P9+Q9+R9-S9-T9 -> 0 | V9: =+FRIGARSA!AB8 -> 6.5 | W9: =+FRESCO!BP9 -> 0 | X9: =+MEXIDELI!W8 -> 46 | Y9: =SUM(U9++V9+W9+X9) -> 52.5 | Z9: =+Y9 -> 52.5 | AA9: =IF((Z9-($AD9*(NETWORKDAYS($AI$3,$AI$3)/$O$2))+AI9)<=0,0,Z9-($AD9*(NETWORKDAYS($AI$3,$AI$3)/$O$2))+AI9) -> 300.05556 | AB9: =IF((AA9-($AD9*(NETWORKDAYS($AI$3,$AJ$3)/$O$2))+AJ9)<=0,0,AA9-($AD9*(NETWORKDAYS($AJ$3,$AI$3)/$O$2))+AJ9) -> 539.16667 | AC9: =+MEXIDELI!AA8+FRESCO!BTO9+FRIGARSA!AA8 -> 6 | AD9: 200 | AF9: =+Y9/AD9 -> 0.2625 | AG9: =+AA9/AD9 -> 1.5002778 | AH9: =+AB9/AD9 -> 2.6958333 | AI9: 252 | AJ9: 168 | AK9: 84 | AM9: =+AL9*AK9 -> 0 | AN9: =+AG9-1.4 -> 0.10027778 | AO9: 1.5 | AP9: =+AO9-AN9 -> 1.3997222 | AQ9: =+AP9*AD9 -> 279.94444
A10: 60 | B10: AVIKO | C10: ACTIVO | D10: 806980 | E10: AVIKO SPICY JACKET WEDGES 4x2500g | F10: 100 | I10: 71 | J10: 4 | K10: =+F10+G10+H10-I10-J10 -> 25 | P10: =+K10+L10+M10-N10-O10 -> 25 | S10: 25 | U10: =+P10+Q10+R10-S10-T10 -> 0 | V10: =+FRIGARSA!AB9 -> 2 | W10: =+FRESCO!BP10 -> 0 | X10: =+MEXIDELI!AB9 -> 56 | Y10: =SUM(U10++V10+W10+X10) -> 58 | Z10: =+Y10 -> 58 | AA10: =IF((Z10-($AD10*(NETWORKDAYS($AI$3,$AI$3)/$O$2))+AI10)<=0,0,Z10-($AD10*(NETWORKDAYS($AI$3,$AI$3)/$O$2))+AI10) -> 176.88889 | AB10: =IF((AA10-($AD10*(NETWORKDAYS($AI$3,$AJ$3)/$O$2))+AJ10)<=0,0,AA10-($AD10*(NETWORKDAYS($AJ$3,$AI$3)/$O$2))+AJ10) -> 194.66667 | AC10: =+MEXIDELI!AA9+FRESCO!BTO10+FRIGARSA!AA9 -> 2 | AD10: 50 | AF10: =+Y10/AD10 -> 1.16 | AG10: =+AA10/AD10 -> 3.5377778 | AH10: =+AB10/AD10 -> 3.8933333 | AI10: 120 | AJ10: 0 | AK10: 108 | AM10: =+AL10*AK10 -> 0 | AN10: =+AG10-1.4 -> 2.1377778 | AO10: 1.5 | AP10: =+AO10-AN10 -> -0.63777778 | AQ10: =+AP10*AD10 -> -31.888889
A11: 60 | B11: AVIKO | C11: ACTIVO | D11: 806982 | E11: AROS DE CEBOLLA 1X1000g | F11: 50 | K11: =+F11+G11+H11-I11-J11 -> 50 | P11: =+K11+L11+M11-N11-O11 -> 50 | S11: 50 | U11: =+P11+Q11+R11-S11-T11 -> 0 | V11: =+FRIGARSA!AB10 -> 37 | W11: =+FRESCO!BP11 -> 0 | X11: =+MEXIDELI!AB10 -> 108 | Y11: =SUM(U11++V11+W11+X11) -> 145 | Z11: =+Y11 -> 145 | AA11: =IF((Z11-($AD11*(NETWORKDAYS($AI$3,$AI$3)/$O$2))+AI11)<=0,0,Z11-($AD11*(NETWORKDAYS($AI$3,$AI$3)/$O$2))+AI11) -> 143.88889 | AB11: =IF((AA11-($AD11*(NETWORKDAYS($AI$3,$AJ$3)/$O$2))+AJ11)<=0,0,AA11-($AD11*(NETWORKDAYS($AJ$3,$AI$3)/$O$2))+AJ11) -> 161.66667 | AC11: =+MEXIDELI!AA10+FRESCO!BTO11+FRIGARSA!AA10 -> 0 | AD11: 50 | AF11: =+Y11/AD11 -> 2.9 | AG11: =+AA11/AD11 -> 2.8777778 | AH11: =+AB11/AD11 -> 3.2333333 | AI11: 0 | AJ11: 0 | AK11: 84 | AM11: =+AL11*AK11 -> 0 | AN11: =+AG11-1.4 -> 1.4777778 | AO11: 1.5 | AP11: =+AO11-AN11 -> 0.022222222 | AQ11: =+AP11*AD11 -> 1.1111111
A12: 60 | B12: AVIKO | C12: OPORTUNIDAD | D12: 260612 | E12: CASTEL STRAIGHT CUT FRIES 4X2500g | F12: 66 | K12: =+F12+G12+H12-I12-J12 -> 66 | P12: =+K12+L12+M12-N12-O12 -> 66 | S12: 48 | T12: 18 | U12: =+P12+Q12+R12-S12-T12 -> 0 | V12: =+FRIGARSA!AB11 -> 4 | W12: =+FRESCO!BP12 -> 0 | X12: =+MEXIDELI!W11 -> 0 | Y12: =SUM(U12++V12+W12+X12) -> 4 | Z12: =+Y12 -> 4 | AA12: =IF((Z12-($AD12*(NETWORKDAYS($AI$3,$AI$3)/$O$2))+AI12)<=0,0,Z12-($AD12*(NETWORKDAYS($AI$3,$AI$3)/$O$2))+AI12) -> 3.9777778 | AB12: =IF((AA12-($AD12*(NETWORKDAYS($AI$3,$AJ$3)/$O$2))+AJ12)<=0,0,AA12-($AD12*(NETWORKDAYS($AJ$3,$AI$3)/$O$2))+AJ12) -> 4.3333333 | AC12: =+MEXIDELI!AA11+FRESCO!BTO12+FRIGARSA!AA11 -> 0 | AD12: 1 | AF12: =+Y12/AD12 -> 4 | AG12: =+AA12/AD12 -> 3.9777778 | AH12: =+AB12/AD12 -> 4.3333333 | AI12: 0 | AJ12: 0 | AK12: 120 | AM12: =+AL12*AK12 -> 0 | AN12: =+AG12-1.4 -> 2.5777778 | AO12: 1.5 | AP12: =+AO12-AN12 -> -1.0777778 | AQ12: =+AP12*AD12 -> -1.0777778
A13: 60 | B13: AVIKO | C13: OPORTUNIDAD | D13: 804661 | E13: AVIKO STEAK FRIES 4X2500G 4X5.5 LBS | F13: 0 | K13: =+F13+G13+H13-I13-J13 -> 0 | P13: =+K13+L13+M13-N13-O13 -> 0 | U13: =+P13+Q13+R13-S13-T13 -> 0 | V13: =+FRIGARSA!AB12 -> 510 | W13: =+FRESCO!BP13 -> 0 | X13: =+MEXIDELI!W12 -> 0 | Y13: =SUM(U13++V13+W13+X13) -> 510 | Z13: =+Y13 -> 510 | AA13: =IF((Z13-($AD13*(NETWORKDAYS($AI$3,$AI$3)/$O$2))+AI13)<=0,0,Z13-($AD13*(NETWORKDAYS($AI$3,$AI$3)/$O$2))+AI13) -> 508.88889 | AB13: =IF((AA13-($AD13*(NETWORKDAYS($AI$3,$AJ$3)/$O$2))+AJ13)<=0,0,AA13-($AD13*(NETWORKDAYS($AJ$3,$AI$3)/$O$2))+AJ13) -> 526.66667 | AC13: =+MEXIDELI!AA12+FRESCO!BTO13+FRIGARSA!AA12 -> 20 | AD13: 50 | AF13: =+Y13/AD13 -> 10.2 | AG13: =+AA13/AD13 -> 10.177778 | AH13: =+AB13/AD13 -> 10.533333 | AI13: 0 | AJ13: 0 | AM13: =+AL13*AK13 -> 0 | AN13: =+AG13-1.4 -> 8.7777778 | AO13: 1.5 | AP13: =+AO13-AN13 -> -7.2777778 | AQ13: =+AP13*AD13 -> -363.88889
A14: 60 | B14: AVIKO | C14: OPORTUNIDAD | D14: 806702 | E14: AVIKO H SUPER CRUNCH 15mm 6x2500g | F14: 0 | K14: =+F14+G14+H14-I14-J14 -> 0 | P14: =+K14+L14+M14-N14-O14 -> 0 | U14: =+P14+Q14+R14-S14-T14 -> 0 | V14: =+FRIGARSA!AB13 -> 87 | W14: =+FRESCO!BP14 -> 0 | X14: =+MEXIDELI!W13 -> 0 | Y14: =SUM(U14++V14+W14+X14) -> 87 | Z14: =+Y14 -> 87 | AA14: =IF((Z14-($AD14*(NETWORKDAYS($AI$3,$AI$3)/$O$2))+AI14)<=0,0,Z14-($AD14*(NETWORKDAYS($AI$3,$AI$3)/$O$2))+AI14) -> 86.444444 | AB14: =IF((AA14-($AD14*(NETWORKDAYS($AI$3,$AJ$3)/$O$2))+AJ14)<=0,0,AA14-($AD14*(NETWORKDAYS($AJ$3,$AI$3)/$O$2))+AJ14) -> 95.333333 | AC14: =+MEXIDELI!AA13+FRESCO!BTO14+FRIGARSA!AA13 -> 0 | AD14: 25 | AF14: =+Y14/AD14 -> 3.48 | AG14: =+AA14/AD14 -> 3.4577778 | AH14: =+AB14/AD14 -> 3.8133333 | AI14: 0 | AJ14: 0 | AK14: 120 | AM14: =+AL14*AK14 -> 0 | AN14: =+AG14-1.4 -> 2.0577778 | AO14: 1.5 | AP14: =+AO14-AN14 -> -0.55777778 | AQ14: =+AP14*AD14 -> -13.944444
A15: 60 | B15: KAIDA | C15: ACTIVO | D15: 505015 | E15: 10 MM NATURAL-KAIDA | U15: =+P15+Q15+R15-S15-T15 -> 0 | W15: =+FRESCO!BP13 -> 0 | X15: =+MEXIDELI!AB21 -> 811 | Y15: =SUM(U15++V15+W15+X15) -> 811 | Z15: =+Y15 -> 811 | AA15: =IF((Z15-($AD15*(NETWORKDAYS($AI$3,$AI$3)/$O$2))+AI15)<=0,0,Z15-($AD15*(NETWORKDAYS($AI$3,$AI$3)/$O$2))+AI15) -> 806.55556 | AB15: =IF((AA15-($AD15*(NETWORKDAYS($AI$3,$AJ$3)/$O$2))+AJ15)<=0,0,AA15-($AD15*(NETWORKDAYS($AJ$3,$AI$3)/$O$2))+AJ15) -> 877.66667 | AC15: =+MEXIDELI!AA14+FRESCO!BTO15+FRIGARSA!AA14 -> 0 | AD15: 200 | AF15: =+Y15/AD15 -> 4.055 | AG15: =+AA15/AD15 -> 4.0327778 | AH15: =+AB15/AD15 -> 4.3883333 | AJ15: 0
E16: RETAIL | AC16: =+MEXIDELI!AA15+FRESCO!BTO16+FRIGARSA!AA15 -> 0 | AJ16: 0
A17: 60 | B17: AVIKO | C17: ACTIVO | D17: 807769 | E17: PAPAS FRITAS CORTE REG 10 X 1000G | F17: 72 | H17: 72 | J17: =48+6.2 -> 54.2 | K17: =+F17+G17+H17-I17-J17 -> 89.8 | O17: 34 | P17: =+K17+L17+M17-N17-O17 -> 55.8 | S17: 55.8 | U17: =+P17+Q17+R17-S17-T17 -> 0 | V17: =+FRIGARSA!AB14 -> 219 | W17: =+FRESCO!BU15 -> 737 | X17: =+MEXIDELI!W14 -> 0 | Y17: =SUM(U17++V17+W17+X17) -> 956 | Z17: =+Y17 -> 956 | AA17: =IF((Z17-($AD17*(NETWORKDAYS($AI$3,$AI$3)/$O$2))+AI17)<=0,0,Z17-($AD17*(NETWORKDAYS($AI$3,$AI$3)/$O$2))+AI17) -> 950.44444 | AB17: =IF((AA17-($AD17*(NETWORKDAYS($AI$3,$AJ$3)/$O$2))+AJ17)<=0,0,AA17-($AD17*(NETWORKDAYS($AJ$3,$AI$3)/$O$2))+AJ17) -> 1039.3333 | AC17: =+MEXIDELI!AA16+FRESCO!BTO17+FRIGARSA!AA16 -> 0 | AD17: 250 | AF17: =+Y17/AD17 -> 3.824 | AG17: =+AA17/AD17 -> 3.8017778 | AH17: =+AB17/AD17 -> 4.1573333 | AI17: 0 | AJ17: 0 | AK17: 120 | AM17: =+AL17*AK17 -> 0 | AN17: =+AG17-1.4 -> 2.4017778 | AO17: 1.5 | AP17: =+AO17-AN17 -> -0.90177778 | AQ17: =+AP17*AD17 -> -225.44444
A18: 60 | B18: AVIKO | C18: ACTIVO | D18: 807329 | E18: AVIKO ORIGINAL 20X450G | F18: 471 | J18: 78 | K18: =+F18+G18+H18-I18-J18 -> 393 | O18: 71 | P18: =+K18+L18+M18-N18-O18 -> 322 | S18: 322 | U18: =+P18+Q18+R18-S18-T18 -> 0 | V18: =+FRIGARSA!W15 -> 0 | W18: =+FRESCO!BU16 -> 179 | X18: =+MEXIDELI!AB15 -> 164 | Y18: =SUM(U18++V18+W18+X18) -> 343 | Z18: =+Y18 -> 343 | AA18: =IF((Z18-($AD18*(NETWORKDAYS($AI$3,$AI$3)/$O$2))+AI18)<=0,0,Z18-($AD18*(NETWORKDAYS($AI$3,$AI$3)/$O$2))+AI18) -> 339.66667 | AB18: =IF((AA18-($AD18*(NETWORKDAYS($AI$3,$AJ$3)/$O$2))+AJ18)<=0,0,AA18-($AD18*(NETWORKDAYS($AJ$3,$AI$3)/$O$2))+AJ18) -> 513 | AC18: =+MEXIDELI!AA17+FRESCO!BTO18+FRIGARSA!AA17 -> 0 | AD18: 150 | AF18: =+Y18/AD18 -> 2.2866667 | AG18: =+AA18/AD18 -> 2.2644444 | AH18: =+AB18/AD18 -> 3.42 | AI18: 0 | AJ18: 120 | AK18: 120 | AM18: =+AL18*AK18 -> 0 | AN18: =+AG18-1.4 -> 0.86444444 | AO18: 1.5 | AP18: =+AO18-AN18 -> 0.63555556 | AQ18: =+AP18*AD18 -> 95.333333
A19: 60 | B19: AVIKO | C19: ACTIVO | D19: 805411 | E19: PAPAS FRITAS ZIGZAG 12/750GRS | F19: 440 | J19: 163 | K19: =+F19+G19+H19-I19-J19 -> 277 | O19: 77 | P19: =+K19+L19+M19-N19-O19 -> 200 | S19: 200 | U19: =+P19+Q19+R19-S19-T19 -> 0 | V19: =+FRIGARSA!W16 -> 0 | W19: =+FRESCO!BU17 -> 164 | X19: =+MEXIDELI!AB16 -> 165 | Y19: =SUM(U19++V19+W19+X19) -> 329 | Z19: =+Y19 -> 329 | AA19: =IF((Z19-($AD19*(NETWORKDAYS($AI$3,$AI$3)/$O$2))+AI19)<=0,0,Z19-($AD19*(NETWORKDAYS($AI$3,$AI$3)/$O$2))+AI19) -> 777.22222 | AB19: =IF((AA19-($AD19*(NETWORKDAYS($AI$3,$AJ$3)/$O$2))+AJ19)<=0,0,AA19-($AD19*(NETWORKDAYS($AJ$3,$AI$3)/$O$2))+AJ19) -> 973.66667 | AC19: =+MEXIDELI!AA18+FRESCO!BTO19+FRIGARSA!AA18 -> 0 | AD19: 350 | AF19: =+Y19/AD19 -> 0.94 | AG19: =+AA19/AD19 -> 2.2206349 | AH19: =+AB19/AD19 -> 2.7819048 | AI19: 456 | AJ19: =432-360 -> 72 | AK19: 108 | AM19: =+AL19*AK19 -> 0 | AN19: =+AG19-1.4 -> 0.82063492 | AO19: 1.5 | AP19: =+AO19-AN19 -> 0.67936508 | AQ19: =+AP19*AD19 -> 237.77778
A20: 60 | B20: AVIKO | C20: ACTIVO | D20: 807679 | E20: AVIKO SPICY WEDGES 20X500G | F20: 33 | H20: 72 | J20: 79 | K20: =+F20+G20+H20-I20-J20 -> 26 | O20: 9 | P20: =+K20+L20+M20-N20-O20 -> 17 | S20: 17 | U20: =+P20+Q20+R20-S20-T20 -> 0 | V20: =+FRIGARSA!W17 -> 0 | W20: =+FRESCO!BU18 -> 33 | X20: =+MEXIDELI!AB17 -> 126 | Y20: =SUM(U20++V20+W20+X20) -> 159 | Z20: =+Y20 -> 159 | AA20: =IF((Z20-($AD20*(NETWORKDAYS($AI$3,$AI$3)/$O$2))+AI20)<=0,0,Z20-($AD20*(NETWORKDAYS($AI$3,$AI$3)/$O$2))+AI20) -> 155.66667 | AB20: =IF((AA20-($AD20*(NETWORKDAYS($AI$3,$AJ$3)/$O$2))+AJ20)<=0,0,AA20-($AD20*(NETWORKDAYS($AJ$3,$AI$3)/$O$2))+AJ20) -> 449 | AC20: =+MEXIDELI!AA19+FRESCO!BTO20+FRIGARSA!AA19 -> 0 | AD20: 150 | AF20: =+Y20/AD20 -> 1.06 | AG20: =+AA20/AD20 -> 1.0377778 | AH20: =+AB20/AD20 -> 2.9933333 | AI20: 0 | AJ20: =600+-360 -> 240 | AK20: 120 | AM20: =+AL20*AK20 -> 0 | AN20: =+AG20-1.4 -> -0.36222222 | AO20: 1.5 | AP20: =+AO20-AN20 -> 1.8622222 | AQ20: =+AP20*AD20 -> 279.33333
A21: 60 | B21: AVIKO | C21: ACTIVO | D21: 805168 | E21: AVIKO AROS DE CEBOLLA PREFRITOS 25/400g | F21: 403 | J21: 6 | K21: =+F21+G21+H21-I21-J21 -> 397 | P21: =+K21+L21+M21-N21-O21 -> 397 | S21: 397 | U21: =+P21+Q21+R21-S21-T21 -> 0 | V21: =+FRIGARSA!W18 -> 0 | W21: =+FRESCO!BU19 -> 96 | X21: =+MEXIDELI!AB18 -> 301 | Y21: =SUM(U21++V21+W21+X21) -> 397 | Z21: =+Y21 -> 397 | AA21: =IF((Z21-($AD21*(NETWORKDAYS($AI$3,$AI$3)/$O$2))+AI21)<=0,0,Z21-($AD21*(NETWORKDAYS($AI$3,$AI$3)/$O$2))+AI21) -> 395.53333 | AB21: =IF((AA21-($AD21*(NETWORKDAYS($AI$3,$AJ$3)/$O$2))+AJ21)<=0,0,AA21-($AD21*(NETWORKDAYS($AJ$3,$AI$3)/$O$2))+AJ21) -> 419 | AC21: =+MEXIDELI!AA20+FRESCO!BTO21+FRIGARSA!AA20 -> 0 | AD21: 66 | AF21: =+Y21/AD21 -> 6.0151515 | AG21: =+AA21/AD21 -> 5.9929293 | AH21: =+AB21/AD21 -> 6.3484848 | AI21: 0 | AJ21: 0 | AN21: =+AG21-1.4 -> 4.5929293 | AO21: 1.5 | AP21: =+AO21-AN21 -> -3.0929293 | AQ21: =+AP21*AD21 -> -204.13333
A22: 60 | B22: AVIKO | C22: INACTIVO | D22: 807363 | E22: Aviko H Super Crunch 14x600g | K22: =+F22+G22+H22-I22-J22 -> 0 | P22: =+K22+L22+M22-N22-O22 -> 0 | U22: =+P22+Q22+R22-S22-T22 -> 0 | V22: =+FRIGARSA!W19 -> 0 | W22: =+FRESCO!BP20 -> 0 | X22: =+MEXIDELI!W19 -> 0 | Y22: =SUM(U22++V22+W22+X22) -> 0 | Z22: =+Y22 -> 0 | AA22: =IF((Z22-($AD22*(NETWORKDAYS($AI$3,$AI$3)/$O$2))+AI22)<=0,0,Z22-($AD22*(NETWORKDAYS($AI$3,$AI$3)/$O$2))+AI22) -> 0 | AB22: =IF((AA22-($AD22*(NETWORKDAYS($AJ$3,$AJ$3)/$O$2))+AJ22)<=0,0,AA22-($AD22*(NETWORKDAYS($AJ$3,$AJ$3)/$O$2))+AJ22) -> 0 | AC22: =+MEXIDELI!AA21+FRESCO!BTO22+FRIGARSA!AA21 -> 7 | AD22: 0 | AH22: =+AB22/AD22 -> #DIV/0! | AI22: 0 | AJ22: 0
A23: 60 | B23: AVIKO | C23: ACTIVO | D23: 809529 | E23: Aviko SC Airfr. PommesFrites 10x750 | K23: =+F23+G23+H23-I23-J23 -> 0 | P23: =+K23+L23+M23-N23-O23 -> 0 | U23: =+P23+Q23+R23-S23-T23 -> 0 | V23: =+FRIGARSA!W20 -> 0 | W23: =+FRESCO!BU21 -> 391 | X23: =+MEXIDELI!W20 -> 0 | Y23: =SUM(U23++V23+W23+X23) -> 391 | Z23: =+Y23 -> 391 | AA23: =IF((Z23-($AD23*(NETWORKDAYS($AI$3,$AI$3)/$O$2))+AI23)<=0,0,Z23-($AD23*(NETWORKDAYS($AI$3,$AI$3)/$O$2))+AI23) -> 390.73333 | AB23: =IF((AA23-($AD23*(NETWORKDAYS($AI$3,$AJ$3)/$O$2))+AJ23)<=0,0,AA23-($AD23*(NETWORKDAYS($AJ$3,$AI$3)/$O$2))+AJ23) -> 395 | AC23: =+MEXIDELI!AA22+FRESCO!BTO23+FRIGARSA!AA22 -> 0 | AD23: 12 | AF23: =+Y23/AD23 -> 32.583333 | AG23: =+AA23/AD23 -> 32.561111 | AH23: =+AB23/AD23 -> 32.916667 | AI23: 0 | AJ23: 0
U24: =+P24+Q24+R24-S24-T24 -> 0 | W24: =+FRESCO!BP23 -> 0 | Y24: =SUM(U24++V24+W24+X24) -> 0 | Z24: =+Y24 -> 0 | AA24: =IF((Z24-($AD24*(NETWORKDAYS($AI$3,$AI$3)/$O$2))+AI24)<=0,0,Z24-($AD24*(NETWORKDAYS($AI$3,$AI$3)/$O$2))+AI24) -> 0 | AB24: =IF((AA24-($AD24*(NETWORKDAYS($AJ$3,$AJ$3)/$O$2))+AJ24)<=0,0,AA24-($AD24*(NETWORKDAYS($AJ$3,$AJ$3)/$O$2))+AJ24) -> 0 | AH24: =+AB24/AD24 -> #DIV/0! | AK24: 120 | AM24: =+AL24*AK24 -> 0
U25: =+P25+Q25+R25-S25-T25 -> 0 | W25: =+FRESCO!BP24 -> 0 | Y25: =SUM(U25++V25+W25+X25) -> 0 | Z25: =+Y25 -> 0 | AA25: =IF((Z25-($AD25*(NETWORKDAYS($AI$3,$AI$3)/$O$2))+AI25)<=0,0,Z25-($AD25*(NETWORKDAYS($AI$3,$AI$3)/$O$2))+AI25) -> 0 | AB25: =IF((AA25-($AD25*(NETWORKDAYS($AJ$3,$AJ$3)/$O$2))+AJ25)<=0,0,AA25-($AD25*(NETWORKDAYS($AJ$3,$AJ$3)/$O$2))+AJ25) -> 0 | AH25: =+AB25/AD25 -> #DIV/0! | AK25: 108 | AM25: =+AL25*AK25 -> 0
D26: TOTAL AVIKO | F26: =+SUM(F4:F25) -> 2101 | G26: =+SUM(G4:G25) -> 0 | H26: =+SUM(H4:H25) -> 144 | I26: =+SUM(I4:I25) -> 230 | J26: =+SUM(J4:J25) -> 529.2 | K26: =+SUM(K4:K25) -> 1485.8 | L26: =+SUM(L4:L25) -> 0 | M26: =+SUM(M4:M25) -> 0 | ... Z26: =+SUM(Z4:Z25) -> 5631.8 | AC26: =SUM(AC4:AC25) -> 411 | AD26: =+SUM(AD4:AD25) -> 3166 | AE26: =+SUM(AE4:AE25) -> 0 | AF26: =+SUM(AF4:AF25) -> 77.948677 | AI26: =+SUM(AI4:AI25) -> 1476 | AJ26: =+SUM(AJ4:AJ25) -> 1548 | AK26: =+SUM(AK4:AK25) -> 1728 | AL26: =+SUM(AL4:AL25) -> 0 | AM26: =+SUM(AM4:AM25) -> 0
F28: =+F26 -> 2101 | G28: =+G26 -> 0 | H28: =+H26 -> 144 | I28: =+I26 -> 230 | J28: =+J26 -> 529.2 | K28: =+K26 -> 1485.8 | P28: =+P26 -> 1245.8 | V28: =+V26 -> 930.8 | W28: =+W26 -> 1614 | Y28: =+Y26 -> 5631.8
F29: =+F28/50 -> 42.02 | J29: ESPACIOS | Y29: =+Y28/1576 -> 3.5734772

Sheet FRIGARSA
A2: CÓDIGO | B2: DESCRIPCIÓN | C2: INV DICIEMBRE 2025 | D2: COMPRAS | E2: Entradas | F2: Salidas | G2: VENTAS | H2: INV ENERO 2026 | I2: COMPRAS | J2: Entradas | K2: Salidas | L2: VENTAS | M2: INV FEB 2026 | N2: COMPRAS | O2: Entradas | P2: Salidas | Q2: VENTAS | R2: INV MARZO 2026 | S2: COMPRAS | T2: Entradas | U2: Salidas | V2: VENTAS | W2: INV ABRIL 2026 | X2: COMPRAS | Y2: Entradas | Z2: Salidas | AA2: VENTAS | AB2: INV MAYO 2026
A3: 806685 | B3: AVIKO H PREM.CRUNCH SHOESTRING 7MM 4X2270G | C3: 45.3 | E3: 2004 | G3: 607 | H3: =+C3+D3+E3-F3-G3 -> 1442.3 | L3: 753 | M3: =+H3+I3+J3-K3-L3 -> 689.3 | O3: 25 | Q3: 687 | R3: =+M3+N3+O3-P3-Q3 -> 27.3 | V3: 25 | W3: =+R3+S3+T3-U3-V3 -> 2.3 | AB3: =+W3+X3+Y3-Z3-AA3 -> 2.3
A4: 806939 | B4: AVIKO CRINKLE CUT 12MM 4 X 2.5 KG | C4: 72 | G4: 58 | H4: =+C4+D4+E4-F4-G4 -> 14 | L4: 5 | M4: =+H4+I4+J4-K4-L4 -> 9 | R4: =+M4+N4+O4-P4-Q4 -> 9 | W4: =+R4+S4+T4-U4-V4 -> 9 | AB4: =+W4+X4+Y4-Z4-AA4 -> 9
A5: 806694 | B5: AVIKO SUPER CRUNCH 9.5mm 3/8 4x2500g | C5: 74 | G5: 74 | H5: =+C5+D5+E5-F5-G5 -> 0 | M5: =+H5+I5+J5-K5-L5 -> 0 | R5: =+M5+N5+O5-P5-Q5 -> 0 | W5: =+R5+S5+T5-U5-V5 -> 0 | AB5: =+W5+X5+Y5-Z5-AA5 -> 0
A6: 804104 | B6: HASHBROWN TRIANG | C6: 22 | G6: 1 | H6: =+C6+D6+E6-F6-G6 -> 21 | L6: 2 | M6: =+H6+I6+J6-K6-L6 -> 19 | Q6: 12 | R6: =+M6+N6+O6-P6-Q6 -> 7 | W6: =+R6+S6+T6-U6-V6 -> 7 | AB6: =+W6+X6+Y6-Z6-AA6 -> 7
A7: 806686 | B7: AVIKO H PREM CRUNCH 9.5 mm 3/8 4x2270g | C7: 5 | E7: 72 | G7: 30 | H7: =+C7+D7+E7-F7-G7 -> 47 | L7: 0 | M7: =+H7+I7+J7-K7-L7 -> 47 | R7: =+M7+N7+O7-P7-Q7 -> 47 | W7: =+R7+S7+T7-U7-V7 -> 47 | AB7: =+W7+X7+Y7-Z7-AA7 -> 47
A8: 804109 | B8: AVIKO SHOESTRING 5x2500g | C8: 71 | E8: 87 | G8: 90.5 | H8: =+C8+D8+E8-F8-G8 -> 67.5 | L8: 61 | M8: =+H8+I8+J8-K8-L8 -> 6.5 | R8: =+M8+N8+O8-P8-Q8 -> 6.5 | V8: 0 | W8: =+R8+S8+T8-U8-V8 -> 6.5 | AB8: =+W8+X8+Y8-Z8-AA8 -> 6.5
A9: 806980 | B9: AVIKO SPICY JACKET WEDGES 4x2500g | C9: 46 | E9: 71 | G9: 48 | H9: =+C9+D9+E9-F9-G9 -> 69 | L9: 60 | M9: =+H9+I9+J9-K9-L9 -> 9 | Q9: 7 | R9: =+M9+N9+O9-P9-Q9 -> 2 | W9: =+R9+S9+T9-U9-V9 -> 2 | AB9: =+W9+X9+Y9-Z9-AA9 -> 2
A10: 806982 | B10: AROS DE CEBOLLA 1X1000g | C10: 95 | H10: =+C10+D10+E10-F10-G10 -> 95 | L10: 50 | M10: =+H10+I10+J10-K10-L10 -> 45 | Q10: 8 | R10: =+M10+N10+O10-P10-Q10 -> 37 | W10: =+R10+S10+T10-U10-V10 -> 37 | AB10: =+W10+X10+Y10-Z10-AA10 -> 37
A11: 260612 | B11: CASTEL STRAIGHT CUT FRIES 4X2500g | C11: 102 | G11: 35 | H11: =+C11+D11+E11-F11-G11 -> 67 | L11: 63 | M11: =+H11+I11+J11-K11-L11 -> 4 | R11: =+M11+N11+O11-P11-Q11 -> 4 | W11: =+R11+S11+T11-U11-V11 -> 4 | AB11: =+W11+X11+Y11-Z11-AA11 -> 4
A12: 804661 | B12: AVIKO STEAK FRIES 4X2500G 4X5.5 LBS | C12: 633 | G12: 20 | H12: =+C12+D12+E12-F12-G12 -> 613 | L12: 30 | M12: =+H12+I12+J12-K12-L12 -> 583 | Q12: 33 | R12: =+M12+N12+O12-P12-Q12 -> 550 | V12: 20 | W12: =+R12+S12+T12-U12-V12 -> 530 | AA12: 20 | AB12: =+W12+X12+Y12-Z12-AA12 -> 510
A13: 808540 | B13: AVIKO H SUPER CRUNCH 15mm 6x2500g | C13: 0 | E13: 216 | H13: =+C13+D13+E13-F13-G13 -> 216 | L13: 54 | M13: =+H13+I13+J13-K13-L13 -> 162 | Q13: 57 | R13: =+M13+N13+O13-P13-Q13 -> 105 | V13: 18 | W13: =+R13+S13+T13-U13-V13 -> 87 | AB13: =+W13+X13+Y13-Z13-AA13 -> 87
A14: 807769 | B14: PAPAS FRITAS CORTE REG 10 X 1000G | C14: 232 | G14: 3 | H14: =+C14+D14+E14-F14-G14 -> 229 | L14: 2 | M14: =+H14+I14+J14-K14-L14 -> 227 | Q14: 6 | R14: =+M14+N14+O14-P14-Q14 -> 221 | V14: 2 | W14: =+R14+S14+T14-U14-V14 -> 219 | AB14: =+W14+X14+Y14-Z14-AA14 -> 219
A15: 807329 | B15: AVIKO ORIGINAL 20X450G | C15: 0 | H15: =+C15+D15+E15-F15-G15 -> 0 | M15: =+H15+I15+J15-K15-L15 -> 0 | R15: =+M15+N15+O15-P15-Q15 -> 0 | W15: =+R15+S15+T15-U15-V15 -> 0 | AB15: =+W15+X15+Y15-Z15-AA15 -> 0
A16: 805411 | B16: PAPAS FRITAS ZIGZAG 12/750GRS | C16: 0 | H16: =+C16+D16+E16-F16-G16 -> 0 | M16: =+H16+I16+J16-K16-L16 -> 0 | R16: =+M16+N16+O16-P16-Q16 -> 0 | W16: =+R16+S16+T16-U16-V16 -> 0 | AB16: =+W16+X16+Y16-Z16-AA16 -> 0
A17: 807679 | B17: AVIKO SPICY WEDGES 20X500G | C17: 0 | H17: =+C17+D17+E17-F17-G17 -> 0 | M17: =+H17+I17+J17-K17-L17 -> 0 | R17: =+M17+N17+O17-P17-Q17 -> 0 | W17: =+R17+S17+T17-U17-V17 -> 0 | AB17: =+W17+X17+Y17-Z17-AA17 -> 0
A18: 805168 | B18: AVIKO AROS DE CEBOLLA PREFRITOS 25/400g | C18: 0 | H18: =+C18+D18+E18-F18-G18 -> 0 | M18: =+H18+I18+J18-K18-L18 -> 0 | R18: =+M18+N18+O18-P18-Q18 -> 0 | W18: =+R18+S18+T18-U18-V18 -> 0 | AB18: =+W18+X18+Y18-Z18-AA18 -> 0
A19: 807363 | B19: Aviko H Super Crunch 14x600g | C19: 0 | H19: =+C19+D19+E19-F19-G19 -> 0 | M19: =+H19+I19+J19-K19-L19 -> 0 | R19: =+M19+N19+O19-P19-Q19 -> 0 | W19: =+R19+S19+T19-U19-V19 -> 0 | AB19: =+W19+X19+Y19-Z19-AA19 -> 0
A20: 809529 | B20: Aviko SC Airfr. PommesFrites 10x750 | C20: 0 | H20: =+C20+D20+E20-F20-G20 -> 0 | M20: =+H20+I20+J20-K20-L20 -> 0 | R20: =+M20+N20+O20-P20-Q20 -> 0 | W20: =+R20+S20+T20-U20-V20 -> 0 | AB20: =+W20+X20+Y20-Z20-AA20 -> 0
A24: TOTAL AVIKO | C24: =+SUM(C3:C23) -> 1397.3 | D24: =+SUM(D3:D23) -> 0 | E24: =+SUM(E3:E23) -> 2450 | F24: =+SUM(F3:F23) -> 0 | G24: =+SUM(G3:G23) -> 966.5 | H24: =+SUM(H3:H23) -> 2880.8 | I24: =+SUM(I3:I23) -> 0 | J24: =+SUM(J3:J23) -> 0 | ... M24: =+SUM(M3:M23) -> 1800.8 | Q24: =+SUM(Q3:Q23) -> 810 | R24: =+SUM(R3:R23) -> 1015.8 | V24: =+SUM(V3:V23) -> 65 | W24: =+SUM(W3:W23) -> 950.8 | AA24: =+SUM(AA3:AA23) -> 20 | AB24: =+SUM(AB3:AB23) -> 930.8
C26: =+C24 -> 1397.3 | D26: =+D24 -> 0 | E26: =+E24 -> 2450 | F26: =+F24 -> 0 | G26: =+G24 -> 966.5 | H26: =+H24 -> 2880.8 | L26: =+L24 -> 1080 | M26: =+M24 -> 1800.8 | Q26: =+Q24 -> 810 | R26: =+R24 -> 1015.8 | S26: =+S24 -> 0 | T26: =+T24 -> 0 | U26: =+U24 -> 0 | V26: =+V24 -> 65 | W26: =+W24 -> 950.8 | X26: =+X24 -> 0 | ... AB26: =+AB24 -> 930.8
C27: =+C26/50 -> 27.946 | G27: ESPACIOS | H27: =+H26/50 -> 57.616 | M27: =+M26/50 -> 36.016

Sheet FRESCO
A2: CÓDIGO | B2: DESCRIPCIÓN | C2: INV DICIEMBRE 2025 | D2: COMPRAS | E2: Entradas | F2: Salidas | G2: VENTAS | H2: INV ENERO 2026 | I2: COMPRAS | J2: Entradas | K2: Salidas | L2: VENTAS | M2: INV FEBRERO 2026 | N2: COMPRAS | O2: Entradas | P2: Salidas | Q2: VENTAS | R2: INV MARZO 2026 | S2: COMPRAS | T2: Entradas | U2: Salidas | V2: VENTAS | W2: INV ABRIL 2026 | X2: COMPRAS | Y2: Entradas | Z2: Salidas | AA2: VENTAS | AB2: INV MAYO 2026 | AC2: COMPRAS | AD2: Entradas | AE2: Salidas | AF2: VENTAS | AG2: INV JUNIO 2026 | AH2: COMPRAS | AI2: Entradas | AJ2: Salidas | AK2: VENTAS | AL2: INV JULIO 2026 | AM2: COMPRAS | AN2: Entradas | AO2: Salidas | AP2: VENTAS | AQ2: INV AGOSTO 2026 | AR2: COMPRAS | AS2: Entradas | AT2: Salidas | AU2: VENTAS | AV2: INV SEPTIEMBRE 2026 | AW2: COMPRAS | AX2: Entradas | AY2: Salidas | AZ2: VENTAS | BA2: INV OCTUBRE 2026 | BB2: COMPRAS | BC2: Entradas | BD2: Salidas | BE2: VENTAS | BF2: INV NOVIEMBRE 2026 | BG2: COMPRAS | BH2: Entradas | BI2: Salidas | BJ2: VENTAS | BK2: INV DICIEMBRE 2026 | BL2: COMPRAS | BM2: Entradas | BN2: Salidas | BO2: VENTAS | BP2: INV ABRIL 2026 | BQ2: COMPRAS | BR2: Entradas | BS2: Salidas | BT2: VENTAS | BU2: INV MAYO 2026
A3: 806685 | B3: AVIKO H PREM.CRUNCH SHOESTRING 7MM 4X2270G | C3: 0 | H3: =+C3+D3+E3-F3-G3 -> 0 | M3: =+H3+I3+J3-K3-L3 -> 0
A4: 806939 | B4: AVIKO CRINKLE CUT 12MM 4 X 2.5 KG | C4: 2 | H4: =+C4+D4+E4-F4-G4 -> 2 | M4: =+H4+I4+J4-K4-L4 -> 2 | R4: =+M4+N4+O4-P4-Q4 -> 2 | BP4: =+R4+BL4+BM4-BN4-BO4 -> 2 | BU4: =+BP4+BQ4+BR4-BS4-BT4 -> 2
A5: 806694 | B5: AVIKO SUPER CRUNCH 9.5mm 3/8 4x2500g | C5: 0 | H5: =+C5+D5+E5-F5-G5 -> 0 | M5: =+H5+I5+J5-K5-L5 -> 0 | R5: =+M5+N5+O5-P5-Q5 -> 0 | BP5: =+R5+BL5+BM5-BN5-BO5 -> 0 | BU5: =+BP5+BQ5+BR5-BS5-BT5 -> 0
A6: 804104 | B6: HASHBROWN TRIANG | C6: 0 | H6: =+C6+D6+E6-F6-G6 -> 0 | M6: =+H6+I6+J6-K6-L6 -> 0 | R6: =+M6+N6+O6-P6-Q6 -> 0 | BP6: =+R6+BL6+BM6-BN6-BO6 -> 0 | BU6: =+BP6+BQ6+BR6-BS6-BT6 -> 0
A7: 806686 | B7: AVIKO H PREM CRUNCH 9.5 mm 3/8 4x2270g | C7: 12 | H7: =+C7+D7+E7-F7-G7 -> 12 | M7: =+H7+I7+J7-K7-L7 -> 12 | R7: =+M7+N7+O7-P7-Q7 -> 12 | BP7: =+R7+BL7+BM7-BN7-BO7 -> 12 | BU7: =+BP7+BQ7+BR7-BS7-BT7 -> 12
A8: 804109 | B8: AVIKO SHOESTRING 5x2500g | C8: 0 | H8: =+C8+D8+E8-F8-G8 -> 0 | M8: =+H8+I8+J8-K8-L8 -> 0 | R8: =+M8+N8+O8-P8-Q8 -> 0 | BP8: =+R8+BL8+BM8-BN8-BO8 -> 0 | BU8: =+BP8+BQ8+BR8-BS8-BT8 -> 0
A9: 806980 | B9: AVIKO SPICY JACKET WEDGES 4x2500g | H9: =+C9+D9+E9-F9-G9 -> 0 | M9: =+H9+I9+J9-K9-L9 -> 0 | R9: =+M9+N9+O9-P9-Q9 -> 0 | BP9: =+R9+BL9+BM9-BN9-BO9 -> 0 | BU9: =+BP9+BQ9+BR9-BS9-BT9 -> 0
A10: 806982 | B10: AROS DE CEBOLLA 1X1000g | C10: 0 | H10: =+C10+D10+E10-F10-G10 -> 0 | M10: =+H10+I10+J10-K10-L10 -> 0 | R10: =+M10+N10+O10-P10-Q10 -> 0 | BP10: =+R10+BL10+BM10-BN10-BO10 -> 0 | BU10: =+BP10+BQ10+BR10-BS10-BT10 -> 0
A11: 260612 | B11: CASTEL STRAIGHT CUT FRIES 4X2500g | C11: 0 | H11: =+C11+D11+E11-F11-G11 -> 0 | M11: =+H11+I11+J11-K11-L11 -> 0 | R11: =+M11+N11+O11-P11-Q11 -> 0 | BP11: =+R11+BL11+BM11-BN11-BO11 -> 0 | BU11: =+BP11+BQ11+BR11-BS11-BT11 -> 0
A12: 804661 | B12: AVIKO STEAK FRIES 4X2500G 4X5.5 LBS | C12: 0 | H12: =+C12+D12+E12-F12-G12 -> 0 | M12: =+H12+I12+J12-K12-L12 -> 0 | R12: =+M12+N12+O12-P12-Q12 -> 0 | BP12: =+R12+BL12+BM12-BN12-BO12 -> 0 | BU12: =+BP12+BQ12+BR12-BS12-BT12 -> 0
A13: 806702 | B13: AVIKO H SUPER CRUNCH 15mm 6x2500g | C13: 0 | H13: =+C13+D13+E13-F13-G13 -> 0 | M13: =+H13+I13+J13-K13-L13 -> 0 | R13: =+M13+N13+O13-P13-Q13 -> 0 | BP13: =+R13+BL13+BM13-BN13-BO13 -> 0 | BU13: =+BP13+BQ13+BR13-BS13-BT13 -> 0
A14: 804661 | B14: AVIKO STEAK FRIES 4X2500G 4X5.5 LBS | C14: 0 | H14: =+C14+D14+E14-F14-G14 -> 0 | M14: =+H14+I14+J14-K14-L14 -> 0 | R14: =+M14+N14+O14-P14-Q14 -> 0 | BP14: =+R14+BL14+BM14-BN14-BO14 -> 0 | BU14: =+BP14+BQ14+BR14-BS14-BT14 -> 0
A15: 807769 | B15: PAPAS FRITAS CORTE REG 10 X 1000G | C15: 165 | H15: =+C15+D15+E15-F15-G15 -> 165 | M15: =+H15+I15+J15-K15-L15 -> 165 | Q15: 47 | R15: =+M15+N15+O15-P15-Q15 -> 118 | BM15: 697 | BO15: 78 | BP15: =+R15+BL15+BM15-BN15-BO15 -> 737 | BU15: =+BP15+BQ15+BR15-BS15-BT15 -> 737
A16: 807329 | B16: AVIKO ORIGINAL 20X450G | C16: 0 | H16: =+C16+D16+E16-F16-G16 -> 0 | M16: =+H16+I16+J16-K16-L16 -> 0 | O16: 149 | Q16: 46 | R16: =+M16+N16+O16-P16-Q16 -> 103 | BM16: 109 | BO16: 33 | BP16: =+R16+BL16+BM16-BN16-BO16 -> 179 | BU16: =+BP16+BQ16+BR16-BS16-BT16 -> 179
A17: 805411 | B17: PAPAS FRITAS ZIGZAG 12/750GRS | C17: 41 | H17: =+C17+D17+E17-F17-G17 -> 41 | M17: =+H17+I17+J17-K17-L17 -> 41 | O17: 168 | Q17: 36 | R17: =+M17+N17+O17-P17-Q17 -> 173 | BM17: 27 | BO17: 36 | BP17: =+R17+BL17+BM17-BN17-BO17 -> 164 | BU17: =+BP17+BQ17+BR17-BS17-BT17 -> 164
A18: 807679 | B18: AVIKO SPICY WEDGES 20X500G | C18: 0 | H18: =+C18+D18+E18-F18-G18 -> 0 | M18: 99 | Q18: 48 | R18: =+M18+N18+O18-P18-Q18 -> 51 | BO18: 18 | BP18: =+R18+BL18+BM18-BN18-BO18 -> 33 | BU18: =+BP18+BQ18+BR18-BS18-BT18 -> 33
A19: 805168 | B19: AVIKO AROS DE CEBOLLA PREFRITOS 25/400g | C19: 8 | H19: =+C19+D19+E19-F19-G19 -> 8 | M19: =+H19+I19+J19-K19-L19 -> 8 | O19: 96 | Q19: 8 | R19: =+M19+N19+O19-P19-Q19 -> 96 | BM19: 8 | BO19: 8 | BP19: =+R19+BL19+BM19-BN19-BO19 -> 96 | BU19: =+BP19+BQ19+BR19-BS19-BT19 -> 96
A20: 807363 | B20: Aviko H Super Crunch 14x600g | C20: 0 | H20: =+C20+D20+E20-F20-G20 -> 0 | M20: =+H20+I20+J20-K20-L20 -> 0 | R20: =+M20+N20+O20-P20-Q20 -> 0 | BP20: =+R20+BL20+BM20-BN20-BO20 -> 0 | BU20: =+BP20+BQ20+BR20-BS20-BT20 -> 0
A21: 809529 | B21: Aviko SC Airfr. PommesFrites 10x750 | C21: 404 | G21: 12 | H21: =+C21+D21+E21-F21-G21 -> 392 | M21: =+H21+I21+J21-K21-L21 -> 392 | Q21: 1 | R21: =+M21+N21+O21-P21-Q21 -> 391 | BM21: 24 | BO21: 24 | BP21: =+R21+BL21+BM21-BN21-BO21 -> 391 | BU21: =+BP21+BQ21+BR21-BS21-BT21 -> 391
H22: =+C22+D22+E22-F22-G22 -> 0 | M22: =+H22+I22+J22-K22-L22 -> 0 | R22: =+M22+N22+O22-P22-Q22 -> 0 | BP22: =+R22+BL22+BM22-BN22-BO22 -> 0 | BU22: =+BP22+BQ22+BR22-BS22-BT22 -> 0
H23: =+C23+D23+E23-F23-G23 -> 0 | M23: =+H23+I23+J23-K23-L23 -> 0 | R23: =+M23+N23+O23-P23-Q23 -> 0 | BP23: =+R23+BL23+BM23-BN23-BO23 -> 0 | BU23: =+BP23+BQ23+BR23-BS23-BT23 -> 0
H24: =+C24+D24+E24-F24-G24 -> 0 | M24: =+H24+I24+J24-K24-L24 -> 0 | R24: =+M24+N24+O24-P24-Q24 -> 0 | BP24: =+R24+BL24+BM24-BN24-BO24 -> 0 | BU24: =+BP24+BQ24+BR24-BS24-BT24 -> 0
A25: TOTAL AVIKO | C25: =+SUM(C3:C24) -> 632 | D25: =+SUM(D3:D24) -> 0 | E25: =+SUM(E3:E24) -> 0 | F25: =+SUM(F3:F24) -> 0 | G25: =+SUM(G3:G24) -> 12 | H25: =+SUM(H3:H24) -> 620 | I25: =+SUM(I3:I24) -> 0 | J25: =+SUM(J3:J24) -> 0 | ... BU25: =+SUM(BU3:BU24) -> 1614
C27: =+C25+C14 -> 632 | D27: =+D25+D14 -> 0 | E27: =+E25+E14 -> 0 | F27: =+F25+F14 -> 0 | G27: =+G25+G14 -> 12 | H27: =+H25+H14 -> 620 | I27: =+I25+I14 -> 0 | J27: =+J25+J14 -> 0 | ... BK27: =+BK25+BK14 -> 0
C28: =+C27/50 -> 12.64 | G28: ESPACIOS | H28: =+H27/50 -> 12.4 | L28: ESPACIOS | M28: =+M27/50 -> 14.38 | Q28: ESPACIOS | R28: =+R27/50 -> 18.92 | V28: ESPACIOS | W28: =+W27/50 -> 0 | AA28: ESPACIOS | AB28: =+AB27/50 -> 0 | AF28: ESPACIOS | AG28: =+AG27/50 -> 0 | AK28: ESPACIOS | AL28: =+AL27/50 -> 0 | AP28: ESPACIOS | AQ28: =+AQ27/50 -> 0 | AU28: ESPACIOS | AV28: =+AV27/50 -> 0 | AZ28: ESPACIOS | BA28: =+BA27/50 -> 0 | BE28: ESPACIOS | BF28: =+BF27/50 -> 0 | BJ28: ESPACIOS | BK28: =+BK27/50 -> 0

Sheet MEXIDELI
L1: 45
A2: CÓDIGO | B2: DESCRIPCIÓN | C2: INV DICIEMBRE 2025 | D2: COMPRAS | E2: Entradas | F2: Salidas | G2: VENTAS | H2: INV ENERO 2026 | I2: COMPRAS | J2: Entradas | K2: Salidas | L2: VENTAS | M2: INV FEB 2026 | N2: COMPRAS | O2: Entradas | P2: Salidas | Q2: VENTAS | R2: INV MARZO 2026 | S2: COMPRAS | T2: Entradas | U2: Salidas | V2: VENTAS | W2: INV ABRIL 2026 | X2: COMPRAS | Y2: Entradas | Z2: Salidas | AA2: VENTAS | AB2: INV MAYO 2026
A3: 806685 | B3: AVIKO H PREM.CRUNCH SHOESTRING 7MM 4X2270G | H3: =+C3+D3+E3-F3-G3 -> 0 | J3: 972 | M3: =+H3+I3+J3-K3-L3 -> 972 | O3: 1620 | Q3: 375 | R3: =+M3+N3+O3-P3-Q3 -> 2217 | V3: 937 | W3: =+R3+S3+T3-U3-V3 -> 1280 | AA3: 342 | AB3: =+W3+X3+Y3-Z3-AA3 -> 938
A4: 806939 | B4: AVIKO CRINKLE CUT 12MM 4 X 2.5 KG | H4: =+C4+D4+E4-F4-G4 -> 0 | J4: 324 | K4: 80 | L4: 10 | M4: =+H4+I4+J4-K4-L4 -> 234 | O4: 108 | Q4: 5 | R4: =+M4+N4+O4-P4-Q4 -> 337 | U4: 80 | V4: 107 | W4: =+R4+S4+T4-U4-V4 -> 150 | AB4: =+W4+X4+Y4-Z4-AA4 -> 150
A5: 806694 | B5: AVIKO SUPER CRUNCH 9.5mm 3/8 4x2500g | H5: =+C5+D5+E5-F5-G5 -> 0 | J5: 168 | L5: 18 | M5: =+H5+I5+J5-K5-L5 -> 150 | O5: 84 | Q5: 33 | R5: =+M5+N5+O5-P5-Q5 -> 201 | V5: 25 | W5: =+R5+S5+T5-U5-V5 -> 176 | AA5: 10 | AB5: =+W5+X5+Y5-Z5-AA5 -> 166
A6: 804104 | B6: HASHBROWN TRIANG | H6: =+C6+D6+E6-F6-G6 -> 0 | M6: =+H6+I6+J6-K6-L6 -> 0 | R6: =+M6+N6+O6-P6-Q6 -> 0 | W6: =+R6+S6+T6-U6-V6 -> 0 | AB6: =+W6+X6+Y6-Z6-AA6 -> 0
A7: 806686 | B7: AVIKO H PREM CRUNCH 9.5 mm 3/8 4x2270g | H7: =+C7+D7+E7-F7-G7 -> 0 | J7: 108 | L7: 20 | M7: =+H7+I7+J7-K7-L7 -> 88 | Q7: 86 | R7: =+M7+N7+O7-P7-Q7 -> 2 | V7: 2 | W7: =+R7+S7+T7-U7-V7 -> 0 | AB7: =+W7+X7+Y7-Z7-AA7 -> 0
A8: 804109 | B8: AVIKO SHOESTRING 5x2500g | H8: =+C8+D8+E8-F8-G8 -> 0 | J8: 168 | L8: 20 | M8: =+H8+I8+J8-K8-L8 -> 148 | O8: 84 | Q8: 94 | R8: =+M8+N8+O8-P8-Q8 -> 138 | T8: 50 | V8: 142 | W8: =+R8+S8+T8-U8-V8 -> 46 | AA8: 6 | AB8: =+W8+X8+Y8-Z8-AA8 -> 40
A9: 806980 | B9: AVIKO SPICY JACKET WEDGES 4x2500g | H9: =+C9+D9+E9-F9-G9 -> 0 | J9: 120 | M9: =+H9+I9+J9-K9-L9 -> 120 | O9: 24 | Q9: 4 | R9: =+M9+N9+O9-P9-Q9 -> 140 | V9: 82 | W9: =+R9+S9+T9-U9-V9 -> 58 | AA9: 2 | AB9: =+W9+X9+Y9-Z9-AA9 -> 56
A10: 806982 | B10: AROS DE CEBOLLA 1X1000g | H10: =+C10+D10+E10-F10-G10 -> 0 | M10: =+H10+I10+J10-K10-L10 -> 0 | O10: 108 | R10: =+M10+N10+O10-P10-Q10 -> 108 | W10: =+R10+S10+T10-U10-V10 -> 108 | AB10: =+W10+X10+Y10-Z10-AA10 -> 108
A11: 260612 | B11: CASTEL STRAIGHT CUT FRIES 4X2500g | H11: =+C11+D11+E11-F11-G11 -> 0 | M11: =+H11+I11+J11-K11-L11 -> 0 | O11: 2 | Q11: 2 | R11: =+M11+N11+O11-P11-Q11 -> 0 | W11: =+R11+S11+T11-U11-V11 -> 0 | AB11: =+W11+X11+Y11-Z11-AA11 -> 0
A12: 804661 | B12: AVIKO STEAK FRIES 4X2500G 4X5.5 LBS | H12: =+C12+D12+E12-F12-G12 -> 0 | M12: =+H12+I12+J12-K12-L12 -> 0 | R12: =+M12+N12+O12-P12-Q12 -> 0 | W12: =+R12+S12+T12-U12-V12 -> 0 | AB12: =+W12+X12+Y12-Z12-AA12 -> 0
A13: 806702 | B13: AVIKO H SUPER CRUNCH 15mm 6x2500g | H13: =+C13+D13+E13-F13-G13 -> 0 | M13: =+H13+I13+J13-K13-L13 -> 0 | R13: =+M13+N13+O13-P13-Q13 -> 0 | W13: =+R13+S13+T13-U13-V13 -> 0 | AB13: =+W13+X13+Y13-Z13-AA13 -> 0
A14: 807769 | B14: PAPAS FRITAS CORTE REG 10 X 1000G | H14: =+C14+D14+E14-F14-G14 -> 0 | M14: =+H14+I14+J14-K14-L14 -> 0 | R14: =+M14+N14+O14-P14-Q14 -> 0 | W14: =+R14+S14+T14-U14-V14 -> 0 | AB14: =+W14+X14+Y14-Z14-AA14 -> 0
A15: 807329 | B15: AVIKO ORIGINAL 20X450G | H15: =+C15+D15+E15-F15-G15 -> 0 | M15: =+H15+I15+J15-K15-L15 -> 0 | O15: 164 | R15: =+M15+N15+O15-P15-Q15 -> 164 | W15: =+R15+S15+T15-U15-V15 -> 164 | AB15: =+W15+X15+Y15-Z15-AA15 -> 164
A16: 805411 | B16: PAPAS FRITAS ZIGZAG 12/750GRS | H16: =+C16+D16+E16-F16-G16 -> 0 | J16: 216 | M16: =+H16+I16+J16-K16-L16 -> 216 | O16: 21 | Q16: 72 | R16: =+M16+N16+O16-P16-Q16 -> 165 | W16: =+R16+S16+T16-U16-V16 -> 165 | AB16: =+W16+X16+Y16-Z16-AA16 -> 165
A17: 807679 | B17: AVIKO SPICY WEDGES 20X500G | H17: =+C17+D17+E17-F17-G17 -> 0 | J17: 120 | M17: =+H17+I17+J17-K17-L17 -> 120 | O17: 136 | R17: =+M17+N17+O17-P17-Q17 -> 256 | W17: =+R17+S17+T17-U17-V17 -> 256 | Z17: 130 | AB17: =+W17+X17+Y17-Z17-AA17 -> 126
A18: 805168 | B18: AVIKO AROS DE CEBOLLA PREFRITOS 25/400g | H18: =+C18+D18+E18-F18-G18 -> 0 | M18: =+H18+I18+J18-K18-L18 -> 0 | O18: 301 | R18: =+M18+N18+O18-P18-Q18 -> 301 | W18: =+R18+S18+T18-U18-V18 -> 301 | AB18: =+W18+X18+Y18-Z18-AA18 -> 301
A19: 807363 | B19: Aviko H Super Crunch 14x600g | H19: =+C19+D19+E19-F19-G19 -> 0 | M19: =+H19+I19+J19-K19-L19 -> 0 | R19: =+M19+N19+O19-P19-Q19 -> 0 | W19: =+R19+S19+T19-U19-V19 -> 0 | AB19: =+W19+X19+Y19-Z19-AA19 -> 0
A20: 809529 | B20: Aviko SC Airfr. PommesFrites 10x750 | H20: =+C20+D20+E20-F20-G20 -> 0 | M20: =+H20+I20+J20-K20-L20 -> 0 | R20: =+M20+N20+O20-P20-Q20 -> 0 | W20: =+R20+S20+T20-U20-V20 -> 0 | AB20: =+W20+X20+Y20-Z20-AA20 -> 0
A21: 505015 | B21: 10 MM NATURAL-KAIDA | O21: 975 | R21: =+M21+N21+O21-P21-Q21 -> 975 | V21: 157 | W21: =+R21+S21+T21-U21-V21 -> 818 | AA21: 7 | AB21: =+W21+X21+Y21-Z21-AA21 -> 811
W22: =+R22+S22+T22-U22-V22 -> 0 | AB22: =+W22+X22+Y22-Z22-AA22 -> 0
W23: =+R23+S23+T23-U23-V23 -> 0 | AB23: =+W23+X23+Y23-Z23-AA23 -> 0
A24: TOTAL AVIKO | C24: =+SUM(C3:C23) -> 0 | D24: =+SUM(D3:D23) -> 0 | E24: =+SUM(E3:E23) -> 0 | F24: =+SUM(F3:F23) -> 0 | G24: =+SUM(G3:G23) -> 0 | H24: =+SUM(H3:H23) -> 0 | I24: =+SUM(I3:I23) -> 0 | J24: =+SUM(J3:J23) -> 2196 | ... AB24: =+SUM(AB3:AB23) -> 3025
C26: =+C24 -> 0 | D26: =+D24 -> 0 | E26: =+E24 -> 0 | F26: =+F24 -> 0 | G26: =+G24 -> 0 | M26: =+M24 -> 2048 | N26: =+N24 -> 0 | O26: =+O24 -> 3627 | P26: =+P24 -> 0 | Q26: =+Q24 -> 671 | R26: =+R24 -> 5004
C27: =+C26/50 -> 0 | G27: ESPACIOS

Sheet ALFRIMEX
A2: PROV | B2: CÓDIGO | C2: DESCRIPCIÓN | D2: INV DICIEMBRE 2025 | E2: COMPRAS | F2: Entradas | G2: Salidas | H2: VENTAS | I2: INV ENERO 2026 | J2: COMPRAS | K2: Entradas | L2: Salidas | M2: VENTAS | N2: INV FEB 2026 | O2: COMPRAS | P2: Entradas | Q2: Salidas | R2: VENTAS | S2: INV FEB 2026
A3: AVIKO | B3: 260612 | C3: CASTEL STRAIGTH CUT FRIES 4x2500g | D3: 514 | H3: 158 | I3: =D3+E3+F3-G3-H3 -> 356 | M3: 312 | N3: =I3+J3+K3-L3-M3 -> 44 | R3: 44 | S3: =+N3+O3+P3-Q3-R3 -> 0
A4: AVIKO | B4: 803528 | C4: AVIKO H POMMES FRITES 11mm 7/16 4x2500g | D4: =#REF!+#REF!+#REF!-#REF!-#REF! -> #REF! | I4: =D4+E4+F4-G4-H4 -> #REF! | N4: =I4+J4+K4-L4-M4 -> #REF! | S4: =#REF!+O4+P4-Q4-R4 -> #REF!
A5: AVIKO | B5: 806980 | C5: AVIKO SPICY JACKET WEDGES 4x2500g | D5: =#REF!+#REF!+#REF!-#REF!-#REF! -> #REF! | I5: =D5+E5+F5-G5-H5 -> #REF! | N5: =I5+J5+K5-L5-M5 -> #REF! | S5: =#REF!+O5+P5-Q5-R5 -> #REF!
A6: AVIKO | B6: 807679 | C6: AVIKO SPICY JACKET WEDGES 20X500G | D6: =#REF!+#REF!+#REF!-#REF!-#REF! -> #REF! | I6: =D6+E6+F6-G6-H6 -> #REF! | N6: =I6+J6+K6-L6-M6 -> #REF! | S6: =#REF!+O6+P6-Q6-R6 -> #REF!
A7: AVIKO | B7: 806918 | C7: AVIKO H SUPER LONG 9.5 MM SKIN ON 4x2500g | D7: =#REF!+#REF!+#REF!-#REF!-#REF! -> #REF! | I7: =D7+E7+F7-G7-H7 -> #REF! | N7: =I7+J7+K7-L7-M7 -> #REF! | S7: =#REF!+O7+P7-Q7-R7 -> #REF!
A8: TOTAL AVIKO | D8: =+D3 -> 514 | E8: =+E3 -> 0 | F8: =+F3 -> 0 | G8: =+G3 -> 0 | H8: =+H3 -> 158 | I8: =+I3 -> 356 | J8: =+J3 -> 0 | K8: =+K3 -> 0 | ... S8: =+S3 -> 0

Sheet CANBELT
A2: CÓDIGO | B2: DESCRIPCIÓN | C2: INV DICIEMBRE 2025 | D2: COMPRAS | E2: Entradas | F2: Salidas | G2: VENTAS | H2: INV ENERO 2026 | I2: COMPRAS | J2: Entradas | K2: Salidas | L2: VENTAS | M2: INV FEB 2026 | N2: COMPRAS | O2: Entradas | P2: Salidas | Q2: VENTAS | R2: INV MARZO 2026 | S2: COMPRAS | T2: Entradas | U2: Salidas | V2: VENTAS | W2: INV ABRIL 2026 | X2: COMPRAS | Y2: Entradas | Z2: Salidas | AA2: VENTAS | AB2: INV MAYO 2026
A3: 806939 | B3: AVIKO CRINKLE CUT 12MM 4 X 2.5 KG | C3: 30 | E3: 50 | G3: 67 | H3: =C3+D3+E3-F3-G3 -> 13 | J3: 80 | L3: 32 | M3: =H3+I3+J3-K3-L3 -> 61 | O3: 18 | Q3: 37 | R3: =M3+N3+O3-P3-Q3 -> 42 | T3: 80 | V3: 42 | W3: =R3+S3+T3-U3-V3 -> 80 | AA3: 24 | AB3: =W3+X3+Y3-Z3-AA3 -> 56
A4: 803528 | B4: AVIKO H POMMES FRITES 11mm 7/16 4x2500g | C4: =#REF!+#REF!+#REF!-#REF!-#REF! -> #REF! | H4: =C4+D4+E4-F4-G4 -> #REF! | M4: =H4+I4+J4-K4-L4 -> #REF! | R4: =M4+N4+O4-P4-Q4 -> #REF! | W4: =R4+S4+T4-U4-V4 -> #REF! | AB4: =W4+X4+Y4-Z4-AA4 -> #REF!
A5: 806980 | B5: AVIKO SPICY JACKET WEDGES 4x2500g | C5: =#REF!+#REF!+#REF!-#REF!-#REF! -> #REF! | H5: =C5+D5+E5-F5-G5 -> #REF! | M5: =H5+I5+J5-K5-L5 -> #REF! | R5: =M5+N5+O5-P5-Q5 -> #REF! | W5: =R5+S5+T5-U5-V5 -> #REF! | AB5: =W5+X5+Y5-Z5-AA5 -> #REF!
A6: 807679 | B6: AVIKO SPICY JACKET WEDGES 20X500G | C6: =#REF!+#REF!+#REF!-#REF!-#REF! -> #REF! | H6: =C6+D6+E6-F6-G6 -> #REF! | M6: =H6+I6+J6-K6-L6 -> #REF! | R6: =M6+N6+O6-P6-Q6 -> #REF! | W6: =R6+S6+T6-U6-V6 -> #REF! | AB6: =W6+X6+Y6-Z6-AA6 -> #REF!
A7: 806918 | B7: AVIKO H SUPER LONG 9.5 MM SKIN ON 4x2500g | C7: =#REF!+#REF!+#REF!-#REF!-#REF! -> #REF! | H7: =C7+D7+E7-F7-G7 -> #REF! | M7: =H7+I7+J7-K7-L7 -> #REF! | R7: =M7+N7+O7-P7-Q7 -> #REF! | W7: =R7+S7+T7-U7-V7 -> #REF! | AB7: =W7+X7+Y7-Z7-AA7 -> #REF!
C8: =+C3 -> 30 | D8: =+D3 -> 0 | E8: =+E3 -> 50 | F8: =+F3 -> 0 | G8: =+G3 -> 67 | H8: =+H3 -> 13 | I8: =+I3 -> 0 | J8: =+J3 -> 80 | ... AB8: =+AB3 -> 56

Sheet FRIJALISCO
AN1: CONTENEDORES EN TRANSITO
L2: =+P2*AI6 -> 0 | O2: 30 | AF2: INV ACTUAL + CONTENEDORES EN TRANSITO - VENTAS | AI2: Consumo mensual, Promedio año en curso | AJ2: Proyeccion de Ventas, con 10% al promedio del consumo mensual | AK2: Duracion de Inv. En Meses Considerando Inv Actual + Contenedores en Transito - Ventas | AN2: C-116 PTO ASAP | AO2: SUGERIDO | AP2: SUGERENCIA DE PEDIDOS, DE CONTENEDOR A 21 PALLET
A3: PROMEDIO DÍAS DE TRANSITO | B3: PROVEEDOR | C3: ESTATUS DE PRODUCTOS | D3: CÓDIGO | E3: DESCRIPCIÓN | F3: INV DICIEMBRE 2025 | G3: COMPRAS | H3: Entradas | I3: Salidas | J3: VENTAS | K3: INV ENERO 2026 | L3: COMPRAS | M3: Entradas | N3: Salidas | O3: VENTAS | P3: INV FEB 2026 | Q3: COMPRAS | R3: Entradas | S3: Salidas | T3: VENTAS | U3: INV MARZO 2026 | V3: COMPRAS | W3: Entradas | X3: Salidas | Y3: VENTAS | Z3: INV ABRIL 2026 | AA3: COMPRAS | AB3: Entradas | AC3: Salidas | AD3: VENTAS | AE3: INV MAYO 2026 | AF3: ACTUAL | AG3: C-116 | AH3: SUGERIDO | AK3: INV. ACTUAL | AL3: C-116 | AN3: 46188 | AP3: Cajas x pallet | AQ3: PALLET | AR3: CAJAS
A4: 60 | B4: WERISNG | C4: ACTIVO | D4: 105632 | E4: 10 MM NATURAL | F4: 3 | H4: =1008 -> 1008 | J4: 968 | K4: =F4+G4+H4+-I4-J4 -> 43 | M4: 835 | N4: 86 | O4: 792 | P4: =+K4+L4+M4-N4-O4 -> 0 | R4: 576 | T4: =543+30 -> 573 | U4: =+P4+Q4+R4-S4-T4 -> 3 | W4: 1288 | X4: 46 | Y4: 1098 | Z4: =+U4+V4+W4-X4-Y4 -> 147 | AB4: 1764 | AD4: 156 | AE4: =+Z4+AA4+AB4-AC4-AD4 -> 1755 | AF4: =+AE4 -> 1755 | AG4: =IF((AF4-($AI4*(NETWORKDAYS(AN3,AN3)/$O$2))+AN4)<=0,0,AF4-($AI4*(NETWORKDAYS(AN3,AN3)/$O$2))+AN4) -> 1726.4083 | AI4: =AVERAGE(J4,O4,T4,Y4) -> 857.75 | AJ4: =+AI4*1.1 -> 943.525 | AK4: =+Z4/AI4 -> 0.17137861 | AL4: =+AG4/AI4 -> 2.0127174 | AM4: =+AH4/AI4 -> 0 | AN4: 0 | AO4: =AR4 -> 0 | AP4: 113 | AR4: =+AQ4*AP4 -> 0 | AS4: =+#REF!-0.4 -> #REF! | AT4: 1.5 | AU4: =+AT4-AS4 -> #REF! | AV4: =+AU4*AI4 -> #REF!
A5: 60 | B5: WERISNG | C5: ACTIVO | D5: 102341 | E5: 10 MM CON COBERTURA | F5: 1000 | J5: 527 | K5: =F5+G5+H5+-I5-J5 -> 473 | M5: 4 | N5: 18 | O5: 331 | P5: =+K5+L5+M5-N5-O5 -> 128 | R5: 324 | S5: 150 | T5: 279 | U5: =+P5+Q5+R5-S5-T5 -> 23 | W5: 120 | X5: 35 | Y5: 73 | Z5: =+U5+V5+W5-X5-Y5 -> 35 | AB5: 504 | AD5: 74 | AE5: =+Z5+AA5+AB5-AC5-AD5 -> 465 | AF5: =+AE5 -> 465 | AG5: =IF((AF5-($AI5*(NETWORKDAYS(AN3,AN3)/$O$2))+AN5)<=0,0,AF5-($AI5*(NETWORKDAYS(AN3,AN3)/$O$2))+AN5) -> 1126.9167 | AI5: =AVERAGE(J5,O5,T5,Y5) -> 302.5 | AJ5: =+AI5*1.1 -> 332.75 | AK5: =+Z5/AI5 -> 0.11570248 | AL5: =+AG5/AI5 -> 3.7253444 | AM5: =+AH5/AI5 -> 0 | AN5: 672 | AO5: =AR5 -> 0 | AP5: 120 | AR5: =+AQ5*AP5 -> 0 | AS5: =+#REF!-0.4 -> #REF! | AT5: 1.5 | AU5: =+AT5-AS5 -> #REF! | AV5: =+AU5*AI5 -> #REF!
A6: 60 | B6: WERISNG | C6: ACTIVO | D6: 102310 | E6: 7 MM CON COBERTURA | F6: 321 | I6: 38 | J6: 238 | K6: =F6+G6+H6+-I6-J6 -> 45 | N6: 8 | O6: 37 | P6: =+K6+L6+M6-N6-O6 -> 0 | R6: 603 | T6: 208 | U6: =+P6+Q6+R6-S6-T6 -> 395 | W6: 18 | X6: 7 | Y6: 241 | Z6: =+U6+V6+W6-X6-Y6 -> 165 | AD6: 66 | AE6: =+Z6+AA6+AB6-AC6-AD6 -> 99 | AF6: =+AE6 -> 99 | AG6: =IF((AF6-($AI6*(NETWORKDAYS(AN3,AN3)/$O$2))+AN6)<=0,0,AF6-($AI6*(NETWORKDAYS(AN3,AN3)/$O$2))+AN6) -> 281.96667 | AI6: =AVERAGE(J6,O6,T6,Y6) -> 181 | AJ6: =+AI6*1.1 -> 199.1 | AK6: =+Z6/AI6 -> 0.91160221 | AL6: =+AG6/AI6 -> 1.5578269 | AM6: =+AH6/AI6 -> 0 | AN6: 189 | AO6: =AR6 -> 0 | AP6: 108 | AR6: =+AQ6*AP6 -> 0 | AS6: =+#REF!-0.4 -> #REF! | AT6: 1.5 | AU6: =+AT6-AS6 -> #REF! | AV6: =+AU6*AI6 -> #REF!
A7: 60 | B7: WERISNG | C7: ACTIVO | D7: 102211 | E7: 7 MM NATURAL | F7: 131 | J7: 129 | K7: =F7+G7+H7+-I7-J7 -> 2 | M7: 1 | N7: 2 | P7: =+K7+L7+M7-N7-O7 -> 1 | R7: 828 | T7: 153 | U7: =+P7+Q7+R7-S7-T7 -> 676 | W7: 18 | X7: 4 | Y7: 188 | Z7: =+U7+V7+W7-X7-Y7 -> 502 | AD7: 36 | AE7: =+Z7+AA7+AB7-AC7-AD7 -> 466 | AF7: =+AE7 -> 466 | AG7: =IF((AF7-($AI7*(NETWORKDAYS(AN3,AN3)/$O$2))+AN7)<=0,0,AF7-($AI7*(NETWORKDAYS(AN3,AN3)/$O$2))+AN7) -> 460.77778 | AI7: =AVERAGE(J7,O7,T7,Y7) -> 156.66667 | AJ7: =+AI7*1.1 -> 172.33333 | AK7: =+Z7/AI7 -> 3.2042553 | AL7: =+AG7/AI7 -> 2.9411348 | AM7: =+AH7/AI7 -> 0 | AO7: =AR7 -> 0 | AP7: 120 | AR7: =+AQ7*AP7 -> 0 | AS7: =+#REF!-0.4 -> #REF! | AT7: 1.5 | AU7: =+AT7-AS7 -> #REF! | AV7: =+AU7*AI7 -> #REF!
A8: 60 | B8: WERISNG | C8: ACTIVO | D8: 104215 | E8: 10 MM CON COBERTURA Y CASCARA | F8: 451 | G8: 3 | J8: 86 | K8: =F8+G8+H8+-I8-J8 -> 368 | M8: 12 | N8: 28 | O8: 88 | P8: =+K8+L8+M8-N8-O8 -> 264 | T8: 146 | U8: =+P8+Q8+R8-S8-T8 -> 118 | W8: 192 | X8: 18 | Y8: 292 | Z8: =+U8+V8+W8-X8-Y8 -> 0 | AB8: 108 | AD8: 84 | AE8: =+Z8+AA8+AB8-AC8-AD8 -> 24 | AF8: =+AE8 -> 24 | AG8: =IF((AF8-($AI8*(NETWORKDAYS(AN3,AN3)/$O$2))+AN8)<=0,0,AF8-($AI8*(NETWORKDAYS(AN3,AN3)/$O$2))+AN8) -> 234.9 | AI8: =AVERAGE(J8,O8,T8,Y8) -> 153 | AJ8: =+AI8*1.1 -> 168.3 | AK8: =+Z8/AI8 -> 0 | AL8: =+AG8/AI8 -> 1.5352941 | AM8: =+AH8/AI8 -> 0 | AN8: 216 | AO8: =AR8 -> 0 | AP8: 108 | AR8: =+AQ8*AP8 -> 0 | AS8: =+#REF!-0.4 -> #REF! | AT8: 1.5 | AU8: =+AT8-AS8 -> #REF! | AV8: =+AU8*AI8 -> #REF!
A9: 60 | B9: WERISNG | C9: ACTIVO | D9: 114054 | E9: GAJOS SAZONADOS | F9: 689 | H9: 66 | J9: 328 | K9: =F9+G9+H9+-I9-J9 -> 427 | N9: 93 | O9: 288 | P9: =+K9+L9+M9-N9-O9 -> 46 | R9: 756 | T9: 281 | U9: =+P9+Q9+R9-S9-T9 -> 521 | W9: 240 | X9: 13 | Y9: 218 | Z9: =+U9+V9+W9-X9-Y9 -> 530 | AD9: 69 | AE9: =+Z9+AA9+AB9-AC9-AD9 -> 461 | AF9: =+AE9 -> 461 | AG9: =IF((AF9-($AI9*(NETWORKDAYS(AN3,AN3)/$O$2))+AN9)<=0,0,AF9-($AI9*(NETWORKDAYS(AN3,AN3)/$O$2))+AN9) -> 559.70833 | AI9: =AVERAGE(J9,O9,T9,Y9) -> 278.75 | AJ9: =+AI9*1.1 -> 306.625 | AK9: =+Z9/AI9 -> 1.9013453 | AL9: =+AG9/AI9 -> 2.0079223 | AM9: =+AH9/AI9 -> 0 | AN9: 108 | AO9: =AR9 -> 0 | AP9: 108 | AR9: =+AQ9*AP9 -> 0 | AS9: =+#REF!-0.4 -> #REF! | AT9: 1.5 | AU9: =+AT9-AS9 -> #REF! | AV9: =+AU9*AI9 -> #REF!
A10: 60 | B10: WERISNG | C10: ACTIVO | D10: 102419 | E10: ONDULADA | F10: 172 | J10: 166 | K10: =F10+G10+H10+-I10-J10 -> 6 | M10: 3 | N10: 6 | O10: 3 | P10: =+K10+L10+M10-N10-O10 -> 0 | R10: 702 | T10: 277 | U10: =+P10+Q10+R10-S10-T10 -> 425 | W10: 20 | X10: 5 | Y10: 83 | Z10: =+U10+V10+W10-X10-Y10 -> 357 | AD10: 20 | AE10: =+Z10+AA10+AB10-AC10-AD10 -> 337 | AF10: =+AE10 -> 337 | AG10: =IF((AF10-($AI10*(NETWORKDAYS(AN3,AN3)/$O$2))+AN10)<=0,0,AF10-($AI10*(NETWORKDAYS(AN3,AN3)/$O$2))+AN10) -> 332.59167 | AI10: =AVERAGE(J10,O10,T10,Y10) -> 132.25 | AJ10: =+AI10*1.1 -> 145.475 | AK10: =+Z10/AI10 -> 2.6994329 | AL10: =+AG10/AI10 -> 2.5148708 | AM10: =+AH10/AI10 -> 0 | AO10: =AR10 -> 0 | AP10: 120 | AR10: =+AQ10*AP10 -> 0 | AS10: =+#REF!-0.4 -> #REF! | AT10: 1.5 | AU10: =+AT10-AS10 -> #REF! | AV10: =+AU10*AI10 -> #REF!
A11: 60 | B11: WERISNG | C11: SUSTITUTO - 102419 | D11: 70714906 | E11: PAPA ONDULADA SUSTITUTO DE 102419 | H11: 200 | J11: 104 | K11: =F11+G11+H11+-I11-J11 -> 96 | M11: 100 | N11: 5 | O11: 100 | P11: =+K11+L11+M11-N11-O11 -> 91 | T11: 11 | U11: =+P11+Q11+R11-S11-T11 -> 80 | Y11: 8 | Z11: =+U11+V11+W11-X11-Y11 -> 72 | AD11: 5 | AE11: =+Z11+AA11+AB11-AC11-AD11 -> 67 | AF11: =+AE11 -> 67 | AG11: =IF((AF11-($AI11*(NETWORKDAYS(AN3,AN3)/$O$2))+AN11)<=0,0,AF11-($AI11*(NETWORKDAYS(AN3,AN3)/$O$2))+AN11) -> 64.611111 | AI11: =AVERAGE(J11,O11,T11) -> 71.666667 | AJ11: =+AI11*1.1 -> 78.833333 | AK11: =+Z11/AI11 -> 1.0046512 | AL11: =+AG11/AI11 -> 0.90155039 | AM11: =+AH11/AI11 -> 0 | AO11: =AR11 -> 0 | AS11: =+#REF!-0.4 -> #REF!
A12: 60 | B12: WERISNG | C12: ACTIVO | D12: R00640 | E12: AROS DE CEBOLLA SUSTITUTO | H12: 100 | J12: 15 | K12: =F12+G12+H12+-I12-J12 -> 85 | N12: 4 | O12: 50 | P12: =+K12+L12+M12-N12-O12 -> 31 | R12: 61 | T12: 28 | U12: =+P12+Q12+R12-S12-T12 -> 64 | X12: 6 | Y12: 41 | Z12: =+U12+V12+W12-X12-Y12 -> 17 | AD12: 15 | AE12: =+Z12+AA12+AB12-AC12-AD12 -> 2 | AF12: =+AE12 -> 2 | AG12: =IF((AF12-($AI12*(NETWORKDAYS(AN3,AN3)/$O$2))+AN12)<=0,0,AF12-($AI12*(NETWORKDAYS(AN3,AN3)/$O$2))+AN12) -> 0.96666667 | AI12: =AVERAGE(J12,O12,T12) -> 31 | AJ12: =+AI12*1.1 -> 34.1 | AK12: =+Z12/AI12 -> 0.5483871 | AL12: =+AG12/AI12 -> 0.031182796 | AM12: =+AH12/AI12 -> 0 | AO12: =AR12 -> 0 | AS12: =+#REF!-0.4 -> #REF!
A13: 60 | B13: WERISNG | C13: SUSTITUTO - 102211 | D13: R00641 | E13: 7 MM NATURAL SUA SUSTITUTO DE 102211 | M13: 64 | N13: 0 | O13: 10 | P13: =+K13+L13+M13-N13-O13 -> 54 | T13: 15 | U13: =+P13+Q13+R13-S13-T13 -> 39 | Z13: =+U13+V13+W13-X13-Y13 -> 39 | AD13: 0 | AE13: =+Z13+AA13+AB13-AC13-AD13 -> 39 | AF13: =+AE13 -> 39 | AG13: =IF((AF13-($AI13*(NETWORKDAYS(AN3,AN3)/$O$2))+AN13)<=0,0,AF13-($AI13*(NETWORKDAYS(AN3,AN3)/$O$2))+AN13) -> 38.583333 | AI13: =AVERAGE(J13,O13,T13) -> 12.5 | AJ13: =+AI13*1.1 -> 13.75 | AK13: =+Z13/AI13 -> 3.12 | AL13: =+AG13/AI13 -> 3.0866667 | AM13: =+AH13/AI13 -> 0 | AO13: =AR13 -> 0 | AP13: 110 | AR13: =+AQ13*AP13 -> 0
D14: SUSTITUTO | F14: =SUM(F4:F13) -> 2767 | G14: =SUM(G4:G13) -> 3 | H14: =SUM(H4:H13) -> 1374 | I14: =SUM(I4:I13) -> 38 | J14: =SUM(J4:J13) -> 2561 | K14: =SUM(K4:K13) -> 1545 | L14: =SUM(L4:L13) -> 0 | M14: =SUM(M4:M13) -> 1019 | ... O14: =SUM(O4:O13) -> 1699 | P14: =+K14+L14+M14-N14-O14 -> 615 | Q14: =SUM(Q4:Q13) -> 0 | R14: =SUM(R4:R13) -> 3850 | S14: =SUM(S4:S13) -> 150 | T14: =SUM(T4:T13) -> 1971 | U14: =+P14+Q14+R14-S14-T14 -> 2344 | V14: =SUM(V4:V13) -> 0 | W14: =SUM(W4:W13) -> 1896 | X14: =SUM(X4:X13) -> 134 | Y14: =SUM(Y4:Y13) -> 2242 | Z14: =+U14+V14+W14-X14-Y14 -> 1864 | AA14: =SUM(AA4:AA13) -> 0 | AB14: =SUM(AB4:AB13) -> 2376 | AC14: =SUM(AC4:AC13) -> 0 | AD14: =SUM(AD4:AD13) -> 525 | AE14: =+Z14+AA14+AB14-AC14-AD14 -> 3715 | AI14: =SUM(AI4:AI13) -> 2177.0833 | AJ14: =SUM(AJ4:AJ13) -> 2394.7917 | AN14: =SUM(AN4:AN13) -> 1185 | AO14: =SUM(AO4:AO13) -> 0 | AQ14: =SUM(AQ4:AQ13) -> 0 | AR14: =SUM(AR4:AR13) -> 0
P15: =+K15+L15+M15-N15-O15 -> 0 | U15: =+P15+Q15+R15-S15-T15 -> 0 | AF15: INV ACTUAL + CONTENEDORES EN TRANSITO - VENTAS | AI15: Consumo mensual, Promedio año en curso | AJ15: Proyeccion de Ventas, con 10% al promedio del consumo mensual | AK15: Duracion de Inv. En Meses Considerando Inv Actual + Contenedores en Transito - Ventas | AN15: CONTENEDORES EN TRANSITO | AP15: Cajas x pallet | AQ15: SUGERENCIA DE PEDIDOS, DE CONTENEDOR A 21 PALLET
A16: PROMEDIO DÍAS DE TRANSITO | B16: PROVEEDOR | C16: ESTATUS DE PRODUCTOS | D16: CÓDIGO | E16: DESCRIPCIÓN | F16: INV DICIEMBRE 2025 | G16: COMPRAS | H16: Entradas | I16: Salidas | J16: VENTAS | K16: INV ENERO 2026 | L16: COMPRAS | M16: Entradas | N16: Salidas | O16: VENTAS | P16: INV FEB 2026 | Q16: COMPRAS | R16: Entradas | S16: Salidas | T16: VENTAS | U16: INV MARZO 2026 | V16: COMPRAS | W16: Entradas | X16: Salidas | Y16: VENTAS | Z16: INV ABRIL 2026 | AA16: COMPRAS | AB16: Entradas | AC16: Salidas | AD16: VENTAS | AE16: INV MAYO 2026 | AQ16: PALLET | AR16: CAJAS
A17: 60 | B17: AVIKO | C17: Oportunidad | D17: 260612 | E17: CASTEL STRAIGHT CUT FRIES 4X2500g | F17: 1 | K17: =F17+G17+H17-I17-J17 -> 1 | M17: 70 | O17: 1 | P17: =+K17+L17+M17-N17-O17 -> 70 | T17: 1 | U17: =+P17+Q17+R17-S17-T17 -> 69 | Y17: 69 | Z17: =+U17+V17+W17-X17-Y17 -> 0 | AE17: =+Z17+AA17+AB17-AC17-AD17 -> 0 | AI17: =AVERAGE(J17,O17) -> 1 | AJ17: =+AI17*1.1 -> 1.1 | AP17: 120
A18: 60 | B18: AVIKO | C18: Oportunidad | D18: 806982 | E18: AROS DE CEBOLLA 1X1000g | F18: 59 | J18: 52 | K18: =F18+G18+H18-I18-J18 -> 7 | N18: 7 | P18: =+K18+L18+M18-N18-O18 -> 0 | U18: =+P18+Q18+R18-S18-T18 -> 0 | Y18: 1 | AI18: =AVERAGE(J18,O18) -> 52 | AJ18: =+AI18*1.1 -> 57.2 | AK18: =+K18/AI18 -> 0.13461538
K19: =F19+G19+H19-I19-J19 -> 0 | P19: =+K19+L19+M19-N19-O19 -> 0 | U19: =+P19+Q19+R19-S19-T19 -> 0 | AP19: 108
K20: =F20+G20+H20-I20-J20 -> 0 | P20: =+K20+L20+M20-N20-O20 -> 0 | U20: =+P20+Q20+R20-S20-T20 -> 0 | AP20: 120
K21: =F21+G21+H21-I21-J21 -> 0 | P21: =+K21+L21+M21-N21-O21 -> 0 | U21: =+P21+Q21+R21-S21-T21 -> 0 | AP21: 120
F22: =SUM(F17:F21) -> 60 | G22: =SUM(G17:G21) -> 0 | H22: =SUM(H17:H21) -> 0 | I22: =SUM(I17:I21) -> 0 | J22: =SUM(J17:J21) -> 52 | K22: =SUM(K17:K21) -> 8 | L22: =SUM(L17:L21) -> 0 | M22: =SUM(M17:M21) -> 70 | ... P22: =SUM(P17:P21) -> 70 | T22: =SUM(T17:T18) -> 1 | U22: =+P22+Q22+R22-S22-T22 -> 69 | V22: =SUM(V17:V18) -> 0 | W22: =SUM(W17:W18) -> 0 | X22: =SUM(X17:X18) -> 0 | Y22: =SUM(Y17:Y18) -> 70 | Z22: =+U22+V22+W22-X22-Y22 -> -1 | AA22: =SUM(AA17:AA18) -> 0 | AB22: =SUM(AB17:AB18) -> 0 | AC22: =SUM(AC17:AC18) -> 0 | AD22: =SUM(AD17:AD18) -> 0 | AE22: =+Z22+AA22+AB22-AC22-AD22 -> -1 | AI22: =SUM(AI17:AI21) -> 53 | AJ22: =SUM(AJ17:AJ21) -> 58.3 | AQ22: =+SUM(AQ17:AQ19) -> 0 | AR22: =+SUM(AR17:AR19) -> 0
A24: PROMEDIO DÍAS DE TRANSITO | B24: PROVEEDOR | C24: ESTATUS DE PRODUCTOS | D24: CÓDIGO | E24: DESCRIPCIÓN | U24: =+P24+Q24+R24-S24-T24 -> 0 | Z24: INV ABRIL 2026 | AE24: INV MAYO 2026 | AF24: INV ACTUAL + CONTENEDORES EN TRANSITO - VENTAS | AI24: Consumo mensual, Promedio año en curso | AJ24: Proyeccion de Ventas, con 10% al promedio del consumo mensual | AK24: Duracion de Inv. En Meses Considerando Inv Actual + Contenedores en Transito - Ventas | AN24: CONTENEDORES EN TRANSITO | AP24: Cajas x pallet | AQ24: PALLET | AR24: CAJAS
A25: 60 | B25: KAIDA | C25: ACTIVO | D25: 505015 | E25: 10 MM NATURAL-KAIDA | K25: 0 | M25: 2000 | O25: 45 | P25: =+K25+L25+M25-N25-O25 -> 1955 | T25: 255 | U25: =+P25+Q25+R25-S25-T25 -> 1700 | V25: 25 | W25: 2221 | Y25: 1098 | Z25: =+U25+V25+W25-X25-Y25 -> 2848 | AB25: 1121 | AD25: 333 | AE25: =+Z25+AA25+AB25-AC25-AD25 -> 3636 | AF25: =IF((Z25-($AI25*(NETWORKDAYS(AN3,AN3)/$O$2))+AN25)<=0,0,Z25-($AI25*(NETWORKDAYS(AN3,AN3)/$O$2))+AN25) -> 2832.4667 | AG25: =IF((AF25-($AI25*(NETWORKDAYS(AN3,AN3)/$O$2))+AN25)<=0,0,AF25-($AI25*(NETWORKDAYS(AN3,AN3)/$O$2))+AN25) -> 2816.9333 | AH25: =IF((AG25-($AI25*(NETWORKDAYS(AO3,AO3)/$O$2))+AO25)<=0,0,AG25-($AI25*(NETWORKDAYS(AO3,AO3)/$O$2))+AO25) -> 2816.9333 | AI25: =AVERAGE(J25,O25,T25,Y25) -> 466 | AJ25: =+AI25*1.1 -> 512.6 | AK25: =+Z25/AI25 -> 6.111588 | AL25: =+AG25/AI25 -> 6.0449213 | AM25: =+AH25/AI25 -> 6.0449213 | AO25: =+AR25 -> 0 | AR25: =+AQ25*AP25 -> 0
K26: =SUM(K25) -> 0 | M26: =+M25 -> 2000 | O26: =+O25 -> 45 | P26: =+P25 -> 1955 | T26: =+T25 -> 255 | U26: =+U25 -> 1700 | V26: =+V25 -> 25 | W26: =+W25 -> 2221 | X26: =+X25 -> 0 | Y26: =+Y25 -> 1098 | Z26: =+Z25 -> 2848 | AA26: =+AA25 -> 0 | ... AE26: =+AE25 -> 3636
F28: =+F22+F14 -> 2827 | G28: =+G22+G14 -> 3 | H28: =+H22+H14 -> 1374 | I28: =+I22+I14 -> 38 | J28: =+J22+J14 -> 2613 | K28: =+K22+K14 -> 1553 | L28: =+L22+L14+L26 -> 0 | M28: =+M22+M14+M26 -> 3089 | N28: =+N22+N14+N26 -> 257 | O28: =+O22+O14+O26 -> 1745 | P28: =+P22+P14+P26 -> 2640 | T28: =+T22+T14+T26 -> 2227 | U28: =+U22+U14+U26 -> 4113 | V28: =+V22+V14+V26 -> 25 | W28: =+W22+W14+W26 -> 4117 | X28: =+X22+X14+X26 -> 134 | Y28: =+Y22+Y14+Y26 -> 3410 | Z28: =+Z22+Z14+Z26 -> 4711 | AA28: =+AA22+AA14+AA26 -> 0 | ... AE28: =+AE22+AE14+AE26 -> 7350 | AI28: =+Y28 -> 3410
J29: ESPACIOS | K29: =+K28/50 -> 31.06 | O29: ESPACIOS | P29: =+P28/50 -> 52.8 | AF29: ROT | AI29: =+AE28/Y28 -> 2.1554252

Sheet RESUMEN LEÓN
J1: INV ACTUAL + CONTENEDORES EN TRANSITO - VENTAS | O1: Consumo mensual, Promedio año en curso | P1: Proyeccion de Ventas, con 20% al promedio del consumo mensual | Q1: Duracion de Inv. En Meses Considerando Inv Actual + Contenedores en Transito - Ventas | T1: CONTENEDORES EN TRANSITO | V1: SUGERENCIA DE PEDIDOS, DE CONTENEDOR A 21 PALLET
T2: C-426 PTO 31/05 | U2: C-429 PTO 20/06
A3: PROMEDIO DÍAS DE TRANSITO | B3: PROVEEDOR | C3: ESTATUS DEL PRODUCTO | D3: CÓDIGO | E3: DESCRIPCIÓN | F3: BAJO CERO | G3: VULPES | H3: TOTAL INVENTARIO MAYO | I3: VENTAS DEL MES DE MAYO | J3: ACTUAL | K3: C-426 | L3: C-429 | M3: MENUDEO | N3: MAYOREO | Q3: ACTUAL | R3: C-426 | S3: C-429 | T3: 46178 | U3: 46199 | V3: Cjas x Tarima | W3: PALLET | X3: CAJAS
A4: 60 | B4: AVIKO | C4: ACTIVO | D4: 807769 | E4: R - PAPAS FRITAS CORTE REG 10 X 1000G | F4: =VLOOKUP(D4,'BAJO CERO'!$A$1:$AB$86,28,0) -> 177 | G4: =VLOOKUP(D4,'VULPES PAPAS'!$A$1:$AB$36,28,0) -> 23.9 | H4: =SUM(F4:G4) -> 200.9 | I4: =VLOOKUP(D4,'VULPES PAPAS'!$A:$AB,27,0) -> 2 | J4: =+H4 -> 200.9 | K4: =IF((J4-($O4*(NETWORKDAYS(TODAY(),$T$3)/45))+T4)<=0,0,J4-($O4*(NETWORKDAYS(TODAY(),$T$3)/45))+T4) -> 300.19 | L4: =IF((K4-($O4*(NETWORKDAYS(TODAY(),$T$3)/45))+U4)<=0,0,K4-($O4*(NETWORKDAYS(TODAY(),$U$3)/45))+U4) -> 262.22167 | O4: =AVERAGE('VULPES PAPAS'!G2,'VULPES PAPAS'!L2,'VULPES PAPAS'!Q2,'VULPES PAPAS'!V2) -> 51.775 | P4: =+O4*1.2 -> 62.13 | Q4: =+H4/O4 -> 3.8802511 | R4: =+K4/O4 -> 5.797972 | S4: =+L4/O4 -> 5.0646387 | T4: 120 | V4: 120 | X4: =+W4*V4 -> 0
A5: 60 | B5: AVIKO | C5: ACTIVO | D5: 807329 | E5: R - AVIKO ORIGINAL 20X450G | F5: =VLOOKUP(D5,'BAJO CERO'!$A$1:$AB$86,28,0) -> 145 | G5: =VLOOKUP(D5,'VULPES PAPAS'!$A$1:$AB$36,28,0) -> 61.5 | H5: =SUM(F5:G5) -> 206.5 | I5: =VLOOKUP(D5,'VULPES PAPAS'!$A:$AB,27,0) -> 0 | J5: =+H5 -> 206.5 | K5: =IF((J5-($O5*(NETWORKDAYS(TODAY(),$T$3)/45))+T5)<=0,0,J5-($O5*(NETWORKDAYS(TODAY(),$T$3)/45))+T5) -> 203.45 | L5: =IF((K5-($O5*(NETWORKDAYS(TODAY(),$T$3)/45))+U5)<=0,0,K5-($O5*(NETWORKDAYS(TODAY(),$U$3)/45))+U5) -> 197.85833 | O5: =AVERAGE('VULPES PAPAS'!G3,'VULPES PAPAS'!L3,'VULPES PAPAS'!Q3,'VULPES PAPAS'!V3) -> 7.625 | P5: =+O5*1.2 -> 9.15 | Q5: =+H5/O5 -> 27.081967 | R5: =+K5/O5 -> 26.681967 | S5: =+L5/O5 -> 25.948634 | V5: 120 | X5: =+W5*V5 -> 0
A6: 60 | B6: AVIKO | C6: ACTIVO | D6: 805411 | E6: R - PAPAS FRITAS ZIGZAG 12/750GRS | F6: =VLOOKUP(D6,'BAJO CERO'!$A$1:$AB$86,28,0) -> 0 | G6: =VLOOKUP(D6,'VULPES PAPAS'!$A$1:$AB$36,28,0) -> 34.92 | H6: =SUM(F6:G6) -> 34.92 | I6: =VLOOKUP(D6,'VULPES PAPAS'!$A:$AB,27,0) -> 0 | J6: =+H6 -> 34.92 | K6: =IF((J6-($O6*(NETWORKDAYS(TODAY(),$T$3)/45))+T6)<=0,0,J6-($O6*(NETWORKDAYS(TODAY(),$T$3)/45))+T6) -> 496.612 | L6: =IF((K6-($O6*(NETWORKDAYS(TODAY(),$T$3)/45))+U6)<=0,0,K6-($O6*(NETWORKDAYS(TODAY(),$U$3)/45))+U6) -> 823.04733 | O6: =AVERAGE('VULPES PAPAS'!G4,'VULPES PAPAS'!L4,'VULPES PAPAS'!Q4,'VULPES PAPAS'!V4) -> 45.77 | P6: =+O6*1.2 -> 54.924 | Q6: =+H6/O6 -> 0.76294516 | R6: =+K6/O6 -> 10.850164 | S6: =+L6/O6 -> 17.982245 | T6: 480 | U6: 360 | V6: 120 | X6: =+W6*V6 -> 0
A7: 60 | B7: AVIKO | C7: ACTIVO | D7: 807679 | E7: R - AVIKO SPICY WEDGES 20X500G | F7: 0 | G7: =VLOOKUP(D7,'VULPES PAPAS'!$A$1:$AB$36,28,0) -> 60.45 | H7: =SUM(F7:G7) -> 60.45 | I7: =VLOOKUP(D7,'VULPES PAPAS'!$A:$AB,27,0) -> 70 | J7: =+H7 -> 60.45 | K7: =IF((J7-($O7*(NETWORKDAYS(TODAY(),$T$3)/45))+T7)<=0,0,J7-($O7*(NETWORKDAYS(TODAY(),$T$3)/45))+T7) -> 145.02 | L7: =IF((K7-($O7*(NETWORKDAYS(TODAY(),$T$3)/45))+U7)<=0,0,K7-($O7*(NETWORKDAYS(TODAY(),$U$3)/45))+U7) -> 440.065 | O7: =AVERAGE('VULPES PAPAS'!G5,'VULPES PAPAS'!L5,'VULPES PAPAS'!Q5,'VULPES PAPAS'!V5) -> 88.575 | P7: =+O7*1.2 -> 106.29 | Q7: =+H7/O7 -> 0.68247248 | R7: =+K7/O7 -> 1.6372566 | S7: =+L7/O7 -> 4.9682755 | T7: 120 | U7: 360 | V7: 120 | X7: =+W7*V7 -> 0
A8: 60 | B8: AVIKO | C8: OPORTUNIDAD | D8: 260612 | E8: CASTEL STRAIGHT CUT FRIES 4X2500g | F8: 0 | G8: =VLOOKUP(D8,'VULPES PAPAS'!$A$1:$AB$36,28,0) -> 0.5 | H8: =SUM(F8:G8) -> 0.5 | I8: =VLOOKUP(D8,'VULPES PAPAS'!$A:$AB,27,0) -> 0 | J8: =+H8 -> 0.5 | K8: =IF((J8-($O8*(NETWORKDAYS(TODAY(),$T$3)/45))+T8)<=0,0,J8-($O8*(NETWORKDAYS(TODAY(),$T$3)/45))+T8) -> 0 | L8: =IF((K8-($O8*(NETWORKDAYS(TODAY(),$T$3)/45))+U8)<=0,0,K8-($O8*(NETWORKDAYS(TODAY(),$U$3)/45))+U8) -> 0 | O8: =AVERAGE('VULPES PAPAS'!G6,'VULPES PAPAS'!L6,'VULPES PAPAS'!Q6,'VULPES PAPAS'!V6) -> 85.125 | P8: =+O8*1.2 -> 102.15 | Q8: =+H8/O8 -> 0.0058737151 | R8: =+K8/O8 -> 0 | S8: =+L8/O8 -> 0 | V8: 120 | X8: =+W8*V8 -> 0
A9: 60 | B9: AVIKO | C9: OPORTUNIDAD | D9: 802142 | E9: AVIKO STRAIGHT CUT 3/8 4x2500g | F9: =VLOOKUP(D9,'BAJO CERO'!$A$1:$AB$86,28,0) -> 0 | G9: =VLOOKUP(D9,'VULPES PAPAS'!$A$1:$AB$36,28,0) -> 0.25 | H9: =SUM(F9:G9) -> 0.25 | I9: =VLOOKUP(D9,'VULPES PAPAS'!$A:$AB,27,0) -> 0 | J9: =+H9 -> 0.25 | K9: =IF((J9-($O9*(NETWORKDAYS(TODAY(),$T$3)/45))+T9)<=0,0,J9-($O9*(NETWORKDAYS(TODAY(),$T$3)/45))+T9) -> 0 | L9: =IF((K9-($O9*(NETWORKDAYS(TODAY(),$T$3)/45))+U9)<=0,0,K9-($O9*(NETWORKDAYS(TODAY(),$U$3)/45))+U9) -> 0 | O9: =AVERAGE('VULPES PAPAS'!G7,'VULPES PAPAS'!L7,'VULPES PAPAS'!Q7,'VULPES PAPAS'!V7) -> 46.75 | P9: =+O9*1.2 -> 56.1 | S9: =+L9/O9 -> 0 | X9: =+W9*V9 -> 0
A10: 60 | B10: AVIKO | C10: ACTIVO | D10: 806982 | E10: AVIKO BREADED ONION RINGS 6x1000g | F10: =VLOOKUP(D10,'BAJO CERO'!$A$1:$AB$86,28,0) -> 173 | G10: =VLOOKUP(D10,'VULPES PAPAS'!$A$1:$AB$36,28,0) -> 92.67 | H10: =SUM(F10:G10) -> 265.67 | I10: =VLOOKUP(D10,'VULPES PAPAS'!$A:$AB,27,0) -> 2 | J10: =+H10 -> 265.67 | K10: =IF((J10-($O10*(NETWORKDAYS(TODAY(),$T$3)/45))+T10)<=0,0,J10-($O10*(NETWORKDAYS(TODAY(),$T$3)/45))+T10) -> 256.087 | L10: =IF((K10-($O10*(NETWORKDAYS(TODAY(),$T$3)/45))+U10)<=0,0,K10-($O10*(NETWORKDAYS(TODAY(),$U$3)/45))+U10) -> 238.51817 | O10: =AVERAGE('VULPES PAPAS'!G8,'VULPES PAPAS'!L8,'VULPES PAPAS'!Q8,'VULPES PAPAS'!V8) -> 23.9575 | P10: =+O10*1.2 -> 28.749 | Q10: =+H10/O10 -> 11.08922 | R10: =+J10/O10 -> 11.08922 | S10: =+L10/O10 -> 9.9558872 | V10: 108 | X10: =+W10*V10 -> 0
A11: 60 | B11: AVIKO | C11: OPORTUNIDAD | D11: 806685 | E11: AVIKO H PREM.CRUNCH SHOESTRING 7MM 4X2270G | F11: =VLOOKUP(D11,'BAJO CERO'!$A$1:$AB$86,28,0) -> 0 | G11: =VLOOKUP(D11,'VULPES PAPAS'!$A$1:$AB$36,28,0) -> 0.5 | H11: =+F11+G11 -> 0.5 | I11: =VLOOKUP(D11,'VULPES PAPAS'!$A:$AB,27,0) -> 0 | J11: =+H11 -> 0.5 | K11: =IF((J11-($O11*(NETWORKDAYS(TODAY(),$T$3)/45))+T11)<=0,0,J11-($O11*(NETWORKDAYS(TODAY(),$T$3)/45))+T11) -> 0.1 | L11: =IF((K11-($O11*(NETWORKDAYS(TODAY(),$T$3)/45))+U11)<=0,0,K11-($O11*(NETWORKDAYS(TODAY(),$U$3)/45))+U11) -> 0 | O11: =+'VULPES PAPAS'!V9 -> 1 | P11: =+O11*1.2 -> 1.2 | S11: =+L11/O11 -> 0 | X11: =+W11*V11 -> 0
A12: 60 | B12: AVIKO | C12: OPORTUNIDAD | D12: 804104 | E12: HASHBROWN TRIANG | F12: =VLOOKUP(D12,'BAJO CERO'!$A$1:$AB$86,28,0) -> 0 | G12: =VLOOKUP(D12,'VULPES PAPAS'!$A$1:$AB$36,28,0) -> 0.25 | H12: =+F12+G12 -> 0.25 | I12: =VLOOKUP(D12,'VULPES PAPAS'!$A:$AB,27,0) -> 0 | J12: =+H12 -> 0.25 | K12: =IF((J12-($O12*(NETWORKDAYS(TODAY(),$T$3)/45))+T12)<=0,0,J12-($O12*(NETWORKDAYS(TODAY(),$T$3)/45))+T12) -> 0 | L12: =IF((K12-($O12*(NETWORKDAYS(TODAY(),$T$3)/45))+U12)<=0,0,K12-($O12*(NETWORKDAYS(TODAY(),$U$3)/45))+U12) -> 0 | O12: =+'VULPES PAPAS'!V10 -> 2 | P12: =+O12*1.2 -> 2.4 | S12: =+L12/O12 -> 0 | X12: =+W12*V12 -> 0
B13: AVIKO | C13: INACTIVO | D13: 806694 | E13: AVIKO H PREM CRUNCH 9.5 mm 3/8 4x2270g | I13: 0 | J13: =+H13 -> 0 | K13: =IF((J13-($O13*(NETWORKDAYS(TODAY(),$T$3)/45))+T13)<=0,0,J13-($O13*(NETWORKDAYS(TODAY(),$T$3)/45))+T13) -> 0 | L13: =IF((K13-($O13*(NETWORKDAYS(TODAY(),$T$3)/45))+U13)<=0,0,K13-($O13*(NETWORKDAYS(TODAY(),$U$3)/45))+U13) -> 0 | O13: =+'VULPES PAPAS'!V11 -> 0 | S13: =+L13/O13 -> #DIV/0! | V13: 108 | X13: =+W13*V13 -> 0
F14: =VLOOKUP(D14,'VULPES PAPAS'!$A:$R,18,0) -> #N/A | L14: =IF((I14-($O14*(NETWORKDAYS(TODAY(),$U$3)/45))+U14)<=0,0,I14-($O14*(NETWORKDAYS(TODAY(),$T$3)/45))+U14) -> 0 | O14: =+'VULPES PAPAS'!V12 -> 0
F15: =VLOOKUP(D15,'VULPES PAPAS'!$A:$R,18,0) -> #N/A | L15: =IF((I15-($O15*(NETWORKDAYS(TODAY(),$U$3)/45))+U15)<=0,0,I15-($O15*(NETWORKDAYS(TODAY(),$T$3)/45))+U15) -> 0 | O15: =+'VULPES PAPAS'!V13 -> 0
F16: =VLOOKUP(D16,'VULPES PAPAS'!$A:$R,18,0) -> #N/A | L16: =IF((I16-($O16*(NETWORKDAYS(TODAY(),$U$3)/45))+U16)<=0,0,I16-($O16*(NETWORKDAYS(TODAY(),$T$3)/45))+U16) -> 0 | O16: =+'VULPES PAPAS'!V14 -> 0
F17: =SUM(F4:F12) -> 495 | G17: =SUM(G4:G16) -> 274.94 | H17: =SUM(H4:H16) -> 769.94 | I17: =SUM(I4:I16) -> 74 | O17: =SUM(O4:O16) -> 352.5775 | P17: =SUM(P4:P16) -> 423.093 | T17: =SUM(T4:T13) -> 720 | U17: =SUM(U4:U13) -> 720 | V17: =SUM(V4:V16) -> 816 | W17: =SUM(W4:W13) -> 0 | X17: =SUM(X4:X13) -> 0
J18: INV ACTUAL + CONTENEDORES EN TRANSITO - VENTAS | O18: Consumo mensual, Promedio año en curso | P18: Proyeccion de Ventas, con 20% al promedio del consumo mensual | Q18: Duracion de Inv. En Meses Considerando Inv Actual + Contenedores en Transito - Ventas | T18: CONTENEDORES EN TRANSITO | V18: SUGERENCIA DE PEDIDOS, DE CONTENEDOR A 21 PALLET
T19: C-116 PTO ASAP
A20: PROMEDIO DÍAS DE TRANSITO | B20: PROVEEDOR | C20: ESTATUS DEL PRODUCTO | D20: CÓDIGO | E20: DESCRIPCIÓN | F20: BAJO CERO | G20: VULPES | H20: TOTAL INVENTARIO MAYO | I20: VENTAS DEL MES DE MAYO | J20: ACTUAL | K20: C-116 | M20: MENUDEO | N20: MAYOREO | Q20: ACTUAL | R20: C-116 | T20: 46188 | V20: Cjas x Tarima | W20: PALLET | X20: CAJAS
A21: 60 | B21: WERSING | C21: ACTIVO | D21: 102341 | E21: 10 MM CON COBERTURA | F21: =VLOOKUP(D21,'BAJO CERO'!$A$1:$AB$86,28,0) -> 385 | G21: =VLOOKUP(D21,'VULPES PAPAS'!$A$1:$AB$36,28,0) -> 49 | H21: =SUM(F21:G21) -> 434 | I21: =VLOOKUP(D21,'VULPES PAPAS'!$A:$AB,27,0) -> 25 | J21: =+H21 -> 434 | K21: =IF((J21-($O21*(NETWORKDAYS(TODAY(),$T$20)/45))+T21)<=0,0,J21-($O21*(NETWORKDAYS(TODAY(),$T$20)/45))+T21) -> 715.76667 | O21: =AVERAGE('VULPES PAPAS'!G21,'VULPES PAPAS'!L21,'VULPES PAPAS'!Q21,'VULPES PAPAS'!V21) -> 371.6875 | P21: =+O21*1.2 -> 446.025 | Q21: =+J21/O21 -> 1.1676476 | R21: =+K21/O21 -> 1.9257217 | T21: 480 | V21: 120 | X21: =+W21*V21 -> 0
A22: 60 | B22: WERSING | C22: ACTIVO | D22: 102310 | E22: 7 MM CON COBERTURA | F22: =VLOOKUP(D22,'BAJO CERO'!$A$1:$AB$86,28,0) -> 273 | G22: =VLOOKUP(D22,'VULPES PAPAS'!$A$1:$AB$36,28,0) -> 66.7 | H22: =SUM(F22:G22) -> 339.7 | I22: =VLOOKUP(D22,'VULPES PAPAS'!$A:$AB,27,0) -> 16 | J22: =+H22 -> 339.7 | K22: =IF((J22-($O22*(NETWORKDAYS(TODAY(),$T$20)/45))+T22)<=0,0,J22-($O22*(NETWORKDAYS(TODAY(),$T$20)/45))+T22) -> 325.62667 | O22: =AVERAGE('VULPES PAPAS'!G22,'VULPES PAPAS'!L22,'VULPES PAPAS'!Q22,'VULPES PAPAS'!V22) -> 26.3875 | P22: =+O22*1.2 -> 31.665 | Q22: =+H22/O22 -> 12.87352 | R22: =+K22/O22 -> 12.340186 | V22: 108 | X22: =+W22*V22 -> 0
A23: 60 | B23: WERSING | C23: ACTIVO | D23: 102211 | E23: 7 MM NATURAL | F23: =VLOOKUP(D23,'BAJO CERO'!$A$1:$AB$86,28,0) -> 139 | G23: =VLOOKUP(D23,'VULPES PAPAS'!$A$1:$AB$36,28,0) -> 40 | H23: =SUM(F23:G23) -> 179 | I23: =VLOOKUP(D23,'VULPES PAPAS'!$A:$AB,27,0) -> 64 | J23: =+H23 -> 179 | K23: =IF((J23-($O23*(NETWORKDAYS(TODAY(),$T$20)/45))+T23)<=0,0,J23-($O23*(NETWORKDAYS(TODAY(),$T$20)/45))+T23) -> 251.16667 | O23: =AVERAGE('VULPES PAPAS'!G23,'VULPES PAPAS'!L23,'VULPES PAPAS'!Q23,'VULPES PAPAS'!V23) -> 100.9375 | P23: =+O23*1.2 -> 121.125 | Q23: =+H23/O23 -> 1.7733746 | R23: =+K23/O23 -> 2.4883385 | T23: 126 | V23: 108 | X23: =+W23*V23 -> 0
A24: 60 | B24: WERSING | C24: ACTIVO | D24: 104215 | E24: 10 MM CON COBERTURA Y CASCARA | F24: =VLOOKUP(D24,'BAJO CERO'!$A$1:$AB$86,28,0) -> 279 | G24: =VLOOKUP(D24,'VULPES PAPAS'!$A$1:$AB$36,28,0) -> 68.75 | H24: =SUM(F24:G24) -> 347.75 | I24: =VLOOKUP(D24,'VULPES PAPAS'!$A:$AB,27,0) -> 25 | J24: =+H24 -> 347.75 | K24: =IF((J24-($O24*(NETWORKDAYS(TODAY(),$T$20)/45))+T24)<=0,0,J24-($O24*(NETWORKDAYS(TODAY(),$T$20)/45))+T24) -> 293.01667 | O24: =AVERAGE('VULPES PAPAS'!G24,'VULPES PAPAS'!L24,'VULPES PAPAS'!Q24,'VULPES PAPAS'!V24) -> 102.625 | P24: =+O24*1.2 -> 123.15 | Q24: =+H24/O24 -> 3.3885505 | R24: =+K24/O24 -> 2.8552172 | T24: 0 | V24: 108 | X24: =+W24*V24 -> 0
A25: 60 | B25: WERSING | C25: ACTIVO | D25: 114054 | E25: GAJOS SAZONADOS | F25: =VLOOKUP(D25,'BAJO CERO'!$A$1:$AB$86,28,0) -> 128 | G25: =VLOOKUP(D25,'VULPES PAPAS'!$A$1:$AB$36,28,0) -> 21.45 | H25: =SUM(F25:G25) -> 149.45 | I25: =VLOOKUP(D25,'VULPES PAPAS'!$A:$AB,27,0) -> 39 | J25: =+H25 -> 149.45 | K25: =IF((J25-($O25*(NETWORKDAYS(TODAY(),$T$20)/45))+T25)<=0,0,J25-($O25*(NETWORKDAYS(TODAY(),$T$20)/45))+T25) -> 326.24333 | O25: =AVERAGE('VULPES PAPAS'!G25,'VULPES PAPAS'!L25,'VULPES PAPAS'!Q25,'VULPES PAPAS'!V25) -> 73.5125 | P25: =+O25*1.2 -> 88.215 | Q25: =+H25/O25 -> 2.0329876 | R25: =+K25/O25 -> 4.4379301 | T25: 216 | V25: 120 | X25: =+W25*V25 -> 0
A26: 60 | B26: WERSING | C26: ACTIVO | D26: 102419 | E26: ONDULADA | F26: =VLOOKUP(D26,'BAJO CERO'!$A$1:$AB$86,28,0) -> 226 | G26: =VLOOKUP(D26,'VULPES PAPAS'!$A$1:$AB$36,28,0) -> 28.25 | H26: =SUM(F26:G26) -> 254.25 | I26: =VLOOKUP(D26,'VULPES PAPAS'!$A:$AB,27,0) -> 38 | J26: =+H26 -> 254.25 | K26: =IF((J26-($O26*(NETWORKDAYS(TODAY(),$T$20)/45))+T26)<=0,0,J26-($O26*(NETWORKDAYS(TODAY(),$T$20)/45))+T26) -> 330.81667 | O26: =AVERAGE('VULPES PAPAS'!G26,'VULPES PAPAS'!L26,'VULPES PAPAS'!Q26,'VULPES PAPAS'!V26) -> 58.9375 | P26: =+O26*1.2 -> 70.725 | Q26: =+H26/O26 -> 4.3138918 | R26: =+K26/O26 -> 5.6130081 | T26: 108 | V26: 108 | X26: =+W26*V26 -> 0
A27: 60 | B27: WERSING | C27: ACTIVO | D27: 102013 | E27: 10 MM NATURAL | F27: =+'BAJO CERO'!AB20 -> 158 | G27: =VLOOKUP(D27,'VULPES PAPAS'!$A$1:$AB$36,28,0) -> 69.23 | H27: =SUM(F27:G27) -> 227.23 | I27: =VLOOKUP(D27,'VULPES PAPAS'!$A:$AB,27,0) -> 38 | J27: =+H27 -> 227.23 | K27: =IF((J27-($O27*(NETWORKDAYS(TODAY(),$T$20)/45))+T27)<=0,0,J27-($O27*(NETWORKDAYS(TODAY(),$T$20)/45))+T27) -> 371.16067 | O27: =AVERAGE('VULPES PAPAS'!G27,'VULPES PAPAS'!L27,'VULPES PAPAS'!Q27,'VULPES PAPAS'!V27) -> 202.63 | P27: =+O27*1.2 -> 243.156 | Q27: =+H27/O27 -> 1.1214035 | R27: =+K27/O27 -> 1.8317163 | T27: 252 | V27: 108 | X27: =+W27*V27 -> 0
A28: 60 | B28: WERSING | D28: 01KFS02 | E28: PAPA ON DULADA SUSTITUTO | F28: =VLOOKUP(D28,'BAJO CERO'!$A$1:$AB$86,28,0) -> #N/A | G28: =VLOOKUP(D28,'VULPES PAPAS'!$A$1:$AB$36,28,0) -> 0 | H28: =SUM(F28:G28) -> #N/A | I28: =VLOOKUP(D28,'VULPES PAPAS'!$A:$AB,27,0) -> 0 | J28: =+H28 -> #N/A | K28: =IF((J28-($O28*(NETWORKDAYS(TODAY(),$T$20)/45))+T28)<=0,0,J28-($O28*(NETWORKDAYS(TODAY(),$T$20)/45))+T28) -> #N/A | P28: =+O28*1.2 -> 0 | Q28: =+H28/O28 -> #N/A | R28: =+K28/O28 -> #N/A | T28: 0 | V28: 108
A29: 60 | B29: WERSING | D29: 01KFS03 | E29: PAPA 1/4 NATURAL SUSTITUTO | F29: =VLOOKUP(D29,'BAJO CERO'!$A$1:$AB$86,28,0) -> #N/A | G29: =VLOOKUP(D29,'VULPES PAPAS'!$A$1:$AB$36,28,0) -> 0 | H29: =SUM(F29:G29) -> #N/A | I29: =VLOOKUP(D29,'VULPES PAPAS'!$A:$AB,27,0) -> 0 | J29: =+H29 -> #N/A | K29: =IF((J29-($O29*(NETWORKDAYS(TODAY(),$T$20)/45))+T29)<=0,0,J29-($O29*(NETWORKDAYS(TODAY(),$T$20)/45))+T29) -> #N/A | P29: =+O29*1.2 -> 0 | R29: =+K29/O29 -> #N/A
A30: 60 | B30: WERSING | C30: SUSTITUTO | D30: 01RCA01 | E30: PAPA CHIPPERBEC SUSTITUTO 102211 | G30: =VLOOKUP(D30,'VULPES PAPAS'!$A$1:$AB$36,28,0) -> 0 | H30: =SUM(F30:G30) -> 0 | I30: =VLOOKUP(D30,'VULPES PAPAS'!$A:$AB,27,0) -> 3 | J30: =+H30 -> 0 | K30: =IF((J30-($O30*(NETWORKDAYS(TODAY(),$T$20)/45))+T30)<=0,0,J30-($O30*(NETWORKDAYS(TODAY(),$T$20)/45))+T30) -> 0 | O30: =AVERAGE('VULPES PAPAS'!L14,'VULPES PAPAS'!Q14,'VULPES PAPAS'!V14) -> 25 | P30: =+O30*1.2 -> 30 | Q30: =+H30/O30 -> 0 | R30: =+K30/O30 -> 0
A31: 60 | B31: WERSING | C31: SUSTITUTO | D31: 01RCA02 | E31: PAPA RECTA 3/8 SUSTITUTO 102013 | G31: =VLOOKUP(D31,'VULPES PAPAS'!$A$1:$AB$36,28,0) -> 0.61 | H31: =SUM(F31:G31) -> 0.61 | I31: =VLOOKUP(D31,'VULPES PAPAS'!$A:$AB,27,0) -> 11 | J31: =+H31 -> 0.61 | K31: =IF((H31-($O31*(NETWORKDAYS(TODAY(),$T$20)/45))+T31)<=0,0,H31-($O31*(NETWORKDAYS(TODAY(),$T$20)/45))+T31) -> 0 | O31: =AVERAGE('VULPES PAPAS'!Q16,'VULPES PAPAS'!V16) -> 44.165 | P31: =+O31*1.2 -> 52.998 | Q31: =+H31/O31 -> 0.013811842 | R31: =+K31/O31 -> 0 | T31: 0 | V31: 108
F32: =+F21+F22+F23+F24+F25+F26+F27+F30+F31 -> 1588 | G32: =SUM(G21:G31) -> 343.99 | H32: =+H21+H22+H23+H24+H25+H26+H27+H30+H31 -> 1931.99 | I32: =SUM(I21:I31) -> 259 | O32: =SUM(O21:O28) -> 936.7175 | P32: =SUM(P21:P28) -> 1124.061 | T32: =SUM(T21:T31) -> 1182 | V32: =SUM(V21:V31) -> 996 | W32: =SUM(W21:W27) -> 0 | X32: =SUM(X21:X27) -> 0
A34: PROMEDIO DÍAS DE TRANSITO | B34: PRVEEDOR | C34: ESTATUS DEL PRODUCTO | D34: CÓDIGO | E34: DESCRIPCIÓN | F34: BAJO CERO | G34: VULPES | H34: TOTAL INVENTARIO | I34: VENTAS DEL MES DE MAYO
A35: 60 | B35: KAIDA | C35: ACTIVO | D35: 505015 | E35: 10 MM NATURAL-KAIDA | F35: =VLOOKUP(D35,'BAJO CERO'!$A$1:$AB$86,28,0)-650 -> 2193.16 | G35: =VLOOKUP(D35,'VULPES PAPAS'!$A$1:$AB$36,28,0)-650 -> 117.31 | H35: =+F35+G35 -> 2310.47 | I35: =VLOOKUP(D35,'VULPES PAPAS'!$A:$AB,27,0) -> 580 | J35: =+H35 -> 2310.47 | K35: =IF((J35-($O35*(NETWORKDAYS(TODAY(),$T$20)/45))+T35)<=0,0,J35-($O35*(NETWORKDAYS(TODAY(),$T$20)/45))+T35) -> 1982.2007 | O35: =AVERAGE('VULPES PAPAS'!G33,'VULPES PAPAS'!L33,'VULPES PAPAS'!Q33,'VULPES PAPAS'!V33) -> 615.505 | P35: =+O35*1.2 -> 738.606 | Q35: =+H35/O35 -> 3.7537794 | R35: =+K35/O35 -> 3.2204461 | V35: 108 | X35: =+W35*V35 -> 0
F36: =SUM(F35) -> 2193.16 | G36: =SUM(G35) -> 117.31 | H36: =SUM(H35) -> 2310.47 | I36: =SUM(I35) -> 580
F37: =+F36+F32+F17 -> 4276.16 | G37: =+G36+G32+G17 -> 736.24 | H37: =+H36+H32+H17 -> 5012.4 | I37: =+I36+I32+I17 -> 913 | J37: =+H37/'VULPES PAPAS'!Q35 -> 3.5197461
F38: =+F37-'BAJO CERO'!AB35 -> -650 | G38: =+G37-'VULPES PAPAS'!AB35 -> -650 | H38: =+H37-'VULPES PAPAS'!AB35-'BAJO CERO'!AB35 -> -1300

Sheet VULPES PAPAS
A1: CÓDIGO | B1: DESCRIPCIÓN | C1: INV DICIEMBRE 2025 | D1: COMPRAS | E1: Entradas | F1: Salidas | G1: VENTAS | H1: INV ENERO 2026 | I1: COMPRAS | J1: Entradas | K1: Salidas | L1: VENTAS | M1: INV FEB 2026 | N1: COMPRAS | O1: Entradas | P1: Salidas | Q1: VENTAS | R1: INV MARZO 2026 | S1: COMPRAS | T1: Entradas | U1: Salidas | V1: VENTAS | W1: INV ABRIL 2026 | X1: COMPRAS | Y1: Entradas | Z1: Salidas | AA1: VENTAS | AB1: INV MAYO 2026
A2: 807769 | B2: PAPAS FRITAS CORTE REG 10 X 1000G | C2: 208 | F2: 0 | G2: 99 | H2: =+C2+D2+E2-F2-G2 -> 109 | L2: 77 | M2: =+H2+I2+J2-K2-L2 -> 32 | Q2: 22 | R2: =+M2+N2+O2-P2-Q2 -> 10 | T2: 25 | V2: 9.1 | W2: =+R2+S2+T2-U2-V2 -> 25.9 | AA2: 2 | AB2: =+W2+X2+Y2-Z2-AA2 -> 23.9
A3: 807329 | B3: AVIKO ORIGINAL 20X450G | C3: 76.75 | G3: 13.25 | H3: =+C3+D3+E3-F3-G3 -> 63.5 | M3: =+H3+I3+J3-K3-L3 -> 63.5 | Q3: 2 | R3: =+M3+N3+O3-P3-Q3 -> 61.5 | W3: =+R3+S3+T3-U3-V3 -> 61.5 | AB3: =+W3+X3+Y3-Z3-AA3 -> 61.5
A4: 805411 | B4: PAPAS FRITAS ZIGZAG 12/750GRS | C4: 28.67 | E4: 60 | G4: 25 | H4: =+C4+D4+E4-F4-G4 -> 63.67 | I4: 4.33 | J4: 10 | L4: 68 | M4: =+H4+I4+J4-K4-L4 -> 10 | O4: 90 | Q4: 90 | R4: =+M4+N4+O4-P4-Q4 -> 10 | T4: 25 | V4: 0.08 | W4: =+R4+S4+T4-U4-V4 -> 34.92 | AB4: =+W4+X4+Y4-Z4-AA4 -> 34.92
A5: 807679 | B5: AVIKO SPICY WEDGES 20X500G | C5: 76.75 | E5: 80 | G5: 88 | H5: =+C5+D5+E5-F5-G5 -> 68.75 | J5: 24 | L5: 92.25 | M5: =+H5+I5+J5-K5-L5 -> 0.5 | O5: 110 | Q5: 92 | R5: =+M5+N5+O5-P5-Q5 -> 18.5 | T5: 64 | V5: 82.05 | W5: =+R5+S5+T5-U5-V5 -> 0.45 | Y5: 130 | AA5: 70 | AB5: =+W5+X5+Y5-Z5-AA5 -> 60.45
A6: 260612 | B6: CASTEL STRAIGHT CUT FRIES 4X2500g | C6: 33.5 | E6: 132 | G6: 108 | H6: =+C6+D6+E6-F6-G6 -> 57.5 | I6: 5 | J6: 0.25 | L6: 62.25 | M6: =+H6+I6+J6-K6-L6 -> 0.5 | R6: =+M6+N6+O6-P6-Q6 -> 0.5 | W6: =+R6+S6+T6-U6-V6 -> 0.5 | AB6: =+W6+X6+Y6-Z6-AA6 -> 0.5
A7: 802142 | B7: AVIKO STRAIGHT CUT 3/8 4x2500g | C7: 47 | G7: 46.75 | H7: =+C7+D7+E7-F7-G7 -> 0.25 | M7: =+H7+I7+J7-K7-L7 -> 0.25 | R7: =+M7+N7+O7-P7-Q7 -> 0.25 | W7: =+R7+S7+T7-U7-V7 -> 0.25 | AB7: =+W7+X7+Y7-Z7-AA7 -> 0.25
A8: 806982 | B8: AVIKO BREADED ONION RINGS 6x1000g | C8: 54.5 | G8: 42.33 | H8: =+C8+D8+E8-F8-G8 -> 12.17 | J8: 86 | L8: 39.33 | M8: =+H8+I8+J8-K8-L8 -> 58.84 | O8: 50 | Q8: 7 | R8: =+M8+N8+O8-P8-Q8 -> 101.84 | V8: 7.17 | W8: =+R8+S8+T8-U8-V8 -> 94.67 | AA8: 2 | AB8: =+W8+X8+Y8-Z8-AA8 -> 92.67
A9: 806685 | B9: AVIKO H PREM.CRUNCH SHOESTRING 7MM 4X2270G | C9: 1.5 | H9: =+C9+D9+E9-F9-G9 -> 1.5 | M9: =+H9+I9+J9-K9-L9 -> 1.5 | R9: =+M9+N9+O9-P9-Q9 -> 1.5 | V9: 1 | W9: =+R9+S9+T9-U9-V9 -> 0.5 | AB9: =+W9+X9+Y9-Z9-AA9 -> 0.5
A10: 804104 | B10: HASHBROWN TRIANG | C10: 2.25 | H10: =+C10+D10+E10-F10-G10 -> 2.25 | M10: =+H10+I10+J10-K10-L10 -> 2.25 | R10: =+M10+N10+O10-P10-Q10 -> 2.25 | V10: 2 | W10: =+R10+S10+T10-U10-V10 -> 0.25 | AB10: =+W10+X10+Y10-Z10-AA10 -> 0.25
A11: 806686 | B11: AVIKO H PREM CRUNCH 9.5 mm 3/8 4x2270g | C11: 13.5 | G11: 13.5 | H11: =+C11+D11+E11-F11-G11 -> 0 | M11: =+H11+I11+J11-K11-L11 -> 0 | R11: =+M11+N11+O11-P11-Q11 -> 0 | W11: =+R11+S11+T11-U11-V11 -> 0 | AB11: =+W11+X11+Y11-Z11-AA11 -> 0
B12: AROS SUSTITUTO | H12: =+C12+D12+E12-F12-G12 -> 0 | J12: 70 | L12: 1 | M12: =+H12+I12+J12-K12-L12 -> 69 | P12: 61 | Q12: 8 | R12: =+M12+N12+O12-P12-Q12 -> 0 | W12: =+R12+S12+T12-U12-V12 -> 0 | AB12: =+W12+X12+Y12-Z12-AA12 -> 0
A13: 01KFS02 | B13: PAPA ON DULADA SUSTITUTO | H13: =+C13+D13+E13-F13-G13 -> 0 | J13: 85 | L13: 77 | M13: =+H13+I13+J13-K13-L13 -> 8 | Q13: 8 | R13: =+M13+N13+O13-P13-Q13 -> 0 | W13: =+R13+S13+T13-U13-V13 -> 0 | AB13: =+W13+X13+Y13-Z13-AA13 -> 0
A14: 01KFS03 | B14: PAPA 1/4 NATURAL SUSTITUTO | H14: =+C14+D14+E14-F14-G14 -> 0 | J14: 50 | L14: 34 | M14: =+H14+I14+J14-K14-L14 -> 16 | Q14: 16 | R14: =+M14+N14+O14-P14-Q14 -> 0 | W14: =+R14+S14+T14-U14-V14 -> 0 | AB14: =+W14+X14+Y14-Z14-AA14 -> 0
A15: 01RCA01 | B15: PAPA CHIPPERBEC | H15: =+C15+D15+E15-F15-G15 -> 0 | M15: =+H15+I15+J15-K15-L15 -> 0 | N15: 52 | Q15: 29 | R15: =+M15+N15+O15-P15-Q15 -> 23 | V15: 20 | W15: =+R15+S15+T15-U15-V15 -> 3 | AA15: 3 | AB15: =+W15+X15+Y15-Z15-AA15 -> 0
A16: 01RCA02 | B16: PAPA RECTA 3/8 SUSTITUTO | H16: =+C16+D16+E16-F16-G16 -> 0 | M16: =+H16+I16+J16-K16-L16 -> 0 | N16: 99.94 | Q16: 50.33 | R16: =+M16+N16+O16-P16-Q16 -> 49.61 | V16: 38 | W16: =+R16+S16+T16-U16-V16 -> 11.61 | AA16: 11 | AB16: =+W16+X16+Y16-Z16-AA16 -> 0.61
H17: =+C17+D17+E17-F17-G17 -> 0 | M17: =+H17+I17+J17-K17-L17 -> 0 | R17: =+M17+N17+O17-P17-Q17 -> 0 | W17: =+R17+S17+T17-U17-V17 -> 0 | AB17: =+W17+X17+Y17-Z17-AA17 -> 0
C18: =+SUM(C2:C17) -> 542.42 | D18: =+SUM(D2:D17) -> 0 | E18: =+SUM(E2:E17) -> 272 | F18: =+SUM(F2:F17) -> 0 | G18: =+SUM(G2:G17) -> 435.83 | H18: =+SUM(H2:H17) -> 378.59 | I18: =+SUM(I2:I17) -> 9.33 | J18: =+SUM(J2:J17) -> 325.25 | ... AB18: =+SUM(AB2:AB17) -> 275.55
A19: CÓDIGO | B19: DESCRIPCIÓN | C19: INV DICIEMBRE 2025 | D19: COMPRAS | E19: Entradas | F19: Salidas | G19: VENTAS | H19: INV ENERO 2026 | I19: COMPRAS | J19: Entradas | K19: Salidas | L19: VENTAS | M19: INV FEB 2026 | N19: COMPRAS | O19: Entradas | P19: Salidas | Q19: VENTAS | R19: INV MARZO 2026 | S19: COMPRAS | T19: Entradas | U19: Salidas | V19: VENTAS | W19: INV ABRIL 2026 | X19: COMPRAS | Y19: Entradas | Z19: Salidas | AA19: VENTAS | AB19: INV MAYO 2026
A20: 105632 | B20: 10 MM NATURAL | C20: 0 | H20: =+C20+D20+E20-F20-G20 -> 0 | M20: =+H20+I20+J20-K20-L20 -> 0 | R20: =+M20+N20+O20-P20-Q20 -> 0 | W20: =+R20+S20+T20-U20-V20 -> 0 | AB20: =+W20+X20+Y20-Z20-AA20 -> 0
A21: 102341 | B21: 10 MM CON COBERTURA | C21: 250.5 | E21: 578 | G21: 695.25 | H21: =+C21+D21+E21-F21-G21 -> 133.25 | I21: 5.5 | J21: 1.75 | L21: 138.5 | M21: =+H21+I21+J21-K21-L21 -> 2 | O21: 150 | Q21: 150 | R21: =+M21+N21+O21-P21-Q21 -> 2 | T21: 545 | V21: 503 | W21: =+R21+S21+T21-U21-V21 -> 44 | Y21: 30 | AA21: 25 | AB21: =+W21+X21+Y21-Z21-AA21 -> 49
A22: 102310 | B22: 7 MM CON COBERTURA | C22: 39.25 | G22: 14 | H22: =+C22+D22+E22-F22-G22 -> 25.25 | I22: 3 | J22: 1 | L22: 28.25 | M22: =+H22+I22+J22-K22-L22 -> 1 | O22: 70 | Q22: 36 | R22: =+M22+N22+O22-P22-Q22 -> 35 | T22: 65 | V22: 27.3 | W22: =+R22+S22+T22-U22-V22 -> 72.7 | Y22: 10 | AA22: 16 | AB22: =+W22+X22+Y22-Z22-AA22 -> 66.7
A23: 102211 | B23: 7 MM NATURAL | C23: 169.75 | E23: 41 | G23: 178.75 | H23: =+C23+D23+E23-F23-G23 -> 32 | L23: 31 | M23: =+H23+I23+J23-K23-L23 -> 1 | O23: 87 | Q23: 77 | R23: =+M23+N23+O23-P23-Q23 -> 11 | T23: 120 | V23: 117 | W23: =+R23+S23+T23-U23-V23 -> 14 | Y23: 90 | AA23: 64 | AB23: =+W23+X23+Y23-Z23-AA23 -> 40
A24: 104215 | B24: 10 MM CON COBERTURA Y CASCARA | C24: 217.25 | G24: 68 | H24: =+C24+D24+E24-F24-G24 -> 149.25 | L24: 130 | M24: 21.25 | Q24: 21 | R24: =+M24+N24+O24-P24-Q24 -> 0.25 | T24: 285 | V24: 191.5 | W24: =+R24+S24+T24-U24-V24 -> 93.75 | AA24: 25 | AB24: =+W24+X24+Y24-Z24-AA24 -> 68.75
A25: 114054 | B25: GAJOS SAZONADOS | C25: 34.5 | E25: 100 | G25: 79 | H25: =+C25+D25+E25-F25-G25 -> 55.5 | I25: 12 | L25: 66.5 | M25: =+H25+I25+J25-K25-L25 -> 1 | O25: 108 | Q25: 82 | R25: =+M25+N25+O25-P25-Q25 -> 27 | T25: 50 | V25: 66.55 | W25: =+R25+S25+T25-U25-V25 -> 10.45 | Y25: 50 | AA25: 39 | AB25: =+W25+X25+Y25-Z25-AA25 -> 21.45
A26: 102419 | B26: ONDULADA | C26: 132 | G26: 128.5 | H26: =+C26+D26+E26-F26-G26 -> 3.5 | L26: 3 | M26: =+H26+I26+J26-K26-L26 -> 0.5 | O26: 130 | Q26: 38 | R26: =+M26+N26+O26-P26-Q26 -> 92.5 | V26: 66.25 | W26: =+R26+S26+T26-U26-V26 -> 26.25 | Y26: 40 | AA26: 38 | AB26: =+W26+X26+Y26-Z26-AA26 -> 28.25
A27: 102013 | B27: 10 MM NATURAL | C27: 12.25 | E27: 238.5 | G27: 217.25 | H27: =+C27+D27+E27-F27-G27 -> 33.5 | I27: 7 | J27: 299 | L27: 205.77 | M27: =+H27+I27+J27-K27-L27 -> 133.73 | O27: 1 | Q27: 128.25 | R27: =+M27+N27+O27-P27-Q27 -> 6.48 | T27: 360 | V27: 259.25 | W27: =+R27+S27+T27-U27-V27 -> 107.23 | AA27: 38 | AB27: =+W27+X27+Y27-Z27-AA27 -> 69.23
H28: =+C28+D28+E28-F28-G28 -> 0 | M28: =+H28+I28+J28-K28-L28 -> 0 | R28: =+M28+N28+O28-P28-Q28 -> 0 | W28: =+R28+S28+T28-U28-V28 -> 0 | AB28: =+W28+X28+Y28-Z28-AA28 -> 0
H29: =+C29+D29+E29-F29-G29 -> 0 | M29: =+H29+I29+J29-K29-L29 -> 0 | R29: =+M29+N29+O29-P29-Q29 -> 0 | W29: =+R29+S29+T29-U29-V29 -> 0 | AB29: =+W29+X29+Y29-Z29-AA29 -> 0
H30: =+C30+D30+E30-F30-G30 -> 0 | M30: =+H30+I30+J30-K30-L30 -> 0 | R30: =+M30+N30+O30-P30-Q30 -> 0 | W30: =+R30+S30+T30-U30-V30 -> 0 | AB30: =+W30+X30+Y30-Z30-AA30 -> 0
C31: =+SUM(C20:C30) -> 855.5 | D31: =+SUM(D20:D30) -> 0 | E31: =+SUM(E20:E30) -> 957.5 | F31: =+SUM(F20:F30) -> 0 | G31: =+SUM(G20:G30) -> 1380.75 | H31: =+SUM(H20:H30) -> 432.25 | I31: =+SUM(I20:I30) -> 27.5 | J31: =+SUM(J20:J30) -> 301.75 | ... AB31: =+SUM(AB20:AB30) -> 343.38
A32: CÓDIGO | B32: DESCRIPCIÓN | C32: INV DICIEMBRE 2025 | D32: COMPRAS | E32: Entradas | F32: Salidas | G32: VENTAS | H32: INV ENERO 2026 | I32: COMPRAS | J32: Entradas | K32: Salidas | L32: VENTAS | M32: INV FEB 2026 | N32: COMPRAS | O32: Entradas | P32: Salidas | Q32: VENTAS | R32: INV MARZO 2026 | S32: COMPRAS | T32: Entradas | U32: Salidas | V32: VENTAS | W32: INV ABRIL 2026 | X32: COMPRAS | Y32: Entradas | Z32: Salidas | AA32: VENTAS | AB32: INV MAYO 2026
A33: 505015 | B33: 10 MM NATURAL-KAIDA | C33: 198 | E33: 480 | G33: 508 | H33: =+C33+D33+E33-F33-G33 -> 170 | J33: 440 | L33: 299.33 | M33: 311.5 | O33: 2308.5 | Q33: 567.5 | R33: =+M33+N33+O33-P33-Q33 -> 2052.5 | S33: 20 | T33: 362 | V33: 1087.19 | W33: =+R33+S33+T33-U33-V33 -> 1347.31 | AA33: 580 | AB33: =+W33+X33+Y33-Z33-AA33 -> 767.31
C34: =+SUM(C23:C33) -> 1619.25 | D34: =+SUM(D23:D33) -> 0 | E34: =+SUM(E23:E33) -> 1817 | F34: =+SUM(F23:F33) -> 0 | G34: =+G33 -> 508 | H34: =+H33 -> 170 | I34: =+SUM(I23:I33) -> 46.5 | J34: =+SUM(J23:J33) -> 1040.75 | K34: =+SUM(K23:K33) -> 0 | L34: =+L33 -> 299.33 | M34: =+M33 -> 311.5 | N34: =+SUM(N23:N33) -> 0 | O34: =+SUM(O23:O33) -> 3180.5 | P34: =+SUM(P23:P33) -> 0 | Q34: =+Q33 -> 567.5 | R34: =+R33 -> 2052.5 | S34: =+SUM(S23:S33) -> 20 | T34: =+SUM(T23:T33) -> 2602 | U34: =+SUM(U23:U33) -> 0 | V34: =+V33 -> 1087.19 | W34: =+W33 -> 1347.31 | X34: =+SUM(X23:X33) -> 0 | Y34: =+SUM(Y23:Y33) -> 400 | Z34: =+SUM(Z23:Z33) -> 0 | AA34: =+AA33+AA18 -> 668 | AB34: =+AB33 -> 767.31
C35: =+C34+C31+C18 -> 3017.17 | D35: =+D34+D31+D18 -> 0 | E35: =+E34+E31+E18 -> 3046.5 | F35: =+F34+F31+F18 -> 0 | G35: =+G34+G31+G18 -> 2324.58 | H35: =+H34+H31+H18 -> 980.84 | I35: =+I34+I31+I18 -> 83.33 | J35: =+J34+J31+J18 -> 1667.75 | ... AB35: =+AB34+AB31+AB18 -> 1386.24
C36: =+C35/65 -> 46.418 | G36: ESPACIOS | H36: =+H35/65 -> 15.089846 | L36: ESPACIOS | M36: =+M35/65 -> 11.297231 | Q36: ESPACIOS | R36: =+R35/65 -> 38.548923 | V36: ESPACIOS | W36: =+W35/65 -> 29.988308 | AA36: ESPACIOS | AB36: =+AB35/65 -> 21.326769

Sheet BAJO CERO
A1: CÓDIGO | B1: DESCRIPCIÓN | C1: INV DICIEMBRE 2025 | D1: COMPRAS | E1: Entradas | F1: Salidas | G1: VENTAS | H1: INV ENERO 2026 | I1: COMPRAS | J1: Entradas | K1: Salidas | L1: VENTAS | M1: INV FEB 2026 | N1: COMPRAS | O1: Entradas | P1: Salidas | Q1: VENTAS | R1: INV MARZO 2026 | S1: COMPRAS | T1: Entradas | U1: Salidas | V1: VENTAS | W1: INV ABRIL 2026 | X1: COMPRAS | Y1: Entradas | Z1: Salidas | AA1: VENTAS | AB1: INV MAYO 2026
A2: 807769 | B2: PAPAS FRITAS CORTE REG 10 X 1000G | C2: 892 | H2: =+C2+D2+E2-F2-G2 -> 892 | M2: =+H2+I2+J2-K2-L2 -> 892 | R2: =+M2+N2+O2-P2-Q2 -> 892 | U2: 715 | W2: =+R2+S2+T2-U2-V2 -> 177 | AB2: =+W2+X2+Y2-Z2-AA2 -> 177
A3: 807329 | B3: AVIKO ORIGINAL 20X450G | C3: 270 | H3: =+C3+D3+E3-F3-G3 -> 270 | M3: =+H3+I3+J3-K3-L3 -> 270 | R3: =+M3+N3+O3-P3-Q3 -> 270 | U3: 125 | W3: =+R3+S3+T3-U3-V3 -> 145 | AB3: =+W3+X3+Y3-Z3-AA3 -> 145
A4: 805411 | B4: PAPAS FRITAS ZIGZAG 12/750GRS | C4: 60 | F4: 60 | H4: =+C4+D4+E4-F4-G4 -> 0 | M4: =+H4+I4+J4-K4-L4 -> 0 | R4: =+M4+N4+O4-P4-Q4 -> 0 | W4: =+R4+S4+T4-U4-V4 -> 0 | AB4: =+W4+X4+Y4-Z4-AA4 -> 0
A5: 807679 | B5: AVIKO SPICY WEDGES 20X500G | C5: 345 | F5: 152 | H5: =+C5+D5+E5-F5-G5 -> 193 | K5: 20 | L5: 0 | M5: =+H5+I5+J5-K5-L5 -> 173 | Q5: 110 | R5: =+M5+N5+O5-P5-Q5 -> 63 | U5: 60 | W5: =+R5+S5+T5-U5-V5 -> 3 | Z5: 3 | AB5: =+W5+X5+Y5-Z5-AA5 -> 0
A6: 260612 | B6: CASTEL STRAIGHT CUT FRIES 4X2500g | C6: 593 | F6: 510 | H6: =+C6+D6+E6-F6-G6 -> 83 | M6: =+H6+I6+J6-K6-L6 -> 83 | R6: =+M6+N6+O6-P6-Q6 -> 83 | W6: =+R6+S6+T6-U6-V6 -> 83 | Z6: 83 | AB6: =+W6+X6+Y6-Z6-AA6 -> 0
A7: 802142 | B7: AVIKO STRAIGHT CUT 3/8 4x2500g | C7: 0 | H7: =+C7+D7+E7-F7-G7 -> 0 | M7: =+H7+I7+J7-K7-L7 -> 0 | R7: =+M7+N7+O7-P7-Q7 -> 0 | W7: =+R7+S7+T7-U7-V7 -> 0 | AB7: =+W7+X7+Y7-Z7-AA7 -> 0
A8: 806982 | B8: AVIKO BREADED ONION RINGS 6x1000g | C8: 173 | H8: =+C8+D8+E8-F8-G8 -> 173 | M8: =+H8+I8+J8-K8-L8 -> 173 | R8: =+M8+N8+O8-P8-Q8 -> 173 | W8: =+R8+S8+T8-U8-V8 -> 173 | AB8: =+W8+X8+Y8-Z8-AA8 -> 173
A9: 806685 | B9: AVIKO H PREM.CRUNCH SHOESTRING 7MM 4X2270G | H9: =+C9+D9+E9-F9-G9 -> 0 | M9: =+H9+I9+J9-K9-L9 -> 0 | R9: =+M9+N9+O9-P9-Q9 -> 0 | W9: =+R9+S9+T9-U9-V9 -> 0 | AB9: =+W9+X9+Y9-Z9-AA9 -> 0
A10: 804104 | B10: HASHBROWN TRIANG | H10: =+C10+D10+E10-F10-G10 -> 0 | M10: =+H10+I10+J10-K10-L10 -> 0 | R10: =+M10+N10+O10-P10-Q10 -> 0 | W10: =+R10+S10+T10-U10-V10 -> 0 | AB10: =+W10+X10+Y10-Z10-AA10 -> 0
A11: 806686 | B11: AVIKO H PREM CRUNCH 9.5 mm 3/8 4x2270g | H11: =+C11+D11+E11-F11-G11 -> 0 | M11: =+H11+I11+J11-K11-L11 -> 0 | R11: =+M11+N11+O11-P11-Q11 -> 0 | W11: =+R11+S11+T11-U11-V11 -> 0 | AB11: =+W11+X11+Y11-Z11-AA11 -> 0
H12: =+C12+D12+E12-F12-G12 -> 0 | M12: =+H12+I12+J12-K12-L12 -> 0 | R12: =+M12+N12+O12-P12-Q12 -> 0 | W12: =+R12+S12+T12-U12-V12 -> 0 | AB12: =+W12+X12+Y12-Z12-AA12 -> 0
H13: =+C13+D13+E13-F13-G13 -> 0 | M13: =+H13+I13+J13-K13-L13 -> 0 | R13: =+M13+N13+O13-P13-Q13 -> 0 | W13: =+R13+S13+T13-U13-V13 -> 0 | AB13: =+W13+X13+Y13-Z13-AA13 -> 0
H14: =+C14+D14+E14-F14-G14 -> 0 | M14: =+H14+I14+J14-K14-L14 -> 0 | R14: =+M14+N14+O14-P14-Q14 -> 0 | W14: =+R14+S14+T14-U14-V14 -> 0 | AB14: =+W14+X14+Y14-Z14-AA14 -> 0
H15: =+C15+D15+E15-F15-G15 -> 0 | M15: =+H15+I15+J15-K15-L15 -> 0 | R15: =+M15+N15+O15-P15-Q15 -> 0 | W15: =+R15+S15+T15-U15-V15 -> 0 | AB15: =+W15+X15+Y15-Z15-AA15 -> 0
H16: =+C16+D16+E16-F16-G16 -> 0 | M16: =+H16+I16+J16-K16-L16 -> 0 | R16: =+M16+N16+O16-P16-Q16 -> 0 | W16: =+R16+S16+T16-U16-V16 -> 0 | AB16: =+W16+X16+Y16-Z16-AA16 -> 0
H17: =+C17+D17+E17-F17-G17 -> 0 | M17: =+H17+I17+J17-K17-L17 -> 0 | R17: =+M17+N17+O17-P17-Q17 -> 0 | W17: =+R17+S17+T17-U17-V17 -> 0 | AB17: =+W17+X17+Y17-Z17-AA17 -> 0
C18: =+SUM(C2:C17) -> 2333 | D18: =+SUM(D2:D17) -> 0 | E18: =+SUM(E2:E17) -> 0 | F18: =+SUM(F2:F17) -> 722 | G18: =+SUM(G2:G17) -> 0 | H18: =+SUM(H2:H17) -> 1611 | I18: =+SUM(I2:I17) -> 0 | J18: =+SUM(J2:J17) -> 0 | ... AB18: =+SUM(AB2:AB17) -> 495
